Workbook

Sheet Cover Sheet
B2: Validation Assessment Outline
B4: Assessment Data
B5: SBU | D5: Site Name | F5: Site Type | H5: Assessment Year | J5: Assessment Day
B6: BSAPIC | F6: Tire mfg.
B8: Assessor Name
G9: Safety assessor
G10: DP assessor
G11: Safety assessor
B15: Results of Previous Validation Assessment | H15: Date
B16: SMA Score | D16: Leadership | F16: Teammates | H16: Organization | J16: System
B19: Working Injury Data (Only Direct Employee)
B20: Year | F20: =IF($H$6="","",$H$6-3) -> 2022 | H20: =IF($H$6="","",$H$6-2) -> 2023 | J20: =IF($H$6="","",$H$6-1) -> 2024
B21: The number of total injury case (D+X1+X2+Y+N1)
B22: The number of fatality/serious injury case (D+X1+X2)
B23: Total Working Hour
B24: TIR* | F24: =IF(F23="","",F21/F23*1000000) -> 0.65156396 | H24: =IF(H23="","",H21/H23*1000000) -> 0.71273158 | J24: =IF(J23="","",J21/J23*1000000) -> 0.75060705
B25: SIR* | F25: =IF(F23="","",F22/F23*1000000) -> 0 | H25: =IF(H23="","",H22/H23*1000000) -> 0 | J25: =IF(J23="","",J22/J23*1000000) -> 0
B26: *These scores are calculated based on Global KPI's calculate rules.

Sheet Leadership Checklist
C1: Level | D1: Criteria 基準 | E1: Element エレメント | G1: Question 質問 | H1: Interview/Check インタビュー/確認 | U1: Interview インタビュー | V1: On-Site Observation 現場確認 | W1: Documents(example) 文書確認（例） | X1: Judgement Criteria 判断基準 | Y1: Judgement 判断 | Z1: Reason 判断理由
H2: Who? | I2: Plant Mgr. 工場長 | J2: Prod. GM 製造部長 | K2: Prod. Mgr. 製造課長 | L2: Foreperson 主任 | M2: Supervisor 職長 | N2: Teammate 技能員 | O2: Maintenance Manager 保全課長 | P2: Maintenance Foreman/Supervisor 保全主任/職長 | Q2: Maintenance Staff 保全員 | R2: Safety mgr. 安全担当課長 | S2: D.P. Manager 防災担当課長 | T2: Others その他 | U2: Content
B3: Ad-hoc | C3: 1 | D3: Site leadership can demonstrate general knowledge of their legal obligations in OH&S and DP management and how to fulfil these. 管理者は労働安全衛生および防災管理における法的義務とその履行方法に関する全般の知識を示すことができる。 | E3: Support 支援 | F3: 1 | G3: In general, does site leadership understand the legal OH&S and DP requirements & how these obligations are fulfilled? 管理者は、自身の安全衛生および防災に関する法的義務を理解しているか？ | H3: Plant manager 工場長 | I3: レ | U3: In general, how are the site's legal requirements identified and fulfilled? 法令要求は、どのように特定され、順守されていますか？ | X3: Plant manager can provide an overview of the legal requirements regarding OH&S and DP management and explain how these requirements are met and kept up to date. 工場長は労働安全衛生および防災管理に関する法的要件の概要を説明し、その要件に適合する方法、および内容が更新されていることを説明ができる。
C4: 1 | D4: Applicable site-specific OH&S regulations have been identified and current safety procedures and processes have been evaluated to ensure they are compliant with local regulation. SBU requirements. 労働安全衛生規則が制定されており、現行の安全手順・実施事項はローカル法規に準拠するよう評価されている。 | E4: Prioritization 優先付け | F4: 2 | G4: Have applicable site-specific OH&S regulations been identified, and site-specific safety procedures been implemented that they are compliant with local regulation and SBU standards? 安全衛生法令が特定されているか？また、安全手順が法令に準拠しているか確認するため、評価が実施されているか？ | H4: Safety Manager 安全担当課長 | R4: レ | U4: How have you ensured that all procedures applicable to your site have been developed & implemented, and meet local regulations & SBU standards? 安全手順・実施事項の法令順守を評価するため、どのような方法をとっていますか？ | X4: H&S manager can provide all of the applicable OH&S procedures for their specific site. 安全担当課長は、現場または事務所にて当該労働安全衛生規定の一覧を示すことができる。
C5: 1 | E5: Prioritization 優先付け | F5: 3 | H5: Safety Manager 安全担当課長 | R5: レ | X5: All safety procedures and processes have been issued and approved by an authorized company subject matter expert. すべての安全手順と安全プロセス（標準）は、権限を与えられた専門家によって承認・発行されている。
C6: 1 | D6: Review of records indicates that legally required OH&S management processes are implemented in a consistent manner. 記録を検証すると、法的要件の労働安全衛生の実施事項が一貫して実行されていることが確認できる。 | E6: Decisions 意思決定 | F6: 4 | G6: Are the OH&S management processes required by regulations executed on time? 法令で要求される労働安全衛生の実施事項が遅延なく、実行されているか？ | H6: Safety Manager 安全担当課長 | R6: レ | V6: Observe in >1 work area the implementation of OH&S processes required by regulation & SBU procedure (e.g. LOTO, Working at Heights) 法的要件の労働安全衛生の実施事項（LOTO、高所作業など）の実施状況について、3つ以上の作業地区を視察する。 | X6: All observed OH&S management processes have been implemented, and comply with SBU or external requirements(e.g. requirements required by regulation). 観察した労働安全衛生管理プロセスは、内部または外部要求（例:法令要求）に応じて遅延なく実行されている。
C7: 1 | D7: Interview statements from workers indicate that safety is considered a priority by leadership. 技能員との面談調査では、管理者のﾘｰﾀﾞｰｼｯﾌﾟによって、技能員は安全が最優先であることを理解している"ことが示される。 | E7: Support 支援 | F7: 5 | G7: Does Site Leadership consider safety a priority? 管理者は、安全を第一優先として、考慮しているか？ | H7: Teammate 技能員 | N7: レ | U7: How important is H&S at work? Does site leadership address safety at the morning assembly, roll-call, etc.? 職場において安全衛生は、どのように重要ですか？ 朝礼や点呼の際に、管理者は安全に関する話をしていますか？ | V7: Sample >3 work areas and talk with teammates about the importance of H&S on site. 3か所以上の作業地区を任意選択し、現場における安全衛生管理の重要性について技能員の話を聞く。 | X7: All teammates interviewed stated that H&S is considered a high priority on site. Leadership address safety at the morning assembly, roll call, etc. 面談した技能員の全員が、現場における安全衛生管理の優先度は高いと述べた。点呼・朝礼などの機会で安全に関する話を受けている。
C8: 1
B9: Reactive | C9: 2 | D9: Communication records and statements from workers indicate that leadership is involved in OH&S management when serious incidents(lost-time-injury, fire accident, etc.) occur. 技能員からの連絡記録および発言により、重大インシデント（休業災害・火災等）が発生した場合には管理者が労働安全衛生管理に参加対応していることが示される。 | E9: Support 支援 | F9: 6 | G9: Is Site Leadership involved in the OH&S management when a serious incident occurs? 管理者は、重大インシデント（休業災害・火災等）発生時、安全衛生管理に関与しているか？ | H9: Teammate 技能員 | N9: レ | U9: What normally happens when a serious incident (lost-time injury, fire accident, etc.) occurs, who does what in your view? 重大インシデント（休業災害・火災等）が発生すると、通常どのような事が起こりますか？あなたの見解では、誰が何をしますか？ | V9: Sample >3 work areas and talk with teammates about last serious incident (lost-time injury, fire accident, etc.) on their line/at site. 3か所以上の作業地区を任意選択し、ラインおよび現場にて最後に発生した重大インシデント（休業災害・火災等）について技能員の話を聞く。 | X9: All teammates stated that, at least, safety manager and site leadership representative (e.g. plant manager, department manager, line manager) was involved in the root cause analysis process when a serious incident(lost-time-injury, fire accident, etc.) occurred 重大インシデント発生時（休業災害・出火事故等）の原因分析プロセス(例:JS分析)には、技能員の全員が、少なくとも安全担当課長と現場の管理者（工場長、部門長、課長・主任・職長など）が参加対応していると述べた。
C10: 2 | D10: Safety performance (Safety KPIs) based on OH&S policy is monitored and tracked by site leadership. 安全成績・安全関連KPIは、安全衛生方針に基づき定められ、管理者によって監視され、追跡管理されている。 | E10: Prioritization 優先付け | F10: 7 | G10: Are safety results (KPIs) being monitored by leadership? 管理者は、安全結果をモニタリングしているか？ | H10: Plant manager 工場長 | I10: レ | V10: Review Line/Cell Boards (e.g. PDCA, Daily Meeting boards) for updated Safety KPI's ラインや作業地区のボード（PDCA、日次会議ボードなど）で、安全関連のKPIが更新されているかを検証する。 | W10: Review safety performance KPI's. 安全関連KPIの検証 | X10: Safety KPIs are tracked at plant, department and line level. 安全関連KPIは、工場、部門、ラインレベルで追跡管理されている。
C11: 2 | E11: Prioritization 優先付け | F11: 8 | H11: Plant manager 工場長 Production general manager 製造部長 | I11: レ | J11: レ | X11: To solve issues on H&S, site leadership follow safety KPIs, and give directions to review the safety program if necessary. 工場長は安全課題を解決するため、安全関連KPIをフォローし、必要に応じて安全施策の見直しを指示している。
C12: 2 | D12: Incident investigation records identify the root causes of incidents, categorizes them, and tracks the number of incidents by each category. (Human error, system error, Natural causes) *インシデント(災害・業務上疾病・ヒヤリ)記録により、インシデント原因を特定および分類し、分類ごとのインシデント件数を追跡管理している。（人的エラー、システムエラー、自然原因） | E12: Prioritization 優先付け | F12: 9 | G12: Are the root causes of incidents categorized and then tracked? 災害の原因は、分類（要因分析）され、追跡（フォロー）されているか？ | H12: Safety Manager 安全担当課長 | R12: レ | W12: Review incident investigation records and determine over a sample what common causes were. インシデント調査記録を検証し、任意選択したものの中から共通原因を判定する。 | X12: A review of 10 most recent incident records show that the cause has been determined and the countermeasures are followed-up by the termination. 直近10件の災害(労働災害・業務上疾病・ヒヤリ)記録を検証すると、分類ごとに原因が特定され、対策完了までフォローされている。
C13: 2 | D13: Safety Initiatives are being implemented to improve safety results, not operational performance results. 安全活動は生産性の改善ではなく、安全成績の改善を目的に実施されている。 | E13: Decisions 意思決定 | F13: 10 | G13: Are safety initiatives being implemented to improve safety or improve operational results? 安全性向上のために、リーダーシップが発揮されているか？ | H13: Safety Manager 安全担当課長 | R13: レ | U13: Review current safety related projects documentation, establishing their purpose and expected results. 現在の安全関連プロジェクトの書類、それらの目的、期待されるを結果は何か？ | W13: Project Charter; Technical Base Plan; Training documents. 取組み計画、技術基本計画（改造等）、教育関連資料。 | X13: Safety department plans to improve safety activities in the plant, and the plan is implemented. 安全担当部署では、工場全体の安全活動の改善業務が、計画され実行されている。
C14: 2
B15: Standardized | C15: 3 | D15: Site tour(s) indicate that line-management conducts floor observations to ensure adherence to safety rules, such as procedures, standards, etc. 現場を視察すると、手順、規格などの安全ルールが遵守されるように、製造課長・主任・職長が技能員を監督していることが示される。 | E15: Support 支援 | F15: 11 | G15: Does line management actively provide feedback to teammates and promote safety while touring their department/area? ライン管理者（課長・主任・職長）は、巡回時、積極的に技能員へフィードバックを行い、安全を推進しているか？ | H15: Managers 管理者 | K15: レ | L15: レ | M15: レ | O15: レ | P15: レ | V15: Sample >3 work areas and observe the extend to which the supervisor is actively supervising/coaching 3か所以上の作業地区を任意選択し、監督者（主任・職長）が積極的に監督および指示を実施している範囲を観察する。 | W15: Review any documented systems used by leadership that demonstrates that safety-focused safety tours, observations, coaching, etc. occur at regular/frequent intervals. The plan, progress, and records of these activities are confirmed. 管理者による安全巡回、現場確認、コーチングなどが定期/不定期で行われていることを示す、文書化されたシステムが整備されているか確認する。またこれらの計画・進捗および記録について確認する。 | X15: Line-management conducts floor observations(e.g. site tours) and provides feedback to teammates to ensure adherence to safety rules, such as procedures, standards, etc. 手順、規格などの安全ルールが遵守されるように、製造課長・主任・職長は巡回等の現場確認を行い、技能員へフィードバックを行っている。
C16: 3 | D16: Interview statements from teammates and line-managers indicate that they accept own responsibilities when it comes to safety management and the importance of their contributions. 技能員と製造課長の面談調査では、安全管理についてそれぞれが責任を有することを受け入れていることが示される。 | E16: Support 支援 | F16: 12 | G16: Do teammates know what their responsibilities are when it comes to Safety? 技能員は、安全に関する自身の責任を理解しているか？ | H16: Teammate 技能員 | N16: レ | U16: To what extend are you truly responsible for safety? And what does that mean to you? 実際にあなたが負っている安全に関する責任は何ですか？あなたにとってそれは、何を意味しますか？ | X16: A sample of 5 all stated that they acknowledge and accept their own responsibilities when it comes to safety management, and can explain what this means. 任意選択した5名の技能員の全員が、安全管理に関する義務があることを認識していることを示し、これを受け入れると述べた。
C17: 3 | D17: Leadership understand the importance of teammate involvement in safety management and can demonstrate clear actions regularly incorporated to help the site realize the positive results of those actions. 管理者は安全管理に従業員が参加することの重要性を理解し、活動結果を含めて、従業員の参加を実現するための明確な活動内容を示すことができる。 | E17: Decisions 意思決定 | F17: 13 | G17: Does leadership know how important teammate involvement in safety is, and involve teammates in safety activities? 管理者は、安全活動に従業員を参加させることの重要性を理解し、安全活動に参加させているか？ | H17: Managers 管理者 | I17: レ | J17: レ | K17: レ | O17: レ | R17: レ | U17: What are your expectations of teammates when it comes to the teammates' involvement in H&S management? あなたは、従業員に対し、安全衛生に関し、どのような期待を持っていますか？ | X17: A sample of 2 managers could both explain why teammate involvement in safety management is important and can provide examples of actions taken (e.g., assigned safety-related tasks/activities, participation in safety committee, etc.) to promote this and the results of those actions. 任意選択した2人の管理者が、安全管理への従業員の参加対応が重要である理由を説明し、その促進活動の例（例：安全活動への参加促進、業務指示、労働安全衛生委員会への出席等）および結果を示すことができる。
C18: 3 | D18: The H&S team, teammates and leadership meet at planned intervals to provide inputs to improve safety on site. 安全担当課、技能員、管理者は、現場の安全を改善する目的で、計画された間隔で会議を開催して意見を出している。 | E18: Decisions 意思決定 | F18: 14 | G18: Is there a H&S meeting with representation from teammates, leadership and H&S, and leadership give directions to solve issues? 技能員、管理者、安全衛生部署からの代表者で構成される安全衛生会議では、管理者、工場長による課題解決のための指示があるか？ | H18: Managers 管理者 | I18: レ | J18: レ | K18: レ | V18: Request attendance at such a meeting and observe what is being discussed. (If a validation assessment, and not able to attend such a meeting, ask for meeting minutes, attendance sheets, etc. that will support the judgement criteria.) そのような会議への出席許可を要請し、議論されている内容を観察する。 参加が難しい場合はそれら会議の議事録や出席表を確認し、判断の根拠とする。 | X18: During the attended meeting, the H&S team discussed the improvement of safety on site, and the meeting was well attended (>75% of members at every meeting). 出席した会議では、安全担当課が現場の安全性の向上について議論し、多数の参加者がいた（すべての会議で全メンバーの75%を超えるメンバーが参加）。
C19: 3 | D19: Leadership often emphasizes the importance of the Safety Rules and breaking the rules results in repercussions/consequences. 管理者は安全ルールの重要性を適時強調しており、規則違反に対しては対応や罰則が発生する。 | E19: Prioritization 優先付け | F19: 15 | G19: Are there repercussions/consequences for not following the Safety Rules and procedures? 安全ルール違反時の影響/結果（罰則・対応手順）はあるか？ | H19: Managers 管理者 | I19: レ | J19: レ | K19: レ | O19: レ | U19: Are there repercussions/consequences for teammates who break the safety rules and procedures? （安全）ルール違反をした従業員に対し、影響/結果（罰則）はありますか？ | W19: Review disciplinary procedure & documented examples of carrying out disciplinary action. 罰則手順書および罰則事例を検証する。 | X19: A sample of 3 managers all confirm that there are repercussions/consequences for teammates that do not follow the Safety Rules and Procedures. 任意選択した3人の管理者が、安全規則や手順を違反した従業員には罰則が発生することを示した。
C20: 3
B21: Proactive | C21: 4 | D21: Leadership keeps track of leading indicators to determine the results of investments made to improve health and safety at the facility 管理者は施設における安全衛生の向上に関する投資結果を示す主要指標を追跡管理している。 | E21: Prioritization 優先付け | F21: 16 | G21: Does Leadership use "Leading indicators" in their safety result tracking? 安全関連の指標について、先行指標（プロセスKPI）を使っているか？ | H21: Plant manager 工場長 | I21: レ | V21: Review site system for updating and communicated safety KPI's 安全関連のKPIが更新されコミュニケーションされていることを現場の仕組みで検証する | W21: Review safety performance KPI's to see if these are leading or lagging. Review Plant PDCA Board or other means of communicating safety results (KPI's) & updated status. 安全関連のKPIの項目が先行値か遅延値かを検証する。 工場のPDCAボードまたはその他の安全KPIや改善履歴について確認する。 | X21: Safety KPIs are tracked positively at plant, department and line level - using "Leading indicators"(e.g. Progress of RA, KPI for 3S activity, internal H&S audits findings, etc.) 安全関連KPIは「先行指標」（例：RA進捗、3S活動評価、内部監査の指摘事項等のプロセスKPI）を使用して、工場、部門、ラインのレベルで積極的に追跡管理されている。
C22: 4 | E22: Prioritization 優先付け | F22: 17 | H22: Plant manager 工場長 | I22: レ | X22: Site leadership follow not only lagging indicator(e.g. # of injuries), but also leading indicators, and give directions to review and/or improve safety programs/systems/activities if necessary. 工場長は、結果系KPI（災害件数等）だけでなく、先行指標(プロセスKPI）をフォローし、必要に応じて施策の見直し・改善を指示している。
C23: 4 | D23: There is a clear OH&S program consisting of multiple improvement/enhancement projects and allocated budgets to address defined OH&S priorities 明確な労働安全衛生プログラム（実施事項）があり、労働安全衛生について定義された優先事項について複数のプロジェクトがあり、予算が計上されている。 | E23: Decisions 意思決定 | F23: 18 | G23: Are there ongoing safety projects addressing safety issues? 安全の問題に対する、進行中の安全プロジェクト（安全に関する取り組み）があるか？ | H23: Safety Manager 安全担当課長 | R23: レ | U23: What are your top-3 risks and how are these being mitigated? あなたにとって、トップ3のリスクは何ですか？それらはどのように低減されていますか？ | X23: The H&S manager has identified the top 3 risks on site based on data and feedbacks from teammates, and can describe the measures or activity for improvement. 安全担当課長は、現場からの意見を踏まえた上で自職場の安全上の課題の優先度を認識しており、その対応方法や改善活動、計画とその進捗について説明できる。
C24: 4 | D24: Managers and/or the safety department are conduct pre- and post- assessments to determine the effectiveness of OH&S initiatives 労働安全衛生活動の有効性を確認するため、製造課長かつ/または安全担当課は安全衛生施策の開始前(導入前)と後に有効性の評価を行っている。 | E24: Prioritization 優先付け | F24: 19 | G24: Are pre and post assessments used to determine the effectiveness of OH&S initiatives? 安全衛生施策の有効性を確認するため、施策の導入前と後に有効性の評価を行っているか？ | H24: Safety Manager 安全担当課長 | R24: レ | W24: Sample 3 H&S projects and review the pre- and post assessment results 3件以上の安全衛生プロジェクトを任意選択し、事前評価と事後評価を検証する。 | X24: A sample of 3 OH&S projects all show that pre-assessments and post-assessments took place to monitor the effectiveness of new OH&S incentives. 任意選択した3件の安全衛生プロジェクトで、事前評価と事後評価が実施され、労働安全衛生インセンティブの有効性が確認できる。
C25: 4 | D25: Hazard reporting records indicate that teammates are actively involved in reporting and addressing hazards and risks in their daily jobs 危険状況報告記録では、日常業務における危険状況やリスクについて、技能員が積極的に報告および対応していることが示される。 | E25: Support 支援 | F25: 20 | G25: Do teammates report hazards (e.g., near misses, hidden dangers) regularly? 技能員は、定期的に危険源(例:ヒヤリ、不具合、潜在的危険源）を報告しているか？ | H25: Managers 管理者 | J25: レ | K25: レ | O25: レ | U25: What was the last hazard (e.g., hidden danger/near miss) reported from within your department and who reported it? 自部署において、直近で報告された危険源（潜在的危険源、ヒヤリ等）は、何ですか？誰がそれを報告しましたか？ | W25: Review how many hazards (e.g., hidden dangers, near misses) have been reported over a given time period. ある一定期間に報告された危険状況件数を検証する。 | X25: A review of the hazard reporting records for the last month show that at least 50% of hazards reported were from teammates on the factory floor. 前月の危険状況報告記録を検証すると、報告された危険状況の50%以上は技能員によるものであった。
C26: 4 | D26: Good safety behaviors of teammates are rewarded and recognized by managements. 技能員の優れた安全行動が管理者によって認知され、表彰されている | E26: Support 支援 | F26: 21 | G26: Are good safety behaviors of teammates rewarded and recognized by managements? 技能員の優れた安全行動が管理者によって認知され、表彰されているか? | H26: Management 管理者 | J26: レ | K26: レ | O26: レ | R26: レ | S26: レ | U26: How do you praise for safety behavior or performance? どのように優れた安全行動や成績を褒める/称賛していますか？ | X26: In a sample of 3 managers, all 3 can explain when rewards are provided for good safety behavior/performance, and give the examples. 任意選択した3人の管理者の全員が、優れた安全活動/成績を賞賛した事例を説明できる。
C27: 4
B28: Excellence | C28: 5 | D28: The safety team can demonstrate how industry(tire industry, rubber industry, manufacturing industry, etc.) *best-practice and scientifically proven best-practices are incorporated in their H&S program 安全担当課は、業界(タイヤ業界、ゴム業界、製造業界 等）の*ベストプラクティスおよび科学的に実証されたベストプラクティスが、安全衛生管理プログラム（実施事項）にどのように組み込まれているかを示すことができる。 | E28: Decisions 意思決定 | F28: 22 | G28: Have you gathered best practices on safety activity from GBS/SBU or external companies, and implement them in the plant? 社外またはGBS/SBUから展開された安全活動の好事例を自工場へ適用し、推進されているか？ | H28: Safety Manager 安全担当課長 | R28: レ | U28: How do you source best-practices and use these to benefit your H&S program? あなたは、どうやってベストプラクティスを収集していますか？ また、それらを事業所の安全衛生プログラムにどのように生かしていますか？ | X28: The H&S manager can give examples of industry best practices, where they came from and how they have been, or are being implemented on site. 安全担当課長は、業界のベストプラクティスの例、その出所、現場における導入方法を示すことができる。（今後実施予定のベストプラクティスを示すことも含める）
C29: 5 | D29: Management contributes to cross-plant and external H&S meetings during which H&S challenges and insights are shared 工場間会議および外部関係者の安全衛生会議では管理部門が貢献し、安全衛生に関する課題や考え方を共有している。 | E29: Support 支援 | F29: 23 | G29: Is there an external/cross-plant safety meeting? If so, does safety manager share H&S issues or best practices? 他工場、もしくは社外との安全会議があり、課題や好事例を共有しているか？ | H29: Safety Manager 安全担当課長 | R29: レ | V29: Request to attend such a meeting and review what is being discussed 会議への参加を依頼し（可能な場合）、議論の内容を確認する。 | W29: Review Meeting attendance Records and Minutes of Meetings shared. 会議出席記録、および議事録が共有されているかを検証する。 | X29: During the attended meeting, management contributed to discussions' in the cross-plant/external safety meeting. (E.g. Safety manager meeting in SBU, meeting in the local safety association, etc.) 出席した会議では、工場間会議および外部関係者の安全衛生会議(例:SBU内の安全課長会議、地域の安全協力会等)で管理者が貢献していた（安全衛生の改善に向けた困りごと・問題・課題提起・ベストプラクティス共有）
C30: 5 | D30: Site leadership has incorporated the OH&S program in their overall strategy and can explain how the conflicting objectives are prevented in that strategy 工場長は、総合戦略に労働安全衛生プログラム（実施事項）を取り入れて、戦略について相反する目標が発生するのを防止する方法を説明できる。 | E30: Support 支援 | F30: 24 | G30: Is there a long term OH&S strategy for the plant? 事業所の長期的な安全衛生計画はあるか？ | H30: Plant manager 工場長 | I30: レ | U30: What do you want to achieve in the area of H&S during the next 5 years and how is that resourced? 今後5年間で、安全衛生に関し、達成したことは何ですか？また、どのようにリソースを配分していますか？ | X30: The Plant Manager can describe his/her 5-year OH&S strategy and its goals, and how it will be implemented and the goals achieved. 工場長は、工場の労働安全衛生戦略、その目標、導入方法、達成済み目標を説明できる。
C31: 5 | D31: All interviewed workers confirm that safety is essential and that they feel comfortable stopping work whenever health or safety might be compromised 面談した技能員の全員から、安全が絶対不可欠であり、安全衛生が損なわれる可能性がある場合には躊躇なく作業を停止できるとの確認が得られる。 | E31: Support 支援 | F31: 25 | G31: Do teammates feel comfortable stopping work if they feel there is a risk of injury? 技能員は、災害リスクに直面した際、作業を停止することを、よいことだと感じているか？ | H31: Teammate 技能員 | N31: レ | U31: When health or safety might be compromised (e.g., you feel there is a risk of injury), what action do you take? Do you feel comfortable stopping or not starting work if you feel unsafe? 災害リスクに直面した際、どのような行動をとりますか？例えば、安全を確認できるまで作業を止めたり、開始せずに待機することをどのように感じますか？ | X31: A sample of 5 teammates all confirm that they feel safety is essential. They are comfortable stopping work when they feel their safety is compromised. 任意選択した5人の技能員が、安全が絶対不可欠であると述べた。安全が損なわれると思ったときには、躊躇なく作業を停止できる。
C32: 5 | D32: Leadership motivate teams to find the best safety practices and provide the resources to implement them. 管理者は、各チームが最善の安全対策を見つけるように推奨し、それを実施するためのリソースを提供している。 | E32: Prioritization 優先付け | F32: 26 | G32: Does leadership motivate teams to find and implement new best practices relevant to safety? 管理者は、各部署に対し、安全に関するベストプラクティスの収集や実行を推進しているか？ | H32: Managers 管理者 | J32: レ | K32: レ | O32: レ | R32: レ | S32: レ | U32: How do teams find the relevant best practices when it comes to safety? 各部署は、どのように安全衛生に関するベストプラクティスを収集していますか？ | X32: A sample of 3 managers, 1 can explain how they motivate teams to find best practices and how they allocate resources to implement them. 任意選択した3人の管理者のうち1人が、チームに対してベストプラクティスを模索する動機付けの方法、および導入するためのリソースを割り当てる方法を説明できる。
C33: 5
I34: =COUNTA(I3:I33) -> 9 | J34: =COUNTA(J3:J33) -> 7 | K34: =COUNTA(K3:K33) -> 7 | L34: =COUNTA(L3:L33) -> 1 | M34: =COUNTA(M3:M33) -> 1 | N34: =COUNTA(N3:N33) -> 4 | O34: =COUNTA(O3:O33) -> 6 | P34: =COUNTA(P3:P33) -> 1 | ... T34: =COUNTA(T3:T33) -> 0
D35: *Best practice includes information gathered from other plants or external companies. The items which were already standardized are excluded. (E.g. Engineering/recurrence prevention measures defined in the international standard or SBU standard)
D36: *ベストプラクティスには、他工場や他社から入手した好事例が含まれる。但し、既に標準化/規格化/要領化された内容を除く。（例：国際規格やSBU規格に規定されている設備対策・類災対策）
D37: *Incidents: lost-time-injury, fire accident, occupational disease, near-miss, recurrence prevention, etc.
D38: インシデントには、災害・出火事故・業務上疾病・ヒヤリ・類災 等を含む

Sheet Teammate Engagement Checklist
D1: Criteria 基準 | E1: Element エレメント | G1: Question 質問 | H1: Interview/Check インタビュー/確認 | U1: Interview インタビュー | V1: On-Site Observation 現場確認 | W1: Documents(example) 文書確認（例） | X1: Judgement Criteria 判断基準 | Y1: Judgement 判断 | Z1: Reason 判断理由 | AA1: Remark | AB1: F-up result (Jun) by APICTC
H2: Who? | I2: Plant Mgr. 工場長 | J2: Prod. GM 製造部長 | K2: Prod. Mgr. 製造課長 | L2: Foreperson 主任 | M2: Supervisor 職長 | N2: Teammate 技能員 | O2: Maintenance Manager 保全課長 | P2: Maintenance Foreman/Supervisor 保全主任/職長 | Q2: Maintenance Staff 保全員 | R2: Safety mgr. 安全担当課長 | S2: D.P. Manager 防災担当課長 | T2: Others その他 | U2: Content
B3: Ad-hoc | C3: 1 | D3: Teammates are made aware of general H&S risks during new hire training. 従業員は、新入社員研修により、一般的な安全衛生関連リスクを認識する。 | E3: Capability 能力 | F3: 1 | G3: Are general H&S risks explained during new-hire training to new teammates? 一般的な安全衛生リスクは、新入社員に周知されているか？ | H3: Teammate 技能員 | N3: レ | U3: What are the three greatest potential risks relevant to your work? あなたの仕事で3件の最重要リスクは何ですか。 | X3: A sample of 5 teammates recognize the H&S risks applicable in their areas and confirmed these were addressed in trainings. 任意選択した5人の技能員が、それぞれの地区に適用される安全衛生関連のリスクを認識しており、その内容が教育訓練で対応されていることが確認できる。
C4: 1 | D4: Teammates know that safety is considered more important than production. 従業員は、生産よりも安全を優先するという意識を持っている | E4: Action 行動 | F4: 2 | G4: Do you think that safety is considered more important than production? あなたは、生産よりも安全が優先されると考えますか？ | H4: Teammate 技能員 | N4: レ | U4: What would be considered a priority: complete the production plan or follow safety procedures? あなたにとって、生産計画の完了と安全手順の準拠ではどちらが優先事項ですか。 | V4: Conduct a site tour during peak and off hours to see if behavior is(un)safer Talk to teammates on the shop floor about the priority that safety has over production. ピーク時間帯とピーク以外の時間帯に現場を視察して、安全な行動を取っているかを確認する。 生産よりも安全が優先されることについて、製造現場の従業員と話をする。 | X4: Teammates know that safety is considered more important than operational results. 各従業員は、生産よりも安全が重要であることを知っている。
C5: 1 | D5: Management is aware of their responsibility in keeping teammates safe and enforcing safety rules and procedures. 管理者は、部下の安全を担保し、安全ルールを順守させる責任があることを認識している。 | E5: Capability 能力 | F5: 3 | G5: Is management aware of their personal impact on safety and do they leverage this to improve safety? 管理者は、安全に対する自身の影響力を認識し、安全向上に、活用しているか？ | H5: Management 管理者 | I5: レ | J5: レ | K5: レ | R5: レ | S5: レ | U5: How can/do you contribute to a safer execution (implementation) of safety procedures, projects, requirements? 安全な作業、要求事項を実行するために、あなたはどのような貢献ができますか。 | X5: In a sample of 3 managers, >1 stated that they do have an impact on teammate safety and they involve themselves with safety processes. 任意選択した3人の管理者のうち1人以上が、自身が従業員の安全に影響を及ぼし、安全プロセスに参加対応していると述べた。（例：巡回による安全状況確認、安全対策の優先順位付け、予算割り当て等）
C6: 1 | D6: Managers explain safety requirements based on regulation to teammate. 管理者は、部下に安全に関する法的要求事項を説明している。 | E6: Knowledge 知識 | F6: 4 | G6: Do managers explain safety requirements based on site-specific regulation to teammates? 管理者は、技能員に安全に関する法的要求事項を説明しているか？ | H6: Production Supervisor 製造主任 | L6: レ | U6: What requirement do you explain to operators on safety requirements based on regulation? 安全に関する法的要求に関して、あなたはどういった内容を技能員に説明していますか？ | W6: Review documented trainings, meetings, etc. where this information would be provided and explained. (e.g., minutes, education manual/record) これらの情報が提供される会議・打ち合わせもしくは教育の記録等を確認する。 | X6: In a sample of 3 managers, > 1 stated that they explain safety requirements based on site-specific regulation to teammates. 任意選択した3人の管理者のうち1人以上が、安全に関する法的要求事項を技能員へ説明している と述べた。
C7: 1
B8: Reactive | C8: 2 | D8: Teammates know how to report when incident(injury, occupational disease/illness, near-miss, hidden danger, fire) occurs, and incident reporting records and interview statements indicate that teammates report incidents. 技能員はインシデント(災害、業務上疾病、ニアミス・潜在的危険源、火災)が発生した際の報告方法を知っており、インシデント報告記録および面談報告書では従業員からインシデントが報告されている。 | E8: Capability 能力 | F8: 5 | G8: Do teammates know how to report incidents (injury, occupational disease/illness, near-miss/hidden danger)? 技能員はインシデント発生時の報告方法を知っていますか？ | H8: Teammate 技能員 | N8: レ | U8: How do you report an incident (injury, occupational disease/illness, near-miss/hidden danger)? Have you reported any recently, or are aware of any recently reported incidents? あなたが最近報告したインシデント（労働災害、疾病、ヒヤリ、潜在的危険源）は何ですか？ もしくは、最近他の技能員によって報告された事例は何かありますか？ | W8: Review incident records and cross-reference these with interview statements インシデント記録を検証し、面談調査と比較検討する。 | X8: A review of the incident records from the last month show that teammates have been reporting incidents (injury, occupational disease/illness, near-miss/hidden danger). In a sample of 5 teammates, at least 4 could explain how to report when an incident happen. 前月のインシデント記録を検証すると、インシデント（労働災害、疾病、ヒヤリ、潜在的危険源）を従業員が報告していることがわかる。任意選択した5人の技能員のうち4人以上がインシデント発生時の報告方法を知っている。
C9: 2 | D9: Teammates are involved in the actions implemented to prevent the reoccurrence of an incident (injury, occupational disease/illness, near-miss, hidden danger, fire) relevant to their daily job to ensure the appropriateness of such actions 各技能員は日常業務の中で事故再発防止対策に参加し、インシデント(災害、業務上疾病、ニアミス・潜在的危険源、火災)への適切な対策をとっている。 | E9: Action 行動 | F9: 6 | G9: Are teammates involved in preventing recurring incidents (injury, occupational disease/illness, near-miss/hidden danger)? 技能員は、再発防止（活動）に参加しているか？ | H9: Teammate 技能員 | N9: レ | U9: If you are involved in preventing incidents (injury, occupational disease/illness, near-miss/hidden danger), what do you do for recurrence prevention? もし、インシデント（労働災害、疾病、ヒヤリ、潜在的危険源）の発生にあなたが関与していた場合、あなたは再発防止のために何をしますか | X9: A sample of 5 teammates, at least 2 said they take part in the actions required to prevent incidents (injury, occupational disease/illness, near-miss/hidden danger) and provide feedback if these actions are not appropriate or useful. 任意選択した5人の技能員のうち2人以上が、インシデント（労働災害、疾病、ヒヤリ、潜在的危険源）防止のために必要な対応措置に参加し、その対応措置が不適切または有用でない場合にはフィードバックを提供すると述べた。
C10: 2 | D10: Statements from teammates indicate that they are informed of recent safety incidents relevant to them and the follow-up/actions taken to address them. 各技能員は、直近の安全関連インシデントの連絡を受けており、管理者から示されたフォローアップを認識している。 | E10: Knowledge 知識 | F10: 7 | G10: Are teammates informed of recent safety incidents (injury, occupational disease/illness, near-miss/hidden danger) in their areas and know what actions have been taken to address these? 技能員は、自職場の最近発生した災害とどのような対策が講じられたか連絡を受けているか？ | H10: Teammate 技能員 | N10: レ | U10: What incidents (injury, occupational disease/illness, near-miss/hidden danger) and the countermeasures were you informed of from management? 最近、連絡を受けたインシデント（労働災害、疾病、ヒヤリ、潜在的危険源）とその対策は何ですか？ | W10: Review incident (injury, occupational disease/illness, near-miss/hidden danger) records and cross-reference these with interview statements インシデント（労働災害、疾病、ヒヤリ、潜在的危険源）記録を検証し、面談調査と比較検討する。 | X10: A sample of 5 teammates can all state that they are informed of recent safety incidents (injury, occupational disease/illness, near-miss/hidden danger) in their areas and actions have been taken to address these. 任意選択した5人の技能員の全員が、自職場で発生した安全関連のインシデント（労働災害、疾病、ヒヤリ、潜在的危険源）と対策情報の連絡を受けた実績がある。
C11: 2
B12: Standardized | C12: 3 | D12: Teammates demonstrate a clear understanding of the H&S rules involved in their work and the relevance of these rules 各技能員は各自の業務に関する安全衛生規則を明確に理解し、その規則の関連性を理解していることが示される。 | E12: Capability 能力 | F12: 8 | G12: Do teammates know the department/job safety rules applicable to them? 技能員は、自部署/自作業に適用される安全ルールを理解しているか？ | H12: Teammate 技能員 | N12: レ | U12: What are the most important safety rules to you and why? あなたにとって最も重要な安全規則は何ですか、それはなぜですか。 | X12: A sample of 5 teammates can all explain the Department/Job Safety Rules in their work area and why they are important and relevant. 任意選択した5人の技能員の全員が、自身の作業地区における当該の部門規則や業務安全ルールについて説明でき、規則の重要性と関連性について理由を説明できる。
C13: 3 | D13: Teammates are trained at planned intervals of the different H&S rules aimed at ensuring their safety. 従業員は、自身の安全を確保するための各種安全衛生ルールを計画的な間隔で教育を受けている。 | E13: Knowledge 知識 | F13: 9 | G13: Are teammates regularly trained about the departmental/job safety rules applicable to them? 技能員は、自部署/自作業に適用される安全ルールについて、定期的に教育を受けているか？ | H13: Teammate 技能員 | N13: レ | U13: How can you provide feedback to management on safety rules? 安全ルールに関してどのように管理者へフィードバックしていますか？ | X13: A sample of 5 teammates all agreed that employees are regularly reminded and trained of the Department/Job Safety rules in their area. 任意選択した5人の技能員の全員が、自身の作業地区における当該の部門規則や業務安全ルールについて定期的に周知され、教育を受けていると回答した。
C14: 3 | D14: Site tour(s) indicates a structural adherence to the Department/Job Safety Rules applied to the sampled working areas. 任意選択された作業地区において、当該の部門規則や業務安全ルールが構造的に順守されていることが現場視察で示される。 | E14: Action 行動 | F14: 10 | G14: Are the Department/Job Safety rules being followed strictly? 自部署/自作業における安全ルールは、厳密に順守されているか？ | H14: Teammate 技能員 | N14: レ | V14: Observe work in three work areas to see if people work in accordance to safety rules 3か所の作業地区で作業を観察し、安全規則に従って作業が行われているか確認する。 | X14: When 3 different work areas were toured and observed, there was a strict adherence to the Department/Job safety rules of that area by the people working in that area. 3か所以上の作業地区を視察すると、その地区の作業者は各作業地区における当該の部門規則や業務安全ルールを厳守していた。 | AA14: Same as item 18 of organization checklist & item 76 of system checklist | AB14: Not yet
C15: 3
B16: Proactive | C16: 4 | D16: Interview statements indicate that teammates take trainings and understand the greatest potential H&S risks involved in their work and the controls applied to reduce these risks. 面談調査では、各技能員が教育を受け、自らの業務における安全衛生上の最重要リスクと管理対象項目を理解していることが示される。 | E16: Knowledge 知識 | F16: 11 | G16: Have teammates taken training on residual risks based on the work standard？ 技能員は、残留リスクについて作業標準ベースに教育を受けているか？ | H16: Teammate 技能員 | N16: レ | U16: Have you taken the training on the residual risks in your tasks? あなたは自作業の残留リスクについて教育を受けましたか？ | X16: A sample of 5 teammates could all state that they took the training on residual risks based on the work standard. 意選択した5人の技能員の全員が、残留リスクについて作業標準ベースに教育を受けていると述べた。
C17: 4 | E17: Capability 能力 | F17: 12 | G17: Do you understand the greatest potential risks, and how they are controlled? 技能員は、最も危険なリスクの内容及び管理方法を把握しているか？ | H17: Teammate 技能員 | N17: レ | U17: Which safety risks involved in your work/job are the most serious in your opinion and why? あなたの業務や役割において最も深刻だと思う安全リスクとその理由を教えてください。 | X17: A sample of 5 teammates could all describe and explain the greatest potential H&S risks in their work, and what controls they use or are in place to mitigate these risks. 任意選択した5人の技能員の全員が、各自の作業における最も深刻な安全衛生関連のリスクおよびリスク低減措置について説明できる。
C18: 4 | D18: Teammates propose improvements of H&S risks and risk mitigation measures at the creations or revisions of work standard, training material, etc. 作業標準や教育訓練資料等を作成、改訂する際、技能員が、安全リスクや低減策の改善提案をしている。 | E18: Capability 能力 | F18: 13 | G18: Have teammates proposed improvements of H&S risks and risk mitigation measures at the creations or revisions of work standards, training materials, etc. 作業標準や教育資料等を作成、改訂する際、安全リスクや低減策の改善提案をしていますか？ | H18: Production Supervisor 製造主任 | L18: レ | W18: Review work standards and training materials to see if revision history and content show inclusion of teammate's recommendations/suggestions. 作業標準や教育訓練資料を検証し、改訂履歴とその内容に技能員の意見が含まれているかを確認する。 | X18: Materials indicate that teammates propose improvements of H&S risks and risk mitigation measures at the creations or revisions of work standards, training materials, etc. 作業標準や教育資料等を作成、改訂する際、技能員が、安全リスクや低減策の改善提案をしていることが示される。
C19: 4 | D19: A sample of teammates participate in the risk assessment (RA) process, and they can demonstrate capability in performing a risk assessment on their work activities 任意選択した技能員が、自身の作業に関するリスクアセスメントに参加しており、リスクアセスメントを実施する能力があることを示すことができる。 | E19: Capability 能力 | F19: 14 | G19: Are some teammates capable of performing full risk assessments? 複数の技能員は、リスクアセスメントの全プロセス（危険源の同定から低減対策まで）を実行する能力があるか？ | H19: Teammate 技能員 | N19: レ | U19: Have you participated in RA process? If so, could you explain the RA process on your work place? 自職場の作業に関して、RAに参加したことがありますか？もしあれば、リスクアセスメントプロセスを説明してください。 | X19: In a sample of 5 teammates, at least two have participated RA process, and he/she could explain a full and accurate Risk Assessment. 任意選択した5人の技能員のうち2人以上が、リスクアセスメントに参加したことがあり、リスクアセスメントを完全かつ正確に実施できる。
C20: 4 | D20: Teammates proposed improvements to prevent incidents (injure, occupational disease/illness, near-miss/hidden danger) and received feedback from managements. 技能員は、インシデント（労働災害、疾病、ヒヤリ、潜在的危険源）に関する改善提案を行い、管理者からフィードバックを受けている。 | E20: Action 行動 | F20: 15 | G20: Have teammates proposed improvements for @reventation of incidents (injure/near-miss/hidden danger) and management has given feedback to them? 技能員から、インシデント（労働災害・ヒヤリ・潜在的危険源）に関する改善提案があり、管理者が対策実施内容をフィードバックしているか | H20: Management 管理者 | J20: レ | K20: レ | R20: レ | S20: レ | U20: How have you respond to proposals for improvement to prevent incidents (injury, occupational disease/illness, near-miss/hidden danger) from teammates? 技能員からのインシデント（労働災害、疾病、ヒヤリ、潜在的危険源）の改善提案に対して、どのように対応していますか？ | X20: Teammates proposed improvements on incidents (injury, occupational disease/illness, near-miss/hidden danger) prevention, and received feedback from managements. 技能員は、インシデント（災害、疾病、ヒヤリ・不具合に関する改善提案を行い、管理者からFBを受けていることが確認できる。
C21: 4 | D21: Review of action plans show that teammates have been involved in the design, implementation and evaluation of safety action plans. 活動計画を検証すると、安全対策計画の設計、導入、評価について、各技能員の参加対応があることが示される。 | E21: Action 行動 | F21: 16 | G21: Are teammates involved and consulted in safety action plans? 技能員は、安全実施計画（策定）に参加し、協議を行っているか？ | H21: Management 管理者 | J21: レ | K21: レ | R21: レ | W21: Review action plans or project planning to determine if these involve consultation steps with workers 活動計画またはプロジェクト計画を検証し、技能員との協議が行われているかを判断する。 | X21: A review of the safety action plans from the most recent safety projects show teammates were involved and consulted. 直近の安全プロジェクト（安全に関する取り組み）における安全関連の活動計画を検証すると、技能員の参加対応と協議があったことが示された。
C22: 4
B23: Excellent | C23: 5 | D23: H&S risks/measures of other departments have been shared at the safety meeting in your department. 自部署内の安全衛生会議等で、他部署での安全リスク/対策について共有されている | E23: Knowledge 知識 | F23: 17 | G23: Are there opportunities to share H&S risks/measures of other departments at the safety meeting in your department? 他部署での安全リスク/対策を共有する場があるか (自部署内の安全衛生会議などで) | H23: Teammate 技能員 | N23: レ | W23: Review the safety meeting material and minutes 会議資料や議事録を確認する。 | X23: H&S risks/measures of other departments have been shared at the safety meeting in your department. 自部署内の安全衛生会議等で、他部署での安全リスク/対策について共有されている.
C24: 5 | D24: Teammates are encouraged to talk with other teams and speak about H&S risks regularly to share best-practices and lessons-learned. 各従業員は、他のチームメンバー（他部署・他工程）と話し合うように奨励され、安全衛生関連のリスクについて定期的な話し合いを持ち、ベストプラクティスや教訓を共有している。 | E24: Capability 能力 | F24: 18 | G24: Do teammates know safety related information (H&S risk, recurrence prevention measures issued by GBS/SBU, etc.) shared among teams (department/areas) and plants? 部署間/工場間で共有された安全関連の情報（安全リスク、類災対策、GBS/SBUからの展開施策 等）を把握しているか？ | H24: Management 管理者 | J24: レ | K24: レ | R24: レ | S24: レ | U24: How is safety knowledge shared between teams and plants? 部署間と工場間で安全関連の知識をどのように共有していますか。 | X24: In a sample of 3 managers, 2 could explain how teams (departments/areas) share safety knowledge about H&S risks and risk mitigation with other teams and different sites. 任意選択した3人の管理者のうち2人が、安全衛生関連のリスクとリスク低減に関する安全関連情報を他のチームや別の現場とどのように共有するかを説明できた。
C25: 5 | D25: The site safety department communicates their best-practices in risk control with other plants to ensure cross-company learning and awareness. 現場の安全担当課は、リスク管理のベストプラクティスを他の工場にも伝達し、全社的な学習と意識向上を図っている。 | E25: Knowledge 知識 | F25: 19 | G25: Do you have opportunities to get *best practices from internal/external sources, and do you implement them in the plant? 社内外の*ベストプラクティス情報を入手する機会があり、自拠点への導入を行っているか？ | H25: Safety Manager 安全担当課長 | R25: レ | W25: Review what best-practices have been communicated and how well these were implemented どのようなベスト・プラクティスが伝達され、どのように実施されたかを検証する。 | X25: A review of the safety processes shows that H&S team has implemented best practices from other sites and these have yielded positive results. 安全関連プロセス(標準)を検証すると、安全衛生管理チームが他の現場のベストプラクティスを導入し、肯定的な結果を得たことを示している。
C26: 5 | D26: Interview statements and site tour(s) indicate that unsafe behavior is perceived as unacceptable. It is that anyone acting unsafe will be corrected by their peers. 面談調査と現場見学で、不安全行動は容認不可と認識されていることが示される。不安全行動をすると、同僚から指摘される。 | E26: Action 行動 | F26: 20 | G26: Is unsafe behavior completely unacceptable on site? 事業所において、不安全行動は、例外なく、容認されていないか？ | H26: Teammate 技能員 | N26: レ | U26: What response would you expect from your colleague when you act unsafe? あなたが不安全行動をした場合、あなたの同僚はどのような反応をすると期待しますか。 | X26: A sample of 5 operators all stated that unsafe behavior is unacceptable and anyone acting unsafe will be corrected by their peers. 任意選択した5人の技能員の全員が、不安全行動は容認できないと述べ、不安全行動をとる者は同僚によって指摘されると述べた。
C27: 5
I28: =COUNTA(I3:I27) -> 1 | J28: =COUNTA(J3:J27) -> 4 | K28: =COUNTA(K3:K27) -> 4 | L28: =COUNTA(L3:L27) -> 2 | M28: =COUNTA(M3:M27) -> 0 | N28: =COUNTA(N3:N27) -> 13 | O28: =COUNTA(O3:O27) -> 0 | P28: =COUNTA(P3:P27) -> 0 | ... T28: =COUNTA(T3:T27) -> 0
D29: *Best practice includes information gathered from other plants or external companies. The items which were already standardized are excluded. (E.g. Engineering/recurrence prevention measures defined in the international standard or SBU standard)
D30: *ベストプラクティスには、他工場や他社から入手した好事例が含まれる。但し、既に標準化/規格化/要領化された内容を除く。（例：国際規格やSBU規格に規定されている設備対策・類災対策）
D31: *Incidents: lost-time-injury, fire accident, occupational disease, near-miss, recurrence prevention, etc.
D32: インシデントには、災害・出火事故・業務上疾病・ヒヤリ・類災 等を含む

Sheet Organization Checklist
D1: Criteria 基準 | E1: Element エレメント | G1: Question 質問 | H1: Interview/Check インタビュー/確認 | U1: Interview インタビュー | V1: On-Site Observation 現場確認 | W1: Documents(example) 文書確認（例） | X1: Judgement Criteria 判断基準 | Y1: Judgement 判断 | Z1: Reason 判断理由 | AA1: Remark | AB1: F-up result (Jun) by APICTC
H2: Who? | I2: Plant Manager 工場長 | J2: Production GM 製造部長 | K2: Production Manager 製造課長 | L2: Production Foreperson 主任 | M2: Production Supervisor 職長 | N2: Teammate 技能員 | O2: Maintenance Manager 保全課長 | P2: Maintenance Foreman/Supervisor 保全主任・職長 | Q2: Maintenance Staff 保全員 | R2: Safety mgr. 安全担当課長 | S2: D.P. Manager 防災担当課長 | T2: Others その他 | U2: Content
B3: Ad-hoc | C3: 1 | D3: Compliance evaluation and training records indicate that H&S training required by regulation (including safety/disaster emergency drills) has been provided to all teammates. 法令遵守状況評価と教育訓練記録から、法令に定められた安全衛生関連の教育訓練（安全・防災の緊急時対応訓練を含む）が全従業員に実施されていることが示される。 | E3: Information 情報 | F3: 1 | G3: Is the legally required H&S training (including safety/disaster emergency drills) given to all teammates? 法令で要求される安全衛生教育（安全・防災の緊急時対応訓練を含む）は、全ての従業員に実施されているか？ | H3: Safety Manager 安全担当課長 | R3: レ | W3: Review local requirements and training records (including safety/disaster emergency drills)to see if a sample of teammates are properly trained. 現地のコンプライアンス記録と教育訓練記録を検証して、任意選択した従業員に適切な教育訓練が提供されているかを確認する。 | X3: A review of the most recent training records show that a sample of 10 randomly selected teammates (regardless of rank) have all received the H&S training (including safety/disaster emergency drills) required by regulation. 直近の教育訓練記録を検証すると、無作為に選択した10人（職位無視）の全員が、法的に必要な安全衛生関連の訓練（安全・防災の緊急時対応訓練を含む）を受けていた。
C4: 1 | D4: Incidents (injury, occupational disease/illness, near-miss, hidden danger) defects are communicated to management and they are encouraged to follow-up. インシデント（労働災害、疾病、ヒヤリ、潜在的危険源）情報は、フォローアップのための推奨事項とともに管理者に伝達されている。 | E4: Communication コミュニケーション | F4: 2 | G4: Do teammates communicate injuries/near-misses/defects to managers, and does management follow-up on them? 管理者は、災害/ヒヤリ/不具合情報を技能員から入手し、フォローアップしているか？ | H4: Management 管理者 | J4: レ | K4: レ | R4: レ | S4: レ | U4: How are you informed of incidents (injuries, near-misses, hidden dangers, etc.,) and what sort of follow-up process do you follow? 自身のプロセスに重要な安全衛生管理リスク（労働災害、ヒヤリ、潜在的危険源）について、どのように情報を得ていますか。 | X4: A sample of 3 managers can all show items recently reported to them and the examples of follow-ups associated with the reports. 任意選択した3人の管理者の全員が、最近報告された内容とそのフォローアップ活動の例を示すことができる。
C5: 1 | D5: Teammates are made aware of the function of safety controls through passive communication channels such as notice boards and e-mails 掲示板やメールなどの受動的な連絡手段を通じて、安全管理の機能を従業員に周知している。 | E5: Communication コミュニケーション | F5: 3 | G5: Is passive communication, such as notification boards and e-mails, being used to convey safety information? 安全管理を周知するための受動的なコミュニケーション（例：掲示物・メールによる展開）は、使用されているか？ | H5: Safety Manager 安全担当課長 | R5: レ | U5: Is passive communication, such as notification boards and e-mails, being used to convey safety information to Teammates? 従業員に自身の安全管理項目を理解させるために、どのような手段を用いていますか。（例：掲示板、メールによる展開） | X5: The H&S manager informs teammates of up to date safety information by notice boards, via emails, or other relevant passive communication system on site. 安全担当課長は、安全関連の最新情報について、掲示板やメール送信等を用いて展開している。
C6: 1 | D6: Roles and responsibilities of safety activities set out, and they are understood by those required to fulfil them 安全活動の役割と責任が明確になっており、その責任を負う者が理解している。 | E6: Participation 参加 | F6: 4 | G6: Does management have defined roles and responsibilities for safety activities? 管理者は、自部署の安全活動の担当者の役割を明確にし、任命しているか？ | H6: Management 管理者 | I6: レ | J6: レ | K6: レ | R6: レ | S6: レ | U6: How do you ensure H&S roles and responsibilities are effectively allocated? 安全衛生管理の役割と責任が効果的に割り当てられていることをどのように確認していますか。 | X6: A sample of 3 managers could all explain their roles and responsibilities on safety activity in their department/section/area. 任意選択した3人の管理者の全員が、自部署の安全活動担当者について役割・活動内容を説明できる。
C7: 1
B8: Reactive | C8: 2 | D8: Incident(injury, fire occupational disease/illness, near-miss, hidden danger)investigations are conducted by qualified people and the identified causes are included in the risk tracking as to-be-controlled risks インシデント（労働災害、疾病、ヒヤリおよび潜在的危険源、類災報告）調査は知識・能力を有した者(安全担当、SE等）が実施し、特定された原因は管理すべきリスクとしてリスク登録簿に登録されている。 | E8: Information 情報 | F8: 5 | G8: Are incident investigations carried out by qualified people? 災害調査は、知識・能力をもった者が実施しているか？ | H8: Safety Manager 安全担当課長 | R8: レ | W8: Review the risk and incident records to identify their correspondence リスク記録とインシデント記録を検証して、相互に対応しているかを確認する。 | X8: A review of the incident records show the last 5 incidents were investigated by qualified people, and the causes were identified and added to the risk tracking. インシデント記録（労働災害、疾病、ヒヤリ、潜在的危険源）を検証すると、直近5件のインシデントが知識・能力を有した者によって調査され、原因を特定し、リスク登録簿に追加されていた。
C9: 2 | D9: H and S activities are observed/reviewed by management for results and activities have the opportunity for continuous improvement about the lagging performance indication (e.g. # of injury, frequency rate, etc.) . 安全衛生活動は管理者によるレビューによって結果系指標（例：災害件数、災害度数率等）の継続的改善を行う機会を与えられている。 | E9: Communication コミュニケーション | F9: 6 | G9: Does management know what safety initiatives are active on site and how they are performing, and impact on the site's lagging indicators? 管理者は、現場でどの安全の取り組みが有効で、どのように実行されているか、把握しているか？ | H9: Management 管理者 | I9: レ | J9: レ | K9: レ | R9: レ | S9: レ | U9: What current safety initiatives are active, and have they resulted in improving lagging indicator performance? 直近の安全衛生管理の取り組みは、どのような成果がありましたか。 また、進捗が遅れている取り組みに対してどのような対応を行いましたか。 | X9: A sample of 3 managers could all describe the most recent H&S initiatives to improve H&S management on site, and knew if the results were positive or negative. 任意選択した3人の管理者の全員が、現場の安全衛生管理改善を目的とした直近の安全衛生の取り組みを説明でき、結果の良し悪しを知っていた。
C10: 2 | D10: Management and the H&S team collaborate to prevent reoccurrence of accidents by addressing the causation of these accidents 管理者と安全担当課が協力して、事故の因果関係を調査し、再発防止に取り組んでいる。 | E10: Participation 参加 | F10: 7 | G10: Is there collaboration between H&S and management to address recurring incidents, with focus on causation? 再発防止において、安全機能と管理者は連携しているか？ | H10: Management 管理者 | I10: レ | J10: レ | K10: レ | R10: レ | S10: レ | W10: Review incident records to determine how management and H&S collaborate, and how well causes are identified and mitigated. リスク記録とインシデント記録を検証して、管理職と安全管理部門がどのように協力して原因へ対応しているかを確認する。 | X10: A review of the incident(injury, occupational disease/illness, near-miss, hidden danger)records from the last month show evidence that the H&S team and management collaborate, and identify the causes and address the countermeasures to prevent the recurrence of incidents. 前月のインシデント（労働災害、疾病、ヒヤリ、潜在的危険源）記録を検証すると、安全担当課と管理者が協力してインシデント（労働災害、疾病、ヒヤリ、潜在的危険源）の再発防止に向け、原因を特定し、対応が実施されていることが示される。
C11: 2 | D11: Safety training for newcomers includes reference to *frequent incidents(injury, occupational disease/illness, near-miss, hidden danger)and severe risks to ensure teammates understand these and corresponding controls. *Frequent incident means that same incident is re-occurring 入社時の安全教育には頻発インシデント（労働災害、疾病、ヒヤリ、潜在的危険源）や重大リスクが含まれており、その内容と当該管理項目を従業員が確実に理解できるようにしている。 | E11: Participation 参加 | F11: 8 | G11: Do safety training sessions for newcomers reference relevant frequent incidents and risks? 安全教育において、よく発生する関連災害やリスクが参照されているか？ | H11: Safety Manager 安全担当課長 | R11: レ | V11: Request to attend such training to determine if relevant incidents are addressed インシデントに対して対応されていることを確認するため、当該教育訓練への参加許可を要請する。 | X11: During the attended training session, the safety training referred to frequent incidents and severe risks, and the controls in place to prevent reoccurrence of them. 出席した安全教育訓練では、頻繁に発生するインシデント（労働災害、疾病、ヒヤリ、潜在的危険源）と重大リスク、その管理事項などを対象としていた。
C12: 2
B13: Standardized | C13: 3 | D13: The H&S team, teammates and their supervisors evaluate the design, implementation and effectiveness of current safety rules in order to optimize these 安全担当課、技能員、監督者は、現在の安全ルールの内容、導入状況、有効性を評価し、最適化を図っている。 | E13: Information 情報 | F13: 9 | G13: Are current Safety rule's effectiveness being evaluated by a team? 現在の安全管理ルールの有効性が、各部署で評価されているか？ | H13: Safety Manager 安全担当課長 | R13: レ | U13: How is the effectiveness of H&S rules evaluated? Are Teammates, Supervisors and H&S involved with the evaluations? 安全ルールの有効性をどのように評価していますか。 またそれらの評価に技能員は関与していますか？ | X13: The H&S manager could describe how the H&S rule's effectiveness is evaluated, who is involved in the evaluation process and how the processes are improved after evaluation. Further, the evaluation includes input by Teammates & Supervisors, along with H&S. 安全担当課長は、安全ルールの有効性の評価方法、評価担当者の氏名、評価後のプロセス改善方法を説明できる。またそれらの評価に安全担当課や技能員の意見が反映されている。
C14: 3 | D14: Interview statements indicate that teammates know who to report to in order to fulfil their H&S/DP relevant responsibilities 面談調査で、従業員は各自の安全衛生や防災に関連する義務事項を果たすための報告すべき相手を知っていることが示される。 | E14: Communication コミュニケーション | F14: 10 | G14: Do teammates know who to speak to about H&S/DP and how the reporting structure works? 技能員は、安全衛生や防災について誰に報告すべきか、また、報告の仕組みを理解しているか？ | H14: Teammate 技能員 | N14: レ | U14: When safety/disaster issue X would occur, who would you logically talk to? 安全・防災上の課題Xが発生した場合、必然的に対話する相手は誰ですか。 | X14: A sample of 5 teammates could all explain who they would report specific safety/disaster issues to. 任意選択した5名の従業員の全員が、安全・防災関連の特定の課題を誰に報告するかについて説明できた。
C15: 3 | D15: Specific safety trainings are repeated at a standard interval to ensure the competence of people working on site. There are mandatory training requirements for each activity. 現場で働く人々の能力を確保するため、特定の安全教育訓練が標準化された間隔で繰り返されている。各作業について必須の教育訓練要件がある。 | E15: Information 情報 | F15: 11 | G15: Is there a skill matrix table for teammates that identifies the training requirements/needs for each job, including training dates? 能力要件表を定めており、各技能員の教育実施日や要件等について記載しているか？ | H15: Production Foreman 製造主任 | L15: レ | W15: Review the skill matrix table for teammates and training dates. 能力要件表と教育の実施日を確認する。 | X15: There are mandatory training requirements for each activity. Specific safety trainings are repeated at a standard interval to ensure the competence of people working on site and ensure compliance with local and SBU requirements. 必須の教育訓練要件が定められており、安全教育訓練が標準化された間隔で繰り返し実施されていることを確認できた。 | AB15: Not yet
C16: 3 | D16: Safety procedures are periodically reviewed to identify opportunities for improvement. This is often done by the H&S team and the line-managers involved in the specific safety processes. すべての安全プログラム(実施事項)は定期的に見直しがあり、改善できるようになっている。多くの場合、安全担当課と特定の安全プログラム(実施事項)に対応する製造課長がこの作業を実施する。 | E16: Participation 参加 | F16: 12 | G16: Are all safety programs reviewed periodically? 全ての安全プログラムは、年に1回、レビューされているか？ | H16: Safety Manager 安全担当課長 | R16: レ | V16: Request to attend such a review to determine if the involved parties reach good results. If unable to attend (e.g., such meeting doesn't occur while conducting the SMA (validation), then review any meeting notes or other documents that resulted from such meeting. 関係者が良好な結果を得ているかどうかを確認するため、検討会議への出席許可を要請する。 調査中にそれらの会議が開催されないなどして参加が困難な場合は、会議の議事録や出席表などを参照することで評価することとする。 | X16: During the attended safety review meeting, or review of meeting minutes if SMA Assessor is unable to attend such meeting, (H&S team and line leaders in attendance), improvement areas were discussed and action plans put in place. 出席した安全検討会議（安全担当課と課長・主任・職長らが出席）では、改善点を討議し、活動計画を策定していた。出席できない場合は、議事録でそれらの活動が行われていることが確認できた。
C17: 3 | D17: Forepersons/supervisors understand the system and scope of management of changes(4M changes) 4M変更管理の仕組み・対象について理解している。 | E17: Communication コミュニケーション | F17: 13 | G17: Is there a system on management of changes? 変更に関する管理の仕組みはありますか？ | H17: Supervisors 監督者 | L17: レ | M17: レ | U17: What is a contents of system and scope for management of change? 4M変更時のシステムとスコープは何ですか？ | X17: A sample of 3 supervisors all explained system and scope of management of change(4M changes). 任意選択した3人の監督者の全員が、４M変更管理の仕組み・対象について説明できた。 | AB17: Not yet
C18: 3
B19: Proactive | C19: 4 | D19: Prior to a change in process or equipment, are the risks associated with the change reviewed, evaluated and communicated with H&S team. 作業や設備の変更の前に、変更に関連したリスクは安全担当課とレビュー・評価を行っている。 | E19: Communication コミュニケーション | F19: 14 | G19: Do management and process owners communicate with H&S team about upcoming changes on site, along with any risks associated with the change? 管理者と監督者は、職場の予定された変更とそれに伴うリスクに関して、安全衛生担当課と話し合っていますか？ | H19: Supervisors 監督者 | L19: レ | M19: レ | U19: How and when do you involve the H&S team in discussions regarding planned changes in your process, along with any risks associated with the planned change? あなたはリスクの変化を伴う作業方法や工程の変更（4M変更）時に、安全担当課をいつ、どのようにそれらに関する議論に参加させていますか。 | X19: A sample of 3 supervisors all confirmed that they discuss with the H&S team the risks associated with upcoming changes to work processes. 任意選択した3人の監督者の全員が、作業工程の変更時、新規の作業が発生する際には、安全担当課とリスクと対応方法について討議したことを示した。
C20: 4 | D20: Safety instructions and trainings have been integrated into regular job-related training which is provided to teammates before they start the associated work. 安全に関する指示と教育訓練は通常の業務関連の教育訓練に統合されて、技能員が関連作業を開始する前に実施されている。 | E20: Information 情報 | F20: 15 | G20: Do work/job specific trainings highlight safety risks and processes associated with that work/job? 作業訓練において、関連する安全上のリスクや作業手順について、強調されているか？ | H20: Production Supervisor 製造主任 | L20: レ | W20: Review work/job specific training materials 作業訓練資料を確認する | X20: Safety instructions and safety training were included in the work specific training materials. 特定作業の教育訓練において、教育資料には、安全関連の指示事項と安全教育訓練が含まれていた。
C21: 4 | D21: Safety procedures and processes are reviewed at regular intervals by those involved, and revisions are made based upon relevant findings. 安全プロセス（要領等）は関係者によって定期的に見直しが行われ、当該指摘事項を含めることによって改善されている。 | E21: Participation 参加 | F21: 16 | G21: Are safety procedures and processes frequency reviewed and updated using findings from the review? 安全手順は、頻繁に見直され、見直し結果をもとに、改善されているか？ | H21: Safety Manager 安全担当課長 | R21: レ | U21: What was the feedback/follow-up you received from management on any incidents (injury, occupational disease/illness, near-miss, hidden danger) you reported? あなたがインシデント（労働災害、疾病、ヒヤリ、潜在的危険源）を報告をした場合、管理者からどのようなフィードバックやフォローアップがありましたか。 | W21: Review the document history of H&S procedures and standards 安全衛生関連の手順書と標準書の改訂記録を検証する。 | X21: A review of the document history from the last year showed where H&S procedures and safety processes had been evaluated and changed/updated by those involved as needed to address newly identified risks and controls. 前年以降の文書改訂履歴を検証すると、新たなリスクや課題について、必要とされる関係者によって、安全衛生管理手順と安全プロセスが変更または発展したことが示された。
C22: 4 | D22: Risk records indicate that hazards/injury/near-miss/defects reported are used by management to take actions and the result of these actions are communicated with the reporter. リスク記録では、危険状況/災害/ヒヤリ/不具合情報が報告された場合には管理部門がその情報を使用し、対応結果が報告者に通知されていることが示される。 | E22: Communication コミュニケーション | F22: 17 | G22: Does management take action when a hazard/injury/near-miss/defects is reported, and communicate these action to the reporter? 管理者は、危険源/災害/ヒヤリ/不具合情報が報告された際、対処しているか？また、対処結果を報告書へフィードバックしているか？ | H22: Teammate 技能員 | N22: レ | U22: What measures did the management take in response to the information you or your colleague reported? And what means was this feedback provided to you? あなたもしくは同僚が報告した不具合情報に対して、管理者はどのような対応を実施しましたか。またそれをどのような手段であなたにフィードバックされましたか。 | X22: A sample of 5 teammates all stated that management had taken specific actions to address hazards they reported, and these actions have been communicated to them 任意選択した5人の技能員の全員が、自分たちが報告した危険状況に対して、管理者が特定の対応措置を実施し、その件について自分たちに報告があったと述べた。
C23: 4
B24: Excellence | C24: 5 | D24: Teammates and managers are mindful of the need for safety, not only for themselves but also for others. Teammates and managers have a genuine concern for one another; a CFT approach is used to review and address safety issues. 技能員と管理者は自分だけでなく他者の安全にも配慮することを意識している。安全ルールの順守やリスクの改善活動は小集団・CFTで実施されている。 | E24: Participation 参加 | F24: 18 | G24: Do teammates and managers have a genuine concern for themselves and one another? When there are safety relates issues, is a CFT approach taken to resolving them? 技能員や管理者は、自身や同僚をお互いに危険に曝さぬように意識しているか？ 安全に関する問題が発生した場合、CFTによる解決への方策が図られているか？ | H24: Teammate 技能員 | N24: レ | V24: Assess 3 work areas to see if workers show consideration towards their safety and others 3か所以上の作業区域を評価し、技能員が自身および他者の安全に配慮しているか確認する。 | W24: Near Miss Reports Behavior Observation System (BOS) execution by leaders. Incident Reports and Investigation ニアミス報告書。 指導者（課長・主任・職長）による安全行動観察(モニタリング）の実施状況。 インシデントレポート（報告書）と調査状況。 | X24: A tour of 3 work areas showed that teammates are actively conscious of their safety and the safety of others. Activities for improvement were conducted in CFT being conscious of safety for not only their selves, but also teammates. 3か所以上の作業区域を視察すると、社員が自身の安全と他者の安全を積極的に意識していることが示された。改善活動は、自分だけでなく他者の安全を意識し、小集団・CFTで実施されている | AA24: Same as item 76 of system check sheet & item 10 of teammage engagement sheet
C25: 5 | D25: Line managers are actively engaging with *external parties to obtain knowledge on how they have controlled their risks and exchange knowledge on safety processes regularly. *External includes other company, SBU, other plants in BS 製造課長は*外部の関係者と積極的に連携し、リスク管理方法に関する情報を入手し、安全プロセスについて情報交換を定期的に行っている。 *外部には他社、SBU、他工場を含む | E25: Participation 参加 | F25: 19 | G25: Do line managers engage with external parties about safety? 管理者（工場長・部長・課長）は、安全の外部団体に参加しているか？ | H25: Management 管理者 | I25: レ | J25: レ | K25: レ | R25: レ | S25: レ | U25: How do you keep yourself informed on safety relevant developments? Do you engage in exchange of safety information and best practices/benchmarking with others outside your site (e.g., other BS sites, other companies, etc.)? 安全関連の当該最新情報をどのように得ていますか。 安全に関するベストプラクティスやベンチマークを社外や他のBSの拠点と交換していますか。 | X25: With a sample of 3 managers, at least 1 said they voluntarily discussed safety with managers from other sites or *external parties to improve safety knowledge. *External includes other company, SBU, other plants in BS 任意選択した3人の管理者の1人以上が、安全関連の知識を向上するため、自発的に他の現場や*外部の管理者と安全について討議したと述べた。 *外部には他社、SBU、他工場を含む
C26: 5 | D26: Risks are assessed at the earliest possible planning stages of every team in the organization to avoid risks where they might materialize. 発生する可能性のあるリスクを回避するため、組織内の各チームができるだけ早い計画段階でリスクを評価している。 | E26: Information 情報 | F26: 20 | G26: Is risk assessment one of the first actions taken when planning new projects/work sessions? 新たなプロジェクト/作業の計画段階において、初期対応の1つとして、RAが実施されているか？ | H26: Management 管理者 | I26: レ | J26: レ | K26: レ | R26: レ | S26: レ | U26: What aspects do you consider when planning new/modified projects? 新規もしくは変更を伴うプロセスの計画作成時に、どのような点を考慮していますか。 | X26: With a sample of 3 managers, at least 2 said that Risk assessment is always done in the early planning stages for upcoming projects/work sessions. 任意選択した3人の管理者の2人以上が、新しいプロジェクトや作業の初期計画段階でリスク評価を常に実施していると述べた。 | AA26: Same as item 74 of system check sheet
C27: 5 | D27: For the improvement of safety management system of the plant, external party evaluate the system. 自工場の安全衛生マネジメント改善のため、社外の評価を受けている。 | E27: Communication コミュニケーション | F27: 21 | G27: Do you receive feedback from third party on effectiveness of safety management system 安全マネジメントシステムの有効性について、定期的に外部のフィードバックを受けていますか？ | H27: Safety Manager 安全担当課長 | R27: レ | U27: Do you use an external / third party to evaluate the effectiveness of the site's safety management system? 事業所の安全管理システムの有効性を評価するために、外部／第三者を利用していますか？ | X27: Regarding the safety management system in the plant, the H&S manager can explain evaluation results by third party, feedback, and the actions taken from these results. 安全担当全課長は、自工場のマネジメント改善のための第3者の評価、フィードバック、およびその対応を説明できる
C28: 5
I29: =COUNTA(I3:I28) -> 5 | J29: =COUNTA(J3:J28) -> 6 | K29: =COUNTA(K3:K28) -> 6 | L29: =COUNTA(L3:L28) -> 4 | M29: =COUNTA(M3:M28) -> 2 | N29: =COUNTA(N3:N28) -> 3 | R29: =COUNTA(R3:R28) -> 14
D30: *Incidents: lost-time-injury, fire accident, occupational disease, near-miss, recurrence prevention, etc.
D31: インシデントには、災害・出火事故・業務上疾病・ヒヤリ・類災 等を含む

Sheet System Checklist
D1: Criteria 基準 | E1: System システム | F1: Element エレメント | H1: Question 質問 | I1: Interview/Check インタビュー/確認 | V1: Interview インタビュー | W1: On-Site Observation 現場確認 | X1: Documents(example) 文書確認（例） | Y1: Judgement Criteria 判断基準 | Z1: Judgement 判断 | AA1: Reason 判断理由 | AB1: Remark | AC1: F-up result (Jun) by APICTC
I2: Who/What? | J2: Plant Manager 工場長 | K2: Production GM 製造部長 | L2: Production Manager 製造課長 | M2: Production Foreperson 製造主任 | N2: Production Supervisor 製造職長 | O2: Teammate 技能員 | P2: Maintenance Manager 保全課長 | Q2: Maintenance Foreperson/Supervisor 保全主任/職長 | R2: Maintenance Staff 保全員 | S2: Safety Manager 安全担当課長 | T2: D.P. Manager 防災担当課長 | U2: Others その他 | V2: Content
B3: Ad-hock | C3: 1 | D3: All teammates receive training on the safety mission statement, *high-risk activities and the regulation for training are known. 全従業員は、安全宣言、および高リスク作業について教育を受けている。また、教育の法令要求は理解されている。 *High-risk activity: Activity which are risk category III&IV. E.g. Work at height, heavy object handling, mobile equipment, caught by machine, tire inflation, etc. *高リスク作業：リスクカテゴリーIII&IVに該当するもの。例：高所作業、重量物、動力車、挟まれ・巻き込まれリスクのある作業、空気充填 等 | E3: Safety communication 安全コミュニケーション | F3: Design 設計 | G3: 1 | H3: Are the regulations concerning safety training known at the site? 事業所において、安全教育に関する法令要求は、把握されているか？ | I3: Safety Manager 安全担当課長 | S3: レ | V3: Are safety training programs established, planned, and implemented to meet legal regulations? 教育訓練は安全に関する法令要求を満たすように定められ、計画・実施されていますか？ | Y3: The regulations concerning safety training are known and followed. 安全教育に関する法令要求は、理解され、順守されている。
C4: 1 | D4: OH&S communication required by regulation is sent by management as per the communication procedure, through multiple communication channels with consideration to language barriers. 法令で要求される安全衛生コミュニケーションは、コミュニケーション手順に基づき、管理者により展開されている。また、複数のコミュニケーション様式により、言語の障壁に配慮している（表現を一般的にしている）。 | E4: Safety communication 安全コミュニケーション | F4: Integration 関連付け | G4: 2 | H4: Does the safety manager send out the OH&S communications required by regulations to relevant departments as per the communication procedure and appropriate methods/language? 安全担当課長は、コミュニケーション手順に従い、法令で要求される安全衛生に関わる情報を関係部署に適切な手段/言語を用いて発信しているか？ | I4: Safety Manager 安全担当課長 | S4: レ | V4: What are the communication channels used for OH&S communication? What official languages are spoken at the site? 安全衛生に関する周知において、コミュニケーションのチャネル（手段・方法）は何ですか？ 事業所での公式な言語は何ですか？ | X4: Review communication records. Review communication channels available at the site. コミュニケーション記録を確認する。 事業所で利用できるコミュニケーションチャネル（手段）を確認する。 | Y4: There is no difference among the language used by teammate working in the plant and the language used in the communication record. (or Multiple forms of communication are used and language differences are accounted for.) 拠点で働いている人の使用言語とコミュニケーション記録の言語に齟齬がない。 (または、様々なコミュニケーションの様式がある際、言語の違いが考慮されている。)
C5: 1 | D5: Evidence indicates that the SBU injury and fire reporting process has been communicated to the relevant people on site. 労働災害・出火事故連絡の手順は、事業所の関係者に周知され、エビデンスがある。 | E5: Incident Management インシデント管理 | F5: Integration 関連付け | G5: 3 | H5: Has the Injury and Fire and Near-miss Reporting Process been communicated to the correct person? 労働災害・出火事故、ヒヤリの連絡手順は、周知されているか？ | I5: Safety Manager 安全担当課長 | S5: レ | V5: Who is involved in injury and fire reporting and how is it ensured that they understand their role? 労働災害・出火事故連絡において、対応者は誰ですか？また、彼らに自身の役割をどのように理解させていますか？ | X5: Review Roles and Responsibility documentation for Injury and Fire Report 労働災害・出火事故連絡に関する役割と責任の文書を確認する。 | Y5: The respondent can explain what needs to be reported and by whom. 回答者は、報告すべき事項と報告者について説明できる。
C6: 1 | D6: Incidents (industrial accidents, fire accidents, near misses/hidden dangers reports and recurrence preventions) local procedure exists and teammates know how to report Near-Misses / Hidden Dangers. 自拠点において発生したインシデント（労働災害、出火事故、ヒヤリおよび潜在的危険源の報告、類災報告）標準があり、チームメートはそれらを報告する方法を把握している。 | E6: Incident Management インシデント管理 | F6: Integration 関連付け | G6: 4 | H6: Is the procedure for reporting to management Near-Misses / Hidden Dangers known by the employees? ヒヤリおよび潜在的危険源を上司に報告する手順を従業員は理解しているか？ | I6: Teammate 技能員 | O6: レ | V6: How would you report a Near-Miss or Hidden Danger? ヒヤリおよび潜在的危険源をどのように報告するか？ | W6: Talk to >3 Teammates to verify if they are aware of the procedure to report a Near-Miss or a Hidden Danger in their work site ３人の技能員と話し、彼らがヒヤリおよび潜在的危険源の報告手順を理解している。 | Y6: The respondent can explain the procedure to report a Near-Miss or Hidden Danger. 回答者は、ヒヤリ及び潜在的危険源についての報告手順を説明できる。
C7: 1 | D7: Changes are managed by an appointed MOC coordinator, a reviewer and change approver who evaluate the legal compliance of a proposed change structurally. 変更は、任命された変更管理起案者・審議者および法令順守評価を行う変更承認者により管理されている。 | E7: Management of Change 変更管理 | F7: Change & Emergency planning 変更管理 & 緊急事態準備 | G7: 5 | H7: Has an MOC Coordinator, an MOC reviewer and final approver been defined with clear roles an responsibilities defined? 変更管理における起案者・審議者・最終承認者は明確になっており、役割と責任が定義（明文化）されているか？ | I7: MOC coordinator 変更管理起案者 | U7: レ | V7: What are in your view are the responsibilities of MOC coordinator, MOC reviewer and final approver in the change management process? 変更管理において、変更の起案者、審議者、承認者の責任は、何だと認識していますか？ | X7: Review Roles and Responsibility documentation for MOC 変更管理に関する役割と責任の文書を確認する。 | Y7: An MOC Coordinator, an MOC reviewer and final approver been appointed. Clear roles and responsibilities are defined for each. 変更の起案者、審議者、承認者が任命されている。また、それぞれの役割・責任が定義されている。
C8: 1 | E8: Management of Change 変更管理 | F8: Change & Emergency planning 変更管理 & 緊急事態準備 | G8: 6 | H8: Are proposed changes evaluated in a structured manner that considers the legal compliance? 起案された変更案は、法令順守の確認を含む標準化された手順に従い、評価（審議）されているか？ | I8: MOC coordinator 変更管理起案者 | U8: レ | V8: What is the process that should be followed when a change occurs? 変更発生時、順守されるべき手順は何ですか？ | X8: Review process for MOC and examples of situations where MOC should have occurred. 変更管理の手順と変更の履歴を確認する。 | Y8: There is a defined process for MOC, that includes a section for legal compliance, and the process is being followed. 変更管理が規定された手順があり、法令確認のステップが含まれ、それらが順守されている。
C9: 1 | D9: People performing service and/or maintenance activities are aware of the LOTO standard and have been provided with locks and tags as required. LOTO実施者（サービス＆メンテナンス）は、LOTO標準を認識している。また、キーとタグは、要求に基づき配布されている。 | E9: LOTO Standard LOTO標準 | F9: Integration 関連付け | G9: 7 | H9: Have the required people been given locks and tags? キーとタグは、（LOTOの実行が）要求される人に配布されているか？ | I9: Safety Manager 安全担当課長 | S9: レ | V9: To whom have you distributed locks and tags for LOTO? どなたにLOTOキーとタグを渡していますか？ | W9: Identify on the shop floor if required service providers and maintenance resources have locks and tags 現場モニタリングにおいて、作業や保全で必要な技能員がキーとタグを持っているか。 | Y9: Locks have been allocated to all relevant factory floor teammates and management. (at minimum for those performing service and maintenance tasks where an exposure to unexpected energization could result in injury) キーは、全ての必要な技能員と管理者に配布されている。（最低限、LOTOせずに設備が稼働した場合に被災するリスクに曝される現場作業および保全作業の従事者）
C10: 1 | E10: LOTO Standard LOTO標準 | F10: Integration 関連付け | G10: 8 | H10: Are the required people educated in the LOTO standard? （LOTOの実行が）要求される人は、LOTO標準を教育されているか？ | I10: Production and Maintenance SV 製造職長 保全職長 | N10: レ | Q10: レ | V10: Who received LOTO training? And is the frequency of LOTO re-training established and followed? 誰がLOTO教育を受けていますか？ また再教育の頻度が定められ、それに基づいた教育を行っていますか？ | X10: Review if training materials and attendance indicate a transfer of required competence. 求められる能力が反映されているか、教育資料と出席状況を確認する。 | Y10: The LOTO standard has been shared with all relevant teammates and they have been trained on this at the appropriate time and frequency. LOTO標準は、全ての必要な技能員に周知され、教育が適切なタイミング・頻度で実施されている。
C11: 1 | D11: People on site demonstrate consistent knowledge of the Safety Rules. 事業所の従業員は、安全ルールに関する一貫した知識を示している。 | E11: Safety Rules 安全ルール | F11: Integration 関連付け | G11: 9 | H11: Do People on site know the safety rules that are required to be followed? 事業所の人たちは、順守が要求される安全ルールを知って（理解して）いますか？ | I11: Teammate 技能員 | O11: レ | V11: What are the site safety rules applicable to the site? 事業所で適用されている事業所の安全ルールは、何ですか？ | W11: Observe in >3 work areas if people demonstrate knowledge of safety rules 3つ以上の作業場の現場モニタリングにおいて、技能員は、安全ルールを理解し、作業しているか。 | Y11: More than three teammates shows understanding of the applicable All Bridgestone Safety Rules in their areas. 少なくとも3人の技能員は自職場に適用されるブリヂストン共通安全ルールを理解している。
C12: 1 | D12: Work at height requirements have been communicated and both managers and teammates are aware of Work at height training requirements . 高所作業の要求事項は、周知されている。管理者と作業者は、両者とも高所作業における教育の要求事項を認識している。 | E12: Work at Height 高所作業 | F12: Integration 関連付け | G12: 10 | H12: Have Work at height requirements been communicated to the necessary teammates? 高所作業の要求事項は、（要求事項の実行が）必要な作業者に周知されていますか？ | I12: Production Foreman 製造主任 | M12: レ | V12: What are the Work at height requirements applicable to this workplace? How was the communication about Work at height done across site? この職場で適用されている高所作業の要求事項は、何ですか？事業所で実施されている高所作業（のルール）について、どのように周知されていますか？ | X12: Review communication records to see if the Work at height requirements were communicated across site コミュニケーション記録を確認し、高所作業の要求事項が事業所全体に周知されているか、確認する。 | Y12: Production foreman could explain the work at height requirement and training and/or communication records shows that Work at height requirements have been communicated with teammates. 製造主任は高所作業における要求事項を説明することが出来るとともに、それを教育記録やコミュニケーション記録（テスト記録）等にて、高所作業の要求事項が周知している。
C13: 1 | E13: Work at Height 高所作業 | F13: Integration 関連付け | G13: 11 | H13: Can teammates say Work at height requirements(What must not be done & What must be done) of All Bridgestone safety rules? 技能員は、BS共通安全ルール”高所作業”の順守事項・禁止事項を言えるか | I13: Teammate 技能員 | O13: レ | V13: What are Work at height rules(What must not be done & What must be done) defined in the All Bridgestone safety rules? BS共通安全ルール”高所作業”の順守事項・禁止事項は何ですか？ | W13: Observe Work at height activities at the shop floor. 現場で高所作業をモニタリングする。 | Y13: More than three teammates is capable of answering All BS safety rules on Work at height operations. 少なくとも3人の技能員は高所作業における安全ルールを回答できる。
C14: 1 | D14: Rules governing the use of mobile equipment have been communicated and both managers and teammates are aware of the training requirements for mobile equipment. 動力車使用を管理するルールは、周知されている。管理者と作業者は、両者とも動力車における教育の要求事項を認識している。 | E14: Mobile Equipment 動力車 | F14: Integration 関連付け | G14: 12 | H14: Have you communicated with drivers about requirements on mobile equipment 動力車の運転に関する要求事項は必要な作業者に周知されていますか？ | I14: Production Supervisor 製造職長 | N14: レ | V14: What are the training requirements for mobile equipment? 動力車に要求される教育は何ですか？ | W14: Observe mobile equipment work at the shop floor and review training requirements with teammates 現場で動力車作業をモニタリングし、技能員に要求される訓練を確認する。 | X14: Review if training materials and attendance indicate a transfer of required competence. 求められる能力が反映されているか、教育資料と出席状況を確認する。 | Y14: Management is capable of show the training records for managed forklift drivers, and records demonstrate a transfer of competence/understanding. 管理者は、教育記録（テスト記録）等にて、管理している技能員への教育履歴を示すことができる。
C15: 1 | D15: The need for housekeeping and removal of unnecessary items in the workplace has been communicated. Visual standard postings are visible in work areas, and the site is utilizing the 3S checklist. 職場における整理と清掃の必要性は、周知されている。 3Sビジュアル標準とチェックリストが整備され、機能している。 | E15: 3S | F15: Integration 関連付け | G15: 13 | H15: Has the need for 3S(Select & remove, Sort, Keep clean) in the work place been properly communicated? 作業場所における3S(整理・整頓・清掃）の必要性は、周知されているか？ | I15: Production and Maintenance Supervisor 製造職長/保全職長 | N15: レ | Q15: レ | V15: How do you ensure that people are aware of the need to remove unnecessary items? あなたは、どのように、技能員が不要物を廃棄する必要性を理解させていますか？ | X15: Review communication records to see if 3S is communicated across site Check line boards for 3S standards コミュニケーション記録を確認し、3Sが事業所全体に周知されているか、確認する。 工程掲示板の3S標準を確認する。 | Y15: The respondent can give at least one method used to implement 3S on site. 回答者は、現場の3S実施方法を少なくとも１つ答えることができる。
C16: 1 | E16: 3S | F16: Integration 関連付け | G16: 14 | H16: Is basic 3S being carried out and prepared 3S (visual) standard posted throughout the site? And 3S (visual) standard are reviewed/revised appropriately? 基本的な3Sは、決められた3S標準やビジュアル標準に基づき、事業所で実行されているか？ 3S標準や3Sビジュアル標準は全てのエリアで作成され、適宜更新されていますか？ | I16: Production and Maintenance Supervisor 製造職長/保全職長 Teammate and Maint Staff 技能員/保全員 | N16: レ | O16: レ | Q16: レ | R16: レ | W16: Conduct a site tour to review 3S visual standards at >3 work areas 現場巡回時、3つ以上の作業場で、3S標準を確認する。 | X16: 3S checklist (3S standard, 3S visual standard, self checklist etc.) 3Sチェックリスト（3S標準、3Sビジュアル標準、セルフチェックシート） | Y16: 3S Documents (3S standard/3S visual standard) are displayed in work areas, and 3S checklist is prepared/standardized 3S文書は現場に掲示されており（3S標準/3Sビジュアル標準）、また3Sチェックリストが準備/標準化されている。
C17: 1 | D17: Management team prepares an annual 3S plan. マネジメントチームは3S計画を準備している。 | E17: 3S | F17: Integration 関連付け | G17: 15 | H17: Have you created an annual 3S activity plan? 年間の3S活動の計画を作成しているか？ | I17: Safety Manager 安全担当課長 | S17: レ | V17: Have you created an annual 3S activity plan？ 年間の3S活動の計画を作成しているか？ | X17: Confirm the annual 3S plan. 3Sの年間計画を確認する。 | Y17: An annual 3S plan has been prepared. 年間の3S計画が作成されている。
C18: 1 | D18: Regulations regarding crane and hoist operations are known and used to establish a standard for crane and hoist safety for the facility. クレーン・ホイスト作業に関する法令要求が周知されている。また、事業所におけるクレーン・ホイスト安全標準に反映されている。 | E18: Crane and Hoist クレーン・ホイスト | F18: Integration 関連付け | G18: 16 | H18: Are the regulations concerning crane and hoist operations known? クレーン・ホイストに関する法令要求は、理解されているか？ | I18: Production SV 製造職長 | N18: レ | V18: What methods do you use to identify and ensure compliance to crane and hoist relevant safety rules ? クレーン・ホイストの安全法令について、どのような方法で特定・順守確認を行っていますか？ | X18: Review safety standard for Crane and Hoist operation クレーン・ホイスト作業の安全標準を確認する。 | Y18: More than three respondents can explain the regulations and who give at least one method for ensuring compliance. 少なくとも3人の回答者が、法令要求を説明できる。また、それを保証する方法を少なくとも１つ以上提示できる。
C19: 1 | E19: Crane and Hoist クレーン・ホイスト | F19: Integration 関連付け | G19: 17 | H19: Is there an established crane and hoist safety standard that complies with legal requirements? 作成されているクレーン・ホイスト標準は、法令要求を順守しているか？ | I19: Safety Manager 安全担当課長 | S19: レ | V19: What is the current safety standard for crane and hoist operation at the site? 事業所における、現在のクレーン・ホイスト安全標準は何ですか？ | Y19: There is a crane and hoist safety standard that highlights the legal requirements. クレーン・ホイストの標準は、法令要求を含んでいる。
C20: 1 | E20: Crane and Hoist クレーン・ホイスト | F20: Integration 関連付け | G20: 18 | H20: Do you conduct the safety training session based on the established crane and hoist safety standard that complies with legal requirements? 法令要求を織り込んだクレーン・ホイスト標準は、クレーン作業者に教育されていますか？ | I20: Production Supervisor 製造職長 | N20: レ | V20: Do you conduct the safety training session based on the established crane and hoist safety standard that complies with legal requirements? 法令要求を織り込んだクレーン・ホイスト標準は、クレーン作業者に教育していますか？ | W20: Observe Crane and Hoist activities at the shop floor. 現場でクレーン・ホイスト作業を確認する。 | Y20: There is a safety training session based on the established crane and hoist safety standard that complies with legal requirements is conducted. All teammates observed were operating cranes and hoists in accordance to the standard. 法令要求を織り込んだクレーン・ホイスト標準は、クレーン作業者に教育されている。また現場確認ですべての技能員が法令要求を遵守していることが確認できる。
C21: 1 | D21: The need for compliance towards the KY standard has been communicated by management. 管理者は、KY標準順守の必要性を周知している。 | E21: KY | F21: Integration 関連付け | G21: 19 | H21: Has the importance of the KY process been communicated to the teammates by management? 管理者（課長以上）は、作業者に、KY手順（4ラウンド）の重要性を周知しているか？ | I21: Production Manager 製造課長 | L21: レ | V21: How was the communication about KY done across site? 事業所で実施されるKY（の手順）について、どのように周知されていますか？ | X21: Review communication records to see if the need to comply with the KY standard was communicated. コミュニケーション記録を確認し、KY標準順守の必要性の周知を確認する。 | Y21: There is evidence of a defined KY process that been communicated with all staff at least once in the past year. 少なくとも過去1回、規定されたKYの手順を全従業員へ周知した記録がある。
C22: 1 | D22: Managements identified what risk assessment it is required to undertake by regulation and knows to what extent these have been performed. 管理者は、法令で実施が要求されるRAを特定し、どの程度実施されたか把握している。 | E22: Risk Assessment リスクアセスメント | F22: Integration 関連付け | G22: 20 | H22: Have the regulations and/or expectations concerning risk assessments been identified? RAに関する法令要求は、特定されているか？ | I22: Safety Manager 安全担当課長 | S22: レ | V22: What are the regulations and/or expectations regarding Risk Assessments? How does the site ensure compliance? 実施されたRAは、対応されるべき法的要件をどの程度カバーしていますか？ | Y22: The respondent can indicate what risk assessments are required by regulation and/or Bridgestone expectation and to what extend each of these is done. 回答者は、どのようなRAが法令で法的に必要であり、どの程度実行されているか提示できる。
C23: 1 | E23: Risk Assessment リスクアセスメント | F23: Integration 関連付け | G23: 21 | H23: Have the risk assessments been performed or is there a plan to complete? RAは、実行されているか？または、計画があるか？ | I23: Production Foreman 製造主任 | M23: レ | V23: When was the last risk assessment performed at the site? 事業所において、いつ直近のRAが実施されましたか？ | X23: Review the last risk assessment report 直近のRA実施記録を確認する。 | Y23: There is evidence that the required risk assessments have been done or there is a plan to complete. 要求されるRAが実施された記録または完了計画がある。
C24: 1 | D24: Contractor employees who perform construction/works in BS have required skills and certification(E.g. crane and hoist). 工事/作業を行う協力会社の従業員は、工事/作業に必要な能力・法的資格(例：クレーン・ホイスト）を有している。 | E24: Contractor management 協力会社の安全管理 | F24: Integration 関連付け | G24: 22 | H24: Do contractor employees who perform construction/works in BS have required skills and certification(E.g. crane and hoist)? 工事/作業を行う協力会社の従業員は、工事/作業に必要な能力・法的資格(例：クレーン・ホイスト）を有しているか？ | I24: Maintenance Supervisor 保全職長 | Q24: レ | V24: How to you confirm that contractor employees who perform construction/works in BS have required skills and certification(E.g. crane and hoist)? 工事/作業を行う協力会社の従業員は、工事/作業に必要な能力・法的資格(例：クレーン・ホイスト）を有していることをどのように確認しているか？ | X24: Review certifications of contractors. 協力会社の資格を確認する。 | Y24: It can be confirmed that contractor employees who perform construction/works in BS have required skills and certification(E.g. crane and hoist). 協力会社の従業員は、工事/作業に必要な能力・法的資格(例：クレーン・ホイスト）を有していることを確認できる。
C25: 1 | D25: Large Tire Manual Handling Operations are identified. A procedure exists and teammates are aware of it. 大型タイヤの手動ハンドリング作業が識別され、標準が存在し、従業員はそれを把握している。 | E25: Large Tire Manual Handling Operation 大型タイヤハンドリング作業 | F25: Integration 関連付け | G25: 23 | H25: Are large tire manual handling operations identified? Is there a procedure for each of these operations? Has an assessment been completed in each case to determine that manual handling is necessary. 大型タイヤのハンドリング作業は特定されており、これらの各作業の標準はあるか？ またそれらの作業が必要だと判断した場合にRAは完了しているか？ | I25: Production SV 製造職長 | N25: レ | V25: How were the large tire handling operations assessed in order to determine that manual handling is necessary? Has a working procedure been developed for each large tire manual handling operation? 大型タイヤの取扱い時、やむを得ず、手動ハンドリングが必要だと判断するため、評価が実施されているか？ 大型タイヤの手動操作ごとに作業標準が作成されているか？ | X25: Review in records for evidence if any feasibility studies, result of risk assessment or other assessment methods were used in order to identify the manual handling of large tires. 大型タイヤの手動ハンドリング作業を特定するために、実現可能性調査、リスク評価、その他方法の実施記録を確認する。 | Y25: There is evidence that a RA or other study has been completed for each operation requiring manual handling of large tires, that operations requiring manual handling of large tires are properly identified. A working procedure exists for each. 大型タイヤの手動ハンドリングを必要とする作業は、適切に識別されており、RAが実施されている。また各作業の作業標準が準備されている。
C26: 1 | E26: Large Tire Manual Handling Operation 大型タイヤハンドリング作業 | F26: Integration 関連付け | G26: 24 | H26: Has the Large Tire Manual Handling Operation procedure been communicated to the relevant people? 大型タイヤハンドリング作業の標準は、関係者へコミュニケーション（周知）されているか？ | I26: Production Supervisor 製造職長 | N26: レ | V26: Who received Large Tire Manual Handling Operations training? 誰が大型タイヤの手動ハンドリングに関する教育を受けているか？ | X26: Review if training materials and attendance indicate a transfer of knowledge regarding Large Tire Manual Handling Operations to the people that require it. 教育資料と受講記録を確認し、大型タイヤ手動ハンドリングを行う人々に教育が行われていることを確認する。 | Y26: Training records show that all relevant people within the site have been given training on the Large Tire Manual Handling Operations procedure, and that there is confirmation of transfer of knowledge. 事業所内の全ての関係者が大型タイヤの手動ハンドリング作業手順に関する教育を受けたことを教育記録から確認できる。
C27: 1 | D27: Ergonomics hazards have been identified on site エルゴノミクス（腰痛等の疾病リスク）に関する危険源を含む作業が現場で特定されている。 | E27: Ergonomics エルゴノミクス | F27: Integration 関連付け | G27: 25 | H27: Have Ergonomics hazards been identified on site? エルゴノミクス（腰痛等の疾病リスク）に関する危険源が現場で特定されているか？ | I27: Safety Manager 安全担当課長 | S27: レ | V27: Is there a record of Ergonomics hazards identified on site? エルゴノミクス（腰痛等の疾病リスク）に関する危険源が現場で特定された記録はあるか？ | X27: Review evidence of Ergonomic hazards identification on site 現場で特定されたエルゴノミクス（腰痛等の疾病リスク）に関する危険源の記録を確認する | Y27: Ergonomic hazards are identified on site. エルゴノミクス（腰痛等の疾病リスク）に基づく危険源は、現場で特定されている。
C28: 1 | D28: Is there a list of all approved chemicals for the site, along with a corresponding Material Use Form (MUF) and Safety Data Sheet (SDS), and these records are kept according to local regulation. Required employees are aware of Chemical hazards. 事業所で承認された全ての化学物質は、リスト化され、対応する原材料取扱基準表およびSDSがあり、これらの記録は法規にしたがって保持されている。 関連する従業員は、化学物質の危険性を認識している。 | E28: Chemical Management 化学物質管理 | F28: Integration 関連付け | G28: 26 | H28: Are all chemicals used on site (production and non-production chemicals) listed in a list of approved chemicals, and each has a corresponding Material Use Form (MUF) and current and compliant Safety Data Sheet (SDS)? 事業所で使用される全ての化学物質はリスト化され、対応する原材料取扱基準表およびSDSはあるか？ | I28: Safety Manager 安全担当課長 | S28: レ | V28: Is there a record of all chemicals used on site (production and non-production chemicals)? Is there a Material Use Form (MUF) and Safety Data Sheet (SDS) for each of the Chemicals listed? 事業所で使用される全ての化学物質の記録はあるか＞記載されている各化学物質の原材料取扱基準表及びSDSはあるか？ | X28: Review evidence that there is a list of approved chemicals, and all relevant documents (MUF, SDS) are available for each material 承認された化学物質のリストがあり、関連する全ての文書（原材料取扱基準表、SDS）が各材料に対して存在することを確認する。 | Y28: All chemical materials used on site are listed in the active chemical listing, and relevant documentation (MUF, SDS) is available for each material. 事業所で使用される全ての化学物質は、承認された化学物質としてリスト化されており、関連する文書（原材料取扱基準表、安全データシート）が管理されている。
C29: 1 | E29: Chemical Management 化学物質管理 | F29: Design 設計 | G29: 27 | H29: Are lists of approved chemicals, Material Use Forms and Safety Data Sheets kept according to local regulation? 認可された化学物質のリスト、原材料取扱基準表、SDSの記録は、法規にしたがって保管されているか？ | I29: Production SV 製造職長 | N29: レ | V29: Request proof of local regulation compliance. 法規への準拠の証明を確認する | X29: Check that Chemical Material documents (MUF, SDS) are stored within the required local regulation timeframe 化学物質に関する書類（原材料取扱基準表、SDS）を確認し、法規で規定された期間、保管されていることを確認する。 | Y29: Chemical Material documents are stored within the required timeframe according to local regulations 化学物質に関連する文書は、法規に従って、必要な期間保存されている。
C30: 1 | E30: Chemical Management 化学物質管理 | F30: Integration 関連付け | G30: 28 | H30: Have employees been made aware of the Chemical hazards of their jobs? 従業員は自身の業務で扱う化学物質の危険性を把握しており、どんな時に危険にさらされるか教育を受けているか？ | I30: Teammate 技能員 | O30: レ | V30: Are you aware of the Chemical hazards of your job? あなたは業務で取り扱う化学物資の危険性を知っているか？ | Y30: Respondent/teammates are aware of the Chemical hazards in the area of their jobs 回答者は、自身の業務における化学物質の危険性を認識している。
C31: 1 | D31: General safety management for maintenance requirements have been communicated and both maintenance managers and staffs are aware of General safety management for maintenance. 設備課長と保全員は、両者とも保全業務における要求事項を認識している。 | E31: General safety management for maintenance 一般保全安全管理 | F31: Integration 関連付け | G31: 29 | H31: Is SBU/site local maintenance safety management procedure trained to maintenance staff? SBUまたは工場保全安全管理要領/手順は、保全員に教育していますか。 | I31: Maintenance Supervisor 保全職長 | Q31: レ | V31: 保全安全の標準に関する教育や周知をいつ、どのような内容で行いましたか？ When and with what content did you provide education and awareness regarding maintenance safety standards? | X31: Training records and content that demonstrates all maintenance team members have received appropriate training. 全ての保全員が、保全安全に関する必要な教育を受けた記録を確認する。 | Y31: There is the training record for maintenance technicians. 保全員に対する教育記録がある。
C32: 1 | D32: Teammates understand the fire risks. 技能員は、火災に関するリスクを理解している。 | E32: Fire Risk Assessment 火災RA | F32: Integration 関連付け | G32: 30 | H32: Are you aware of fire risks in your job position/services? 自工程の火災リスクを認識しているか？ | I32: Teammate 技能員 | O32: レ | V32: Do you remember the event situation of fire accident which occurred in your department? What are the most highest fire risks do you think in your job positions or in your services? 自工程で発生した火災発生状況や自工程の火災リスクを知っているか？ | W32: Interview to >3 Teammates to verify. 少なくとも3人以上の技能員と話して確認する | X32: － | Y32: All respondents can answer 2 more than fire risks. 2つ以上の火災リスクを全員が回答できる
C33: 1 | D33: The flammable materials are listed and these list are frequently and properly maintained. 火災の原因となる危険物がリスト化され、それらのリストが適切な方法・頻度で更新されている。 | E33: Flammable Materials Management 危険物管理 | F33: Design 設計 | G33: 31 | H33: Are you aware of laws and regulations regarding flammable materials? 危険物に関する法令を理解しているか？ | I33: Production Supervisor 製造職長/主任 | M33: レ | N33: レ | V33: What/Where/How the flammable materials stored in your own process? 自工程で扱う危険物はどこで、何を、どのようにして管理していますか？ | W33: － | X33: Check the flammable material list/management method. 危険物のリストとその管理方法に関する文書を確認する。 | Y33: The flammable material list is updated on the basis of defined frequency and methods. 火災の原因となる危険物を含めたリストが決められた頻度・方法によって更新されている
C34: 1 | D34: When conducting hot work, the required control measures are correctly recognized. 火気工事の際に必要となる処置を理解している。 | E34: Hot Work Management 火気使用 | F34: Design 設計 | G34: 32 | H34: When conducting hot work, do you review a fire watcher assignment? 火気使用時に火気監視人の配置条件を把握しているか？ | I34: Maintenance Supervisor 保全職長/主任 | Q34: レ | V34: Do you assign the fire watcher correctly when using fire performing hot work? 火気使用時に火気監視人を配置していますか？ | W34: If construction is underway with hot work, check on-site. 火気工事があれば、現場を確認する | X34: － | Y34: Be able to answer the monitor assignment status. 監視人の配置状況を回答できる
C35: 1 | D35: The fire extinguishing equipment is properly managed and operated. 消火設備の管理と運用が適切に行われている。 | E35: Fire Fighting 消火設備 | F35: Design 設計 | G35: 33 | H35: Do you perform the periodic inspection of the fire extinguishing equipment in accordance with laws and regulations? 消火設備の定期点検を国・地域の要求事項に従い実施しているか？ | I35: D.P. Manager 防災担当課長 | T35: レ | V35: Have the fire equipment been periodically inspected? 消防設備（火災報知器、消火器、消火栓）の点検を行っていますか？ | W35: － | X35: Confirm inspection records. 点検結果を確認する。 | Y35: They can answer the status of the fire extinguishing equipment (inspection results). 適切に点検が行われていることが確認できる
C36: 1 | D36: Mixing MUST 11 is deployed and educated in sites. 精練MUST11の内容が工場内で展開され、適切な教育が実施されている。 | E36: Mixing MUST-11 精練MUST11 | F36: Design 設計 | G36: 34 | H36: Is Mixing MUST11 deployed to mixing department and maintenance department? MUST11が工場内で展開されているか？ | I36: Teammate (Mixing), Maintenance Staff 技能員（精練）、保全員 | O36: レ | R36: レ | V36: What tasks and inspection items related to MUST 11 have you been educated? MUST11に関連した教育ではどのような作業、点検項目があることを教育されましたか？ | W36: Talk to >3 Teammates to verify. 少なくとも3人上の技能員と話して確認する | X36: Confirm training records. 教育記録を確認する。 | Y36: Everyone can explain the check/maintenance works associated with MUST11. 全員がMUST11に関連する確認・点検作業について説明できる
C37: 1 | D37: The evacuation drill are conducted for all employees working in the site. 事業所の全従業員を対象とした避難訓練を実施している。 | E37: Disaster Prevention General 一般事項 | F37: Integration 関連付け | G37: 35 | H37: Have employees experienced evacuation routes and procedures during evacuation drills? 従業員へ避難訓練で避難ルートおよび手順を経験しているか？ | I37: D.P. Manager 防災担当課長 | T37: レ | V37: Are you involved in evacuation drills once a year for the entire business site? 年に１回、事業所全体で避難訓練を実施しているか？ | W37: － | X37: Confirm evacuation drill record. 避難訓練記録を確認する。 | Y37: The evacuation drill are conducted for all persons on site. 事業所内の全員を対象とした避難訓練を実施している
C38: 1 | D38: Electric systems (wiring/equipment) that have to be checked are listed and updated properly. 電気配線/機器の確認箇所がリスト化され、適切な頻度で更新されている。 | E38: Electric system 電気配線 | F38: Integration 関連付け | G38: 36 | H38: Do you standardize the inspection points and maintenance plan for electrical wiring? 電気配線の管理箇所や点検計画はあるか？ | I38: D.P. Manager, Maintenance Manager 防災担当課長、保全課長 | P38: レ | T38: レ | V38: Do you standardize what and how electrical wirings* are inspected based on global standards? (*cables, switch board, individual area's wiring etc.) 事業所内の電気配線（電線、配電盤、および見えない配線等）について、GSで確認すべきポイントを基にそれらのリスト・年間点検計画を作成していますか？ | W38: － | X38: Confirm the working standard that established electric system's maintenance methods/points. 電気配線の点検方法・点検場所に関する作業標準を確認する。 | Y38: They can show documented rules on how to manage and inspect electrical system. 電気配線の管理や点検方法に関する文書化されたルールを示すことが出来る
C39: 1
B40: Reactive | C40: 2 | D40: Updating training material or providing additional training is reviewed when accidents occur. 災害発生時、教育見直しの必要性、または追加教育の実施について、検討されている。 | E40: Safety communication 安全コミュニケーション | F40: Change & Emergency planning 変更管理 & 緊急事態準備 | G40: 37 | H40: Are trainings needs and content reviewed and edited after an accident occurs? 災害発生後、教育の必要性や内容について、見直し・改訂が実施されているか？ | I40: Safety Manager 安全担当課長 | S40: レ | V40: When was the last review on the safety training needs? When was the last update on training material? Did it include any feedback based on latest incidents? 直近で、安全教育の必要性は、いつ見直されましたか？直近で、教育資料は、いつ更新されましたか？また、最近の災害情報が織り込まれていますか？ | X40: Review last safety incident and its action plans 直近の労働災害、および実行計画を確認する。 | Y40: There is evidence of at least one training that was reviewed after an accident. 災害後、教育が見直された事例が少なくとも１つ確認できる。
C41: 2 | D41: The site has a process to communicate the cause of accidents timely as indicated by communication records. 拠点は、コミュニケーション手順を保持し、タイムリーな災害原因の共有化に使用している。また、そのコミュニケーション記録がある。 | E41: Safety communication 安全コミュニケーション | F41: Integration 関連付け | G41: 38 | H41: Are the causes of accidents/incidents that have occurred at this site communicated to teammates and is this shown by communication records? 自工場で発生した災害・事故の原因は従業員に周知され、コミュニケーション記録に記載されているか？ | I41: Safety Manager/Teammate 安全担当課長/技能員 | O41: レ | S41: レ | V41: When are the addressed new hazards or the causes of incidents communicate(ed) to you if any? あなたは、いつ災害の原因や新たな危険源について、周知され/しましたか（もしあれば）？ | W41: Talk to teammates from >3 work areas to address latest communicated incident 3つ以上の作業場で技能員に、最近周知された災害に関してヒアリングする。 | X41: Review communication records コミュニケーション記録を確認する。 | Y41: The respondent indicates that the causes of incidents are communicated to him/her. Communication records contains evidence that incidents are communicated properly across site. 回答者は、災害の原因を周知されており、周知記録には、事業全体に周知されたことが確認できる。
C42: 2 | D42: Site Safety Manager leader shares the incident or fire reports from other sites. 事業所の安全担当課長は他事業所からの災害報告や出火報告の情報を共有化している。 | E42: Incident Management インシデント管理 | F42: Integration 関連付け | G42: 39 | H42: Does the safety leader share incident reports from other sites? 安全担当課長は、他事業所の災害報告を共有化しているか？ | I42: Teammate 技能員 | O42: レ | V42: Are you in any way made aware of incident that occurred on other Bridgestone facilities? BSの他事業所で発生した災害に関して、知っていますか？ | Y42: Respondent can provide examples of accidents which occurred on other facilities and how that information was obtained. There is evidence of incident reports from other sites being shared. 回答者は、他事業所で発生した災害事例、また、どのように情報を入手したか説明できる。
C43: 2 | D43: Countermeasures following of incidents (industrial accidents, fire accidents, near misses/hidden dangers reports and recurrence preventions) are implemented. 自拠点において発生したインシデント（労働災害、出火事故、ヒヤリおよび潜在的危険源の報告、類災報告）への対策が実施されている。 | E43: Incident Management インシデント管理 | F43: Change & Emergency planning 変更管理 & 緊急事態準備 | G43: 40 | H43: Did you take measures to recently incidents*? *Refer to “Safety Maturity Assessment Guidelines” (Manufacturing) Appendix 4 発生したインシデント（労働災害、出火事故、ヒヤリ、潜在的危険源、類災報告）に対して対策を実施しているか？ *添付資料4 生産拠点向け安全成熟度評価：システムチェックシート 「インシデント管理」 補足説明資料を参照 | I43: Safety Manager 安全担当課長 | S43: レ | V43: Is there a record of countermeasures implemented after incidents (industrial accidents, fire accidents, near misses, hidden dangers reports and recurrence preventions) identified? インシデント（労働災害、出火事故、ヒヤリ、潜在的危険源、類災報告）発生後、対策が実施された記録はあるか？ | X43: Review the Near-misses reports and action plans to check if the countermeasures were implemented. ヒヤリ報告書と対応計画を確認し、対策が実施されていることを確認する。 | Y43: The incident (industrial accidents, fire accidents, near misses/hidden dangers reports and recurrence preventions) that recently occurred were taken countermeasures based on global standards. インシデント（労働災害、出火事故、ヒヤリおよび潜在的危険源の報告、類災報告）の報告を受けて、グローバル標準に基づいた対策が実施されている。
C44: 2 | D44: Change initiators and approvers have been trained to fulfil their duties based on a local process in preparation to change on safety, IH and DP. 変更の審議者および承認者は、事業所の安全衛生・防災に関わる変更の地区手順に基づき、責務を遂行するために必要な教育を受けている。 | E44: Management of Change 変更管理 | F44: Change & Emergency planning 変更管理 & 緊急事態準備 | G44: 41 | H44: Have change initiators been adequately trained to fulfil their duties? 変更管理に関わる人たちは、責務について、適切な教育を受けているか？ | I44: MOC coordinator 変更管理起案者 | U44: レ | V44: What are the training required for change initiators and approvers? 変更管理の対応者・承認者に求められる教育は、何ですか？ | X44: Review training records to see if the required training was completed 要求される教育が完了しているか、教育記録を確認する。 | Y44: Change initiators and approvers have received MOC training and this is indicated by the records. 変更の起案者・審議者・承認者は、変更管理(4M変更）の教育を受けている。また、その記録がある。
C45: 2 | D45: The LOTO standard(site standard, ECP, work standard, etc.) is reviewed in response to incidents, audit findings, authority guidance and concerns raised by teammates． LOTO標準（事業所の標準・ECP*・作業標準等）は、災害・監査結果・行政指導・従業員からの困り事に基づき、見直しされている。 *動力源遮断手順書 | E45: LOTO Standard LOTO標準 | F45: Design 設計 | G45: 42 | H45: Is the LOTO standard reviewed after incidents, audits or when opportunity areas have been identified? LOTO標準は、災害、監査、特定された（改善の）機会の後、見直しされていますか？ | I45: Safety Manager 安全担当課長 | S45: レ | V45: When was the last review of LOTO standard/training materials? Was it done based on feedback/action plans from an incident/audit? 直近で、いつLOTO標準やLOTOの教育内容は見直されましたか？また、災害または監査の結果・実施計画に基づき、（LOTO標準の）見直しが実施されていますか？ | X45: Cross check the revision history against such events to verify if updates have been made 災害や監査等により更新されているか確認するため、改訂履歴でクロスチェックする。 | Y45: The LOTO standard(site standard, ECP, work standard, etc.) was revised based on incident causes, audit findings, authority guidance and concerns raised by teammates, if necessary． 災害要因や監査、技能員からの困りごとで、LOTO手順書（事業所の標準・ECP*・作業標準等）の改善が必要な場合、手順書が見直しされている *動力源遮断手順書
C46: 2 | D46: The effectiveness of Site Safety Rules is reviewed in response to incidents, audits and authority's guidance. 事業所の安全ルールの有効性は、災害・監査や行政指導に基づき、見直しされている。 | E46: Safety Rules 安全ルール | F46: Design 設計 | G46: 43 | H46: Is the effectiveness of the Site Safety Rules reviewed after incidents, audits or opportunity areas have been identified? 事業所の安全ルールの有効性は、災害、監査、特定された（改善の）機会の後、見直されていますか？ | I46: Safety Manager 安全担当課長 | S46: レ | V46: What information is used to determine the effectiveness of Site Safety Rules? Are Site Safety Rules reviewed following incidents, audits, etc. where improvements/changes may be needed? 事業所の安全ルールの有効性は、どのような情報をもとに、判断されていますか？ それらは事故等が発生した後に見直しが図られていますか？ | X46: Cross check the revision history against such events to verify if updates have been made 災害や監査等により更新されているか確認するため、改訂履歴でクロスチェックする。 | Y46: The respondent can clearly indicate how Site Safety Rules are reviewed and improved, as needed following an incident. 回答者は、安全ルールがどのように見直され、改善されるか明確に提示できる。
C47: 2 | D47: Work at height training and controls are reviewed and improved when incidents involving Work at height have occurred. 高所作業の教育・作業管理は、高所作業に関する災害が発生した際、見直され、改善されている。 | E47: Work at Height 高所作業 | F47: Design 設計 | G47: 44 | H47: Is the Work at height procedure and its trainings reviewed after a Work at height incident has occurred? 高所作業の災害後、高所作業手順や教育は、見直されていますか？ | I47: Teammate 技能員 | O47: レ | V47: Is there, in your view, a clear development or review of Work at height safety standards when an Work at height incident has occurred? あなたの考えでは、高所作業における災害が発生した際、高所作業の安全標準が明確に（具体的に）改善されていますか？ | W47: Talk to teammates from >3 work areas 3つ以上の作業場で技能員にヒアリングする。 | X47: Cross check the revision history against such events to verify if updates have been made 災害や監査等により更新されているか確認するため、改訂履歴でクロスチェックする。 | Y47: A sample of 3 teammates all confirm that Work at height incidents initiate a Work at height process review. 少なくとも3人の技能員のサンプルチェックにおいて、高所作業の災害が発生した場合、高所作業手順の見直しにつながっていることを確認できる。
C48: 2 | D48: The implementation and design of mobile equipment safety controls are reviewed and improved after incidents occur. 動力車における安全管理の実行・設計は、災害発生時、見直され、改善されている。 | E48: Mobile Equipment 動力車 | F48: Design 設計 | G48: 45 | H48: Is there any accidents on mobile equipment last one year? Is the Mobile Equipment procedure and its trainings reviewed after an incident involving mobile equipment has occurred? 過去１年間に動力車の災害は発生しましたか？動力車関連の災害後、動力車作業手順や教育は、見直されていますか？ | I48: Production SV 製造職長 | N48: レ | V48: When was the last review of mobile equipment procedure? Was it done based on feedback/action plans from an incident? 直近で、いつ動力車手順は見直されましたか？また、災害または監査の結果・実施計画に基づき、（動力車手順の）見直しが実施されていますか？ | X48: Review the incident log and cross check relevant incidents with the content of the standard 災害履歴を確認し、標準の内容と災害が関連しているか、クロスチェックする。 | Y48: Respondent can give examples of incidents from the previous 12 months and can explain what process improvements have been implemented because of those incidents. 回答者は、過去1年間の災害について、事例をあげることができる。また、災害によって、どのような改善が実行されたか説明できる。
C49: 2 | D49: 3S leaders have been appointed and regularly inspect work areas and teams follow-up on the findings/advice from the 3S leader. 3S実行責任者は、任命され、定期的に作業場をチェックしている。また、作業者が3S実行責任者からの指示・助言を実行している。 | E49: 3S | F49: Integration 関連付け | G49: 46 | H49: Has a 3S leader been appointed in each area? 3Sのエリアごとの責任者は、任命されていますか？ | I49: Safety Manager 安全担当課長 | S49: レ | W49: Observe >3 work areas to see if there are 3S leaders and if teams take them seriously 3つ以上の作業場でのモニタリングにおいて、３Sリーダー（実行責任者）がいるか、チーム（各工程）は真剣に取り組んでいるか、確認する。 | Y49: There is an officially appointed 3S leader on site. 事業所で正式に任命された3Sリーダー（実行責任者）がいる。
C50: 2 | E50: 3S | F50: Integration 関連付け | G50: 47 | H50: Does the 3S leader inspect work areas and follow up on his/her recommended actions are complete? 3S実行責任者は、職場内を点検し、推奨事項が完了しているかフォローアップしていますか？ | I50: Safety Manager 安全担当課長 | S50: レ | V50: Can you share examples of actions defined during 3S inspections done by 3S leader? Were the actions completed? How often does 3S tours occur on the site (lead by 3S leader)? 3S実行責任者によって3S点検時に特定された指示事例を教えてください。その指示は対応済ですか？ 事業所において、3S実行責任者主導による3S巡回の頻度を教えてください。 | W50: Observe >3 work areas to see if action from 3S inspections by leaders were completed 3つ以上の作業場でのモニタリングにおいて、3S実行責任者による３S点検に基づく対応は、完了しているか、確認する。 | Y50: There is evidence of 3S inspections and recommended actions to improve 3S. 3S点検、改善に向けた推奨事項に関し、記録がある。
C51: 2 | D51: There is a list of licensed and trained crane operators who are aware of past incidents and know how to prevent reoccurrence of these. 有資格で教育済のクレーン作業者一覧がある。また、クレーン作業者は、過去災害および再発防止方法を理解している。 | E51: Crane and Hoist クレーン・ホイスト | F51: Integration 関連付け | G51: 48 | H51: Is there a list of licensed crane operators? クレーンの有資格者リストはありますか？ | I51: Production SV 製造職長 | N51: レ | X51: Official list of licensed crane operators 正式なクレーン有資格者リスト | Y51: There is an official list of licensed crane operators that highlights the expiry dates of their licenses. クレーンの有資格者、および資格の期限に関し、正式なリストがある。
C52: 2 | E52: Crane and Hoist クレーン・ホイスト | F52: Integration 関連付け | G52: 49 | H52: Are the crane operators aware of past incidents and know the procedures to avoid these from happening again? クレーン操作者は、過去災害を認識していますか？また、再発防止に向けた手順を理解していますか？ | I52: Teammate 技能員 | O52: レ | V52: Have there been any significant incidents which you have been made aware of? あなたが知っている過去発生した重大な災害は何ですか？ | W52: Talk to teammates from >3 work areas about last crane incidents 3つ以上の作業場で、直近のクレーンに関する災害について、ヒアリングする。 | X52: Review the incident log for crane operations クレーン作業に関する災害履歴を確認する。 | Y52: A minimum of 3 teammates know hoist & crane incidents occurred at the site, and can explain the actions for improvement. 少なくとも3人の技能員は、過去1年間での、クレーン災害が自工場で発生しているか把握している。また、災害が発生していた場合、改善が実行されたか説明できる。
C53: 2 | D53: Incident investigation results are used to supplement the risk tracking either by registering the causation as a new risk or adjusting control levels. 災害調査結果は、原因を新しいリスクとして登録する、もしくは管理レベルを調整することにより、リスク登録の補完に使用されている。 | E53: Risk Assessment リスクアセスメント | F53: Integration 関連付け | G53: 50 | H53: Is there a risk tracking on site? 事業所において、リスク一覧は、ありますか？ | I53: Safety Manager 安全担当課長 | S53: レ | V53: How is risk tracked at the site? 事業所におけるリスクは、どのように進捗管理されていますか？ | W53: Observe >3 work areas to see how risk is tracked and displayed 3つ以上の作業場で、リスクの追跡（管理）と掲示を確認する。 | Y53: There is a risk tracking that lists specific risks on site. 現場のリスクを登録したリストがある。
C54: 2 | E54: Risk Assessment リスクアセスメント | F54: Integration 関連付け | G54: 51 | H54: Are new risks added to the risk tracking or safety controls adjusted after incident investigations? 災害調査後、新たなリスクがリスク一覧に追加されますか？また、安全管理（方法）は見直されますか？ | I54: Safety Manager 安全担当課長 | S54: レ | V54: What methods do you use to ensure that the risk record and H&S controls are up-to-date with any incident investigation results? リスク記録と、その安全衛生管理は災害調査結果をもとに、どんな方法で（どのように）更新されていますか？ | X54: Review the incident log and cross check relevant incidents with the content of the standard 災害履歴を確認し、標準の内容と災害が関連しているか、クロスチェックする。 | Y54: The respondent can provide at least one method and connected example of how the causes of incidents are used to supplement risk records. 回答者は、災害の原因がどのようにリスク記録に反映されるかの方法と事例を、少なくとも１つ提示できる。
C55: 2 | D55: KY is conducted by everyone on site. KYは、事業所の全員に実施されている。 | E55: KY | F55: Integration 関連付け | G55: 52 | H55: Is KYT are conducted by all employee on site? KYTは、事業所の全ての従業員が実施しているか？ | I55: Production Foreman 製造主任 | S55: レ | V55: Who are involved in KYT? 誰がKYTに参加しますか？ | X55: Review KYT execution records KYT実施記録を確認する。 | Y55: KYT records show that all teammates and temporary staff have submitted a KYT within the last 3 months. KYT記録により、過去3か月間、全従業員と派遣社員はKYTを提出している（参加している）。
C56: 2 | D56: Pre-work meetings are conducted prior to the start of work, risks are identified and risk mitigation measures/administrative controls are defined. 作業の開始前に事前打ち合わせを実施し、リスクの顕在化およびその対応/リスク低減対策を決めている。 | E56: Contractor management 協力会社の安全管理 | F56: Integration 関連付け | G56: 53 | H56: Are pre-work meetings conducted prior to the start of work, are risks identified and risk mitigation measures/administrative controls defined. 作業の開始前に事前打ち合わせを実施し、リスクの顕在化およびその対応/リスク低減対策を決めているか？ | I56: Maintenance Supervisor 保全職長 | Q56: レ | V56: Are pre-work meetings conducted with contractors? What points are discussed at the meeting? 作業開始前に打ち合わせを実施しているか？どういった内容が打ち合わせで議論されているか？ | X56: Review records of pre-work meetings with contractors. 協力会社作業開始前の打ち合わせ記録を確認する。 | Y56: There is evidence that pre-work meetings are conducted prior to the start of work, risks are identified and risk mitigation measures/administrative controls are defined. 作業の開始前に事前打ち合わせを実施し、リスクの顕在化およびその対応/リスク低減対策を決めている記録がある。
C57: 2 | D57: The contractor selection criteria are established based on regulatory, Bridgestone, and/or site safety requirements. And contractor is reviewed based on these criteria and judged to determine if the contractor may be selected for work. 拠点の安全要件に基づき協力会社の選定基準が定められている。また選定基準に基づき協力会社を評価し、当該協力会社の選定可否を判断している。 | E57: Contractor management 協力会社の安全管理 | F57: Integration 関連付け | G57: 54 | H57: Are there criteria for selecting contractors and are contracts awarded in accordance with those criteria? Are contracts renewed at a regular frequency? 協力会社を選定する際の基準があり、それに従って契約しているか？契約の更新は決めれた頻度で行っているか？ | I57: procurement Manager 調達担当課長 | U57: レ | V57: What selection criteria do you use to evaluate contractors? Are evaluations conducted on a regular basis? 協力会社をどのような選定基準で評価していますか？ 評価は定期的に行われていますか？ | X57: Confirm the evaluation criteria and the records of the evaluated contractors. 協力会社の選定基準と評価した記録を確認する。 | Y57: There are evaluation criteria for contractors, and there are records that demonstrate that contractor evaluation criteria is being followed. 協力会社の選定基準があり、またそれに従った評価記録がある。
C58: 2 | D58: The large tire manual handling procedure is reviewed in response to incidents． 大型タイヤ手動ハンドリング標準は災害・ヒヤリ発生時にレビューされている。 | E58: Large Tire Manual Handling Operation 大型タイヤハンドリング作業 | F58: Integration 関連付け | G58: 55 | H58: Is the large tire manual handling operation procedure reviewed in response to incidents? 災害・ヒヤリの発生に対して、大型タイヤ手動ハンドリング標準のレビュー（見直し）を行っているか？ | I58: Production Foreman 製造主任 | M58: レ | V58: When was the last review of the Large Tire Manual Handling Operations procedure? Was this done based on a reported incident? 大型タイヤ手動ハンドリング標準を最後にレビューしたのはいつか？報告された災害に基づき実施されているか？ | X58: Check the revision history against the time of the last incident reported on a Large Tire Manual Handling Operation to verify if corresponding updates have been made 大型タイヤ手動ハンドリングに関しての災害・ヒヤリが報告された際、標準が更新されていることを改訂履歴から確認する。 | Y58: The Large Tire Manual Handling Operations procedure was reviewed based on a reported incident 報告された災害・ヒヤリに基づいて、大型タイヤの手動操作手順が見直されている。
C59: 2 | D59: Employees are aware of Ergonomic hazards 従業員は、エルゴノミクス（腰痛等の疾病リスク）上の危険源を認識している。 | E59: Ergonomics エルゴノミクス | F59: Integration 関連付け | G59: 56 | H59: Have employees been made aware of the Ergonomics hazards of their jobs and when they are increasing their ergonomic risks due to poor techniques or not using tools provided to prevent these hazards? 従業員は、エルゴノミクス（腰痛等の疾病リスク）上の危険源を認識しており、どんなときにエルゴノミクス上の危険にさらされるか知らされているか？ また必要な保護具を使用しなかったり、作業標準を守らなかった場合のリスクについても認識しているか？ | I59: Teammate 技能員 | O59: レ | V59: Are you aware of the Ergonomics hazards of your job? Have you or any teammate been informed when your are increasing your risk to them when performing incorrect movements or using assists incorrectly? あなたの業務におけるエルゴノミクス（腰痛等の疾病リスク）上の危険源を認識しているか？あなた又は他の従業員は、不適切な動きや誤ったアシスト(ツール)を使用し危険にさらされたとき、声掛けされるか？ | W59: Talk to >3 Teammates to verify if communication has been made to inform them of Ergonomic hazards 3人以上の従業員にインタビューし、エルゴノミクス（腰痛等の疾病リスク）上の危険源に関してコミュニケーションが取られていることを確認する | Y59: Respondent/teammates are aware of the Ergonomics hazards of their jobs, and the importance of using proper techniques and tools provided to minimize the ergonomic risks. 従業員は、自身の業務におけるエルゴノミクス（腰痛等の疾病リスク）に関する危険性を認識しており、定められたリスク低減対策や作業標準の効果を理解している。
C60: 2 | D60: There are countermeasures in place to reduce exposure to Chemical Hazards (e.g., gloves, local exhaust, etc.) according to the information on Material Use Form (MUF), Safety Data Sheet (SDS), and PPE hazard assessment. 原材料取扱基準表（MUF)およびSDSの情報にしたがって、化学物質の暴露を低減するための対策が講じられている。（例：手袋、局所排気等） | E60: Chemical Management 化学物質管理 | F60: Integration 関連付け | G60: 57 | H60: Are countermeasures in place to reduce exposure to Chemical Hazards? 化学物質に関する危険にさらされることを低減する対策が行われているか？ | I60: Production Manager 製造課長 | L60: レ | V60: Is there a record of countermeasures(PPE, engineering controls) implemented for identified Chemical hazards? 特定された化学物質の危険源に対して、実施されている対策(設備対策や保護具）の記録があるか？ | X60: Review the chemical materials list, PPE hazard assessment, and action plans to check if the countermeasures were implemented to reduce chemical hazards exposure. 化学物質リストおよび対応計画を確認し、化学物質の危険源の暴露を低減するための対策が実施されていることを確認する。 | Y60: Countermeasures (PPE, engineering controls, etc.) are being implemented, per PPE hazard assessment, or other method of reviewing hazards and risk, to reduce exposure of chemical hazards on site. 現場にて化学物質の危険源の暴露を低減するための対策が実施されている。
C61: 2 | D61: Maintenance manager responding to risks and sharing information as defined in the standard before to start the maintenance work. 設備課長は、保全作業前に標準で定められたリスク対応と情報共有を適切に行っている。 | E61: General safety management for maintenance 一般保全安全管理 | F61: Integration 関連付け | G61: 58 | H61: Do you hold the premeeting before maintenance work? And during this meeting do you identify the risks and determine risk mitigation & control? 作業の開始前に事前打ち合わせを実施し、リスクの顕在化およびその対応/リスク低減対策を決めているか？ | I61: Maintenance Supervisor 保全職長/主任 | Q61: レ | V61: 作業開始前に確認・実施すべき事項はどのような内容ですか？ What kind of things should I you check and implement before starting work? | Y61: The identified risks and determined risk mitigation & control are filled out on premeeting minutes. 顕在化したリスクおよびリスク低減対策が事前打ち合わせ議事録に記載されている。
C62: 2 | D62: Before maintenance, maintenance technicians join KY activity/tool box meeting and able to understand the shared information/cautions in work. 作業者は保全作業前のKY活動やミーティングに参加し、共有された内容や作業上の注意事項について理解している。 | E62: General safety management for maintenance 一般保全安全管理 | F62: Integration 関連付け | G62: 59 | H62: Are the identified risks and determined risks mitigation & control shared to maintenance staff. 顕在化したリスクおよび決定したリスク低減対策は保全員に周知されていますか？ | I62: Maintenance Supervisor 保全職長/主任 | Q62: レ | V62: 作業開始前の打ち合わせに作業を行うすべての保全員が参加していますか？ Do all maintenance staffs who perform task/maintenance service participate in the discussion before starting work? | W62: Confirm the record of sharing information and these clue (sign, attend list etc.). 共有された情報とその確認（サイン・参加者一覧等）の記録を確認する。 | Y62: Maintenance technicians can answer the identified risks and determined risk mitigation & control. 保全員は直近で従事した作業事例で顕在化したリスクおよびリスク低減対策を答えることができる。
C63: 2 | E63: General safety management for maintenance 一般保全安全管理 | F63: Integration 関連付け | G63: 60 | H63: Do the maintenance technicians recognize what actions they should take when any unexpected / uncontrolled change occurs or new risks are identified? 保全員は、保全作業中に想定されていない変化点や新たなリスクを発見した場合の対応方法を理解しているか？ | I63: Maintenance staff 保全員 | R63: レ | V63: 保全作業中に異常や共有されていないリスクを発見した際、どのように対応しますか？ How do you respond when you discover anomalies or unshared risks during maintenance work? | Y63: Maintenance technicians can answer that they have to suspend the maintenance work and report to the responsible person. 保全員は、作業を中断し、上司へ連絡することを回答できる。
C64: 2 | D64: Teammates understand the fire prevention rules. 技能員は、防火に関するルールを理解している。 | E64: Fire Risk Assessment 火災RA | F64: Integration 関連付け | G64: 61 | H64: Are you aware of the fire prevention measures (rules) in your own processes/services? 自工程の防火対策(ルール)を理解しているか？ | I64: Teammate 技能員 | O64: レ | V64: What are the fire prevention rules (SDS contents and operation standards) to address risks? リスクに対する防火ルール(SDS内容や作業標準)を知っているか？ | W64: Interview to >3 Teammates to verify. 少なくとも3人以上の技能員と話して確認する | X64: － | Y64: All respondents can answer 2 more than fire prevention rules. 2つ以上の防火ルールを全員が回答できる
C65: 2 | D65: Fire prevention control on the flammable materials are trained/educated to the teammates who may treat. 危険物の管理方法に関して適切に周知・教育を実施している。 | E65: Flammable Materials Management 危険物管理 | F65: Integration 関連付け | G65: 62 | H65: Do you share information or educate that the teammates can properly treat flammable materials? 危険物が正しく管理されるように周知・教育を行っているか？ | I65: D.P. Manager 防災担当課長 | T65: レ | V65: How do you conduct sharing information and educate for teammates the flammable materials to ensure that they are properly controlled? 危険物の保管量や廃棄方法についてどのように周知していますか。また逸脱が無いかどのように確認していますか。 | W65: Check the posted materials that notice the flammable materials storage limit/disposal methods. 危険物の保管量や廃棄方法が掲示もしくは参照できるようになっているか確認する | X65: Check the flammable material rules that limit of storage volume and how to disposal. 危険物保管量や廃棄方法に関するルールを確認する | Y65: Respondent can show the standard/rule that defines how to store and dispose the flammable materials 周知の頻度・手段について提示できる。また、周知した記録が提示できる
C66: 2 | D66: When conducting hot work, the required fire fighting tools are correctly prepared. 火気工事に必要な消火器等が適切に準備されている。 | E66: Hot Work Management 火気使用 | F66: Integration 関連付け | G66: 63 | H66: When hot work has to be performed do you prepare the existence of necessary fire fighting tools? 火気使用の際に必要な消火器等の準備がされているか？ | I66: Maintenance Supervisor 保全職長/主任 | Q66: レ | V66: Do you prepare the existence of necessary fire fighting tools when conduct hot work? 火気使用を伴う作業の開始前に消火器等の備品が準備されていることを確認していますか？ | W66: If construction is underway with hot work, check on-site. 火気工事があれば、現場を確認する | X66: － | Y66: Have prepared fire fighting tools required when using fire in advance (readily available when required). 火気使用時に必要な用具を事前に準備できている(必要時に即準備できる)
C67: 2 | D67: When conducting hot work, the curing to prevent spreading sparks are properly conducted. 火気工事の際に火花を防ぐための養生を適切に実施している。 | E67: Hot Work Management 火気使用 | F67: Integration 関連付け | G67: 64 | H67: Do you prepare the proper curing to prevent spreading sparks during hot work? 火花飛散防止のための養生を適切に行っているか？ | I67: Maintenance Supervisor 保全職長/主任 | Q67: レ | V67: Before/during hot work, is the curing condition inspected if sparks are well protected? 飛散する火花を想定して、隙間なく養生が出来ているか確認するプロセスがありますか？ | W67: If construction is underway with hot work, check on-site. 火気工事があれば、現場を確認する | X67: Confirm conduct records if any. Confirm the hot work working standard. 実施記録があれば、確認する 火気工事の際の作業標準を確認する | Y67: There are have record that the curing were confirmed at before hot work. 火気工事の際に養生を確認した記録がある
C68: 2 | D68: Teammates understand how to use the fire extinguisher. 技能員は消火設備の使用方法について理解している。 | E68: Fire Fighting 消火設備 | F68: Design 設計 | G68: 65 | H68: Are you trained how to use the fire extinguishing equipment? 消火設備の使用方法を理解しているか？ | I68: Teammate 技能員 | O68: レ | V68: What actions should you take when you identify the fire from your workplace? 火災が発生した際の対応方法（連絡・消火・避難の方法等）について教えてください。 | W68: Talk to >3 Teammates to verify. 少なくとも3人以上の技能員と話して確認する | X68: Confirm the training record. 教育記録を確認する | Y68: Everyone can answer how to respond in the event of a fire. 全員が火災が発生した際の対応方法を教育プログラムに基づいて適切に回答できる
C69: 2 | D69: Teammates understand requirements defined in Mixing MUST 11. 技能員は精練MUST11の要求事項を理解している。 | E69: Mixing MUST-11 精練MUST11 | F69: Integration 関連付け | G69: 66 | H69: Do you understand the operation standards related to MUST11? MUST11に関する作業標準を理解しているか？ | I69: Mixing Supervisor, Teammate (Mixing) 製造（精練）職長/主任、技能員（精練） | M69: レ | N69: レ | O69: レ | V69: Do you understand the operation standards of MUST11? Please tell me the contents. MUST11の作業標準を理解していますか？ どのような内容かを教えてください | W69: － | X69: － | Y69: Everyone understands the operation standards of MUST11. 全員がMUST11の作業標準を理解している
C70: 2 | D70: The fire prevention training are conducted proper frequency/method. 火災予防に関する教育を、適切な頻度・方法で実施している。 | E70: Disaster Prevention General 一般事項 | F70: Integration 関連付け | G70: 67 | H70: Is DP training conducted to teammates on hiring or job transferring? 入社時、異動時の火災予防に関する研修などを行い、育成しているか？ | I70: D.P. Manager 防災担当課長 | T70: レ | V70: Do you provide fire prevention training etc. for new employees and transferred employees? 新入時、異動時、定期に火災予防に関する研修など行っていますか？ | W70: － | X70: Confirm training records. 研修記録を確認する | Y70: Everyone receives fire prevention training etc. when they are newly employed or transferred from other departments. 入社時、受入時、異動時に全員が火災予防に関する研修などを受けている
C71: 2 | D71: Electric system inspection method are trained to person in charge. 電気配線/機器の点検方法について教育が実施されている。 | E71: Electric system 電気配線 | F71: Design 設計 | G71: 68 | H71: Do you standardize how to maintain the electrical wirings? 電気配線の管理方法はあるか？ | I71: D.P. Manager, Maintenance Manager 防災担当課長、保全課長 | P71: レ | T71: レ | V71: Do you establish the corrective measures when defects are identified by electric system inspections? And are you training maintenance staffs on these? 電気配線の点検において不具合が確認された場合の是正方法について定められ、適切に教育されているか？ | W71: － | X71: Confirm the electric system's training program/ training records. 点検に関する教育資料とその教育記録を確認する | Y71: There is a record of training on the electrical system. 電気配線の管理方法について適切に教育された記録がある
C72: 2
B73: Standardized | C73: 3 | D73: Training curricula are reviewed when adjustments are made to safety rules and controls significant to that training. 当該教育にとって重要な安全ルール・管理が変更された際、教育カリキュラムが見直されている。 | E73: Safety communication 安全コミュニケーション | F73: Design 設計 | G73: 69 | H73: Are trainings reviewed and adjusted when safety rules and controls that involve that specific subject matter change? 安全ルール・安全管理に変更が生じた場合は、教育の見直し・変更が行われているか？ | I73: Safety Manager 安全担当課長 | S73: レ | V73: How is training content kept up-to-date with adjustments made to safety controls? 安全管理に対応するため、教育内容はどのように更新されていますか？ | X73: Review the facility's training plan and training material 事業所の教育計画、および教育資料を確認する。 | Y73: A sample of 3 training file's document history shows they have been adjusted based on relevant safety control changes. ３つのファイル文書の履歴のサンプルチェックにおいて、安全管理の変更に伴い、見直しが実施されている。
C74: 3 | D74: Site safety rules and are communicated by management structurally as indicated by worker statements and communication records. 事業所の安全ルールは、作業者の意見や周知記録に示すように、管理者によって周知されている。 | E74: Safety communication 安全コミュニケーション | F74: Integration 関連付け | G74: 70 | H74: Are site safety rules communicated to teammates in a clear and structured manner? 事業所の安全ルール、明確かつ標準化された方法で、作業者に周知されているか？ | I74: Teammate 技能員 | O74: レ | V74: When do you receive any information about safety at work and is this information relevant to you? あなたは、いつ職場の安全に関する情報を受け取りますか？また、その情報は、あなたに関係するものですか？ | W74: Talk to teammates from >3 work areas about safety communication at site 3つ以上の作業場で、事業所の安全に関するコミュニケーションについて、ヒアリングする。 | X74: Review communication records コミュニケーション記録を確認する。 | Y74: A sample of three teammates all say that they are well informed and can explain how the information communicated contributes to their safety. 3人の技能員のサンプルチェックにおいて、情報が十分周知され、周知された情報がどのように自身の安全確保につながっているか、説明できる。
C75: 3 | D75: The Safety Leader is knowledgeable in the Recurrence Prevention Procedure of incidents (industrial accidents, fire accidents, near misses/hidden dangers reports and recurrence preventions) occurred and complies with recommendations and countermeasure implementation instructions. 安全担当課長は、発生したインシデント（労働災害、出火事故、ヒヤリおよび潜在的危険源の報告、類災報告）の再発防止手順を理解し、推奨事項や対策指示を実行している。 | E75: Incident Management インシデント管理 | F75: Integration 関連付け | G75: 71 | H75: After incidents occur, do you know what actions should be taken to prevent a recurrence? インシデント（労働災害、出火事故、ヒヤリ、潜在的危険源、類災報告）が発生した際、安全担当課として再発防止のためにどのような行動をするか理解しているか？ | I75: Safety Manager 安全担当課長 | S75: レ | V75: Do you conduct countermeasures based on results of cause analysis when incidents (industrial accidents, fire accidents, near misses/hidden dangers reports and recurrence preventions) occurred. インシデント発生時（労働災害、出火事故、ヒヤリおよび潜在的危険源、類災報告）に分析に基づいて対策を実施・計画していますか？ | Y75: The safety manager can show the plan and measures based on analysis to incidents. (Approach for engineering measure, working standards, training education, etc.) 回答者は、インシデントに対して分析に基づいた対応を計画し、実施していることが示せる。 (設備対策、作業標準、教育方法等へのアプローチ）
C76: 3 | D76: Reports of incidents (industrial accidents, fire accidents, and near misses, hidden dangers reports) are stored according to local legislations. The effectiveness of the countermeasures is evaluated. 自拠点におけるインシデント報告書（労働災害報告書、出火事故報告書、ヒヤリ報告書）は、地区基準に基づき保管されている。また、対策の有効性が評価されている。 | E76: Incident Management インシデント管理 | F76: Change & Emergency planning 変更管理 & 緊急事態準備 | G76: 72 | H76: Is the effectiveness of implemented countermeasures reviewed with the reporting individual, H&S and maintenance department? 対策の有効性は、報告者や安全担当課、保全課によってレビューされているか？ | I76: Safety Manager 安全担当課長 | S76: レ | V76: Is there a record of countermeasures closed and marked as complete after a incidents (industrial accidents, fire accidents, near misses/hidden dangers reports and recurrence preventions) occurred? Was this reviewed and agreed with the reporting individual? インシデント（労働災害、出火事故、ヒヤリおよび潜在的危険源、類災報告）が発生した後、対策完了を確認できる記録はあるか？また、それは報告者とレビューし合意がなされているか？ | X76: Review the near-misses reports and action plans to check if the countermeasures were reviewed and closed with confirmation by the reporting individual ヒヤリ報告書と対応計画をレビューし、対策がレビューされ完了し、ヒヤリ報告者に確認を求めていることを確認する。 | Y76: The countermeasures for incidents are confirmed by the reporting individual and effectiveness are evaluated by the H&S and maintenance departments. インシデントに対する対策は報告者による確認され、またその対策の有効性は安全衛生課や保全課によって評価されている。
C77: 3 | D77: Site safety rules and work standards are analyzed to identify how the proposed change might affect these positively or negatively. 起案された変更がどのような良い/悪い影響を与えるか特定するため、事業所の安全ルール・作業標準が使用されている。 | E77: Management of Change 変更管理 | F77: Change & Emergency planning 変更管理 & 緊急事態準備 | G77: 73 | H77: Are the site's safety rules analyzed in depth and are the risks regarding the change evaluated considered when a proposed change is being deliberated? 起案された変更（3M/4M）を審議する際、事業所の安全ルール・作業標準が十分に分析され、変更に関するリスクが評価されているか？ | I77: Safety Manager 安全担当課長 | S77: レ | V77: Who reviews impact of changes on the safe system of work? 作業の安全に関する変更において、誰がその影響を審議しますか？ | Y77: The respondent can explain how proposed changes are reviewed, and confirms the site safety rules and work standards are analyzed with the proposal. 回答者は、起案された変更がどのように審議されるか説明できる。また、事業所の安全ルール・作業標準が提案内容と共に分析されている。
C78: 3 | E78: Management of Change 変更管理 | F78: Change & Emergency planning 変更管理 & 緊急事態準備 | G78: 74 | I78: Safety Manager 安全担当課長 | S78: レ | X78: Review change records for safety evaluation and approval 安全に関する評価、および承認がわかる変更記録を確認する。 | Y78: Documentation from a sample of 3 changes support safety review and approval of changes. ３つの変更事例で、安全に関する審議と承認が確認できる。 | AB78: Same issue from QM audit | AC78: Done (refer item no. 8 of priority item F-up sheet)
C79: 3 | D79: LOTO procedures are understood and being followed. LOTOに関する安全ルールの適用と有効性について、定期的に見直され、改善の機会が活用されている。 | E79: LOTO Standard LOTO標準 | F79: Integration 関連付け | G79: 75 | H79: Do you know LOTO operation procedure in your process/work? 自工程/業務での、LOTO手順は理解していますか? | I79: Operators 技能員 Maintenance Staff 保全員 | O79: レ | R79: レ | V79: How do you perform LOTO in your process/works? 自工程/業務で、どのようにLOTOを実施しますか？ | X79: Review ECP and/or work standards ECP（動力車断手順書）または作業標準書を確認する。 | Y79: The respondent can explain LOTO procedure. 技能員がLOTO手順を説明できることを確認
C80: 3 | E80: LOTO Standard LOTO標準 | F80: Integration 関連付け | G80: 76 | H80: Is LOTO being performed correctly on site? LOTOは現場において正しく実施されていますか？ | I80: Tour 現場巡回 | V80: Is LOTO being performed correctly on site? LOTOは現場において正しく実施されていますか？ | W80: Conduct a site tour to review LOTO application and use in >3 work areas. 現場巡回時、3つ以上の作業場で、LOTOの適用と運用を確認する。 | Y80: LOTO was correctly followed by all teammates and maintenance staffs observed performing maintenance/operation tasks that required LOTO. In case that LOTO operation cannot be observed on site, confirm site tour records, etc. LOTOが必要な作業・保全において、確認した全ての技能員・保全員が正しくLOTOを実施している。 該当作業確認できない場合は、巡回記録等により確認する。 | AB80: Same issue from safety verification
C81: 3 | E81: LOTO Standard LOTO標準 | F81: Integration 関連付け | G81: 77 | H81: Is the LOTO system being used with periodical monitoring? LOTOの仕組みは運用され、定期的にモニタリングが実施されているか？ | I81: Production SV and Maintenance SV 製造職長と保全職長 | N81: レ | Q81: レ | V81: How do you monitor that LOTO is being implemented correctly? LOTOの実施についてどのようにモニタリングをしていますか？ | W81: Conduct record of patrol/monitoring on site. 管理者による現場巡回・モニタリングの記録を確認する。 | X81: W81V81:W81W82V81:W81U81:W81 | Y81: There are performed patrol/monitoring to LOTO activity including maintenance. LOTO作業(保全を含む)に対して巡回やモニタリングが行われている。
C82: 3 | D82: ECP(Energy control procedures) includes all applicable energy source(electrical, mechanical, pneumatic, etc.) has been prepared for all applicable machinery. LOTO対象の全ての設備に対し、対象となるエネルギー源（電気、機械（惰性運転・自重落下等）、空圧等）に対するECP(動力源遮断手順書)が作成されている。 | E82: LOTO Standard LOTO標準 | F82: Integration 関連付け | G82: 78 | H82: Are ECPs prepared for all applicable machinery? LOTO対象の全ての設備に対し、ECP（動力車断手順書）を作成していますか？ | I82: Production SV 製造職長 Maintenance SV 保全担当職長 | N82: レ | Q82: レ | V82: Do ECPs include LOTO procedures on all applicable energy sources(electrical, mechanical, pneumatic, etc.)? ECP（動力車断手順書）には対象となるエネルギー源（電気、機械、空圧等）の手順が含まれていますか？ | W82: Talk with >3 teammates to see if they are able to identify properly risks related to LOTO 3人以上の技能員がLOTO(未実施時)におけるリスクを正しく特定しているか、ヒアリングする。 | X82: Review ECPs ECP（動力車断手順書）を確認する。 | Y82: ECP includes all applicable energy source(electrical, mechanical, pneumatic, etc.) has been prepared for all applicable machinery. LOTO対象の全ての設備に対し、対象となるエネルギー源（電気、機械（惰性運転・自重落下等）、空圧等）に対するECP（動力車断手順書）が作成されている。
C83: 3 | D83: teammates have a consistent understanding of the Safety Rules applicable to them as indicated by worker statements. 作業者は、適用される安全ルールを理解しており、作業者の意見で確認できる。 | E83: Safety Rules 安全ルール | F83: Integration 関連付け | G83: 79 | H83: Do all teammates have a good knowledge of the Safety Rules applicable to their work/process? 全ての作業者は、自部署/自作業に適用される安全ルールを（十分）理解しているか？ | I83: Teammate 技能員 | O83: レ | V83: What Safety Rules are most essential to your job? あなたの仕事において、最も必要な安全ルールは、何ですか？ | W83: Talk to teammates from >3 work areas about safety rules 3つ以上の作業場で、安全ルールについて、技能員にヒアリングする。 | Y83: A minimum of three teammates can demonstrate knowledge of the Safety Rules and explain key points on safety in the work standard. 少なくとも3人の技能員は、安全ルールを理解し、作業標準内での安全に関するポイントを説明することができる。
C84: 3 | D84: The teammates understand Work at height safety rules, and follow the rules correctly. 技能員は、高所作業に関する標準を理解しており、標準は正しく順守されている。 | E84: Work at Height 高所作業 | F84: Integration 関連付け | G84: 80 | H84: Do you know Work at height safety rules in your plant? 自工場の高所作業に関する安全ルールを理解していますか？ | I84: Operators 技能員 | O84: レ | V84: What is Work at height safety rules in your plant? 自工場の高所作業時の安全ルールは何ですか？ | Y84: The respondent can explain Work at height safety rules. 技能員は、高所作業に関する標準の内容を説明できる。
C85: 3 | E85: Work at Height 高所作業 | F85: Integration 関連付け | G85: 81 | H85: Are Work at height controls being used and applied by teammates performing tasks that require Work at height? 高所作業の管理は、運用されているか？また、高所作業において、実行されているか？ | I85: Tour 現場巡回 | W85: Conduct a site tour to review Work at height application in all areas currently performing Work at height tasks. 現場巡回時、高所作業が行われる全作業場において、高所作業（標準）が適用されているか、確認する。 | Y85: Work at height Procedures were correctly followed by all teammates observed performing Work at height tasks. In case that Work at height operation cannot be observed on site, confirm site tour records, etc. 高所作業標準は、確認した全ての技能員に正しく順守されている。該当作業確認できない場合は、巡回記録等により確認
C86: 3 | D86: Site tour(s) indicate that observed operators use mobile equipment in accordance to prescribed controls. 現場巡回において、作業者は規定の管理に従い、動力車を使用している。 | E86: Mobile Equipment 動力車 | F86: Integration 関連付け | G86: 82 | H86: Do you know mobile equipment driving rules in your plant? 自工場での、動力車の運転ルールは理解していますか? | I86: Teammate 技能員 | O86: レ | V86: What is mobile equipment safety rules in your plant? 自工場の動力車運転時の安全ルールは何ですか？ | Y86: The respondent can explain mobile equipment safety rules. (speed limit, load capacity, forks down, wear seatbelt, hoot at cross walks, etc.) 技能員は、動力車運転に関する標準の内容を説明できる。（制限速度、荷重、爪の降下、シートベルト着用など）
C87: 3 | E87: Mobile Equipment 動力車 | F87: Integration 関連付け | G87: 83 | H87: Do all teammates that use mobile equipment follow the rules and procedures for mobile equipment? 動力車を使用している全作業者は、動力車に関するルール・手順を順守しているか？ | I87: Teammate 技能員 | O87: レ | W87: Observe >3 teammates to see if these adhere to the mobile equipment safety rules 3人以上の技能員のモニタリングにおいて、動力車の安全ルールが順守されているか、確認する。 | Y87: A minimum of three operators teammates show good application of mobile equipment safety rules. In case that forklift operation cannot be observed on site, confirm site tour records, etc. 少なくとも3人の技能員は、動力車の安全ルールを順守している。該当作業確認できない場合は、巡回記録等により確認 | AB87: Same issue from safety verification | AC87: Done (refer item no. 1 of priority item F-up sheet)
C88: 3 | D88: All unnecessary objects are being removed from the workspace and necessary items have a fixed and clearly marked position which is respected by the teammates. 全ての不要物は、職場から排除されている。また、必要なモノは、従業員によって明示された所定の場所に置かれている。 | E88: 3S | F88: Integration 関連付け | G88: 84 | H88: Are all unnecessary objects being removed from the work area? 全ての不要物は、作業場から排除されているか？ | I88: Teammate 技能員 | O88: レ | W88: Inspect >3 work areas to see if these are clear from unnecessary items Unnecessary Items are marked as defect and have a schedule fixing date 3つ以上の作業場で、不要物がないか、確認する。 不要物は、不具合品として明示され、廃棄日が決められている。 | Y88: The 3S Visual Standard was prepared and all inspected work areas were cleaned (no debris on floor, no spillages) as defined in the 3S visual standard, and there were no unnecessary objects (or plan to remove) that were not currently in use in the work area. 3Sビジュアル標準が作成され、標準で規定されたように、確認した全ての作業場で清掃され（床に破片や屑がない）、現在使用されていない不要物がない（または廃棄予定日が定められている）。 | AB88: Same issue from safety verification | AC88: Done (refer item no. 4 of priority item F-up sheet)
C89: 3 | E89: 3S | F89: Integration 関連付け | G89: 85 | H89: Are necessary equipment/tools being put in clearly marked and fixed positions? 必要なものは、明示された決められた場所に置かれているか？ | I89: Teammate 技能員 | O89: レ | W89: Inspect >3 work areas to see if necessary items have a marked location 3つ以上の作業場で、必要なものが明示された場所に置かれているか、確認する。 | Y89: All necessary items are stored in their clearly marked space/position. 必要な全てのものは、明確に表示された場所/位置に置かれている。 | AB89: Same issue from safety verification | AC89: Done (refer item no. 4 of priority item F-up sheet)
C90: 3 | D90: Crane operators are aware of the safety rules applicable to them and show adherence to these as indicated during the site tour(s) and worker statements. クレーン作業者は、適用される安全ルールを理解している。また、現場巡回時や作業者の意見から、順守状況を確認できる。 | E90: Crane and Hoist クレーン・ホイスト | F90: Integration 関連付け | G90: 86 | H90: Do you know crane and hoist operation rules in your process? 自工程での、クレーン・ホイストの操作ルールは理解していますか? | I90: Teammate 技能員 | O90: レ | V90: What is crane and hoist safety rules in your process? 自工程のクレーン・ホイスト操作時の安全ルールは何ですか？ | Y90: The respondent can explain crane and hoist safety rules. 技能員は、クレーン・ホイスト作業に関する標準の内容を説明できる。
C91: 3 | E91: Crane and Hoist クレーン・ホイスト | F91: Integration 関連付け | G91: 87 | H91: Do crane operators follow the rules and standards concerning cranes and hoist operations? クレーン作業者は、クレーン・ホイストのルール・標準を順守しているか？ | I91: Teammate 技能員 | O91: レ | V91: What safety rules are most essential to the tasks you perform with a crane your job? あなたが行うクレーンを使用した業務において、最も必要な安全ルールは、何ですか？ | W91: Observe if crane operators act in accordance to safety rules クレーン作業者が安全ルールに従っているか、確認する。 | Y91: A minimum of 3 crane operators work according to the crane and hoist safety rules stated in the crane and hoist procedure (Operator and others were kept away from hoisted loads, there was a work leader that gave hand signals, hoisted load's stability was checked with a lift of a few inches, etc.). In case that hoist and crane operation cannot be observed on site, confirm site tour records, etc. 少なくとも3人のクレーン操作者は、クレーン・ホイスト標準で規定された安全ルールに従い、作業している（吊り荷の下から外れ、第三者も遠ざける、合図を行う作業指揮者、吊り上げ後の地切りなど）。 該当作業確認できない場合、職長巡回やモニタリング等での順守記録を確認 | AB91: Same issue from safety verification
C92: 3 | D92: KYT is conducted regularly and an annual KYT evaluation is conducted to improve the system. KYTは、定期的に実施されている。また、KYT評価は、仕組みの改善のために実施されている。 | E92: KY | F92: Integration 関連付け | G92: 88 | H92: Is KYT conducted periodically in accordance with SBU or/and site standard by everyone on site? KYTは、SBU/現場の標準で決められた頻度で実施されているか？ | I92: Production Foreman 製造主任 | M92: レ | V92: How often KYT is KYT conducted? どれくらいの頻度でKYTを実施していますか？ | X92: Review KYT execution records KYT実施記録を確認する。 | Y92: KYT records indicate that KYT is completed periodically in accordance with SBU and/or site standard by everyone on site. KYT記録によると、SBU/現場の標準で決められた頻度で、全員に実施されている。
C93: 3 | E93: KY | F93: Integration 関連付け | G93: 89 | H93: Is the KYT activity evaluated and opportunity for improvement discussed with the plant manager annually? 毎年、KYTの活動内容は、評価され、改善の機会を事業所長と議論されているか？ | I93: Safety Manager 安全担当課長 | S93: レ | V93: When was the last KYT activity review and what was the outcome of it? 直近で、いつKYT活動は見直されましたか？また、その（見直し）結果は何ですか？ | Y93: The KYT activity is evaluated and opportunity for improvement is discussed with the plant manager annually. KYT 活動は、毎年評価され、改善の機会を事業所長と議論されている。
C94: 3 | D94: A review of risk records shows that the majority of risks are covered by administrative and engineering technical controls. 大部分のリスクは、ハードおよびソフト対策によりカバーされていることが、リスク記録で確認できる。 | E94: Risk Assessment リスクアセスメント | F94: Design 設計 | G94: 90 | H94: Are all risks in the risk register covered by administrative or technical controls? Besides, are the remaining risks written in the work standard? 登録されたリスクカテゴリIII&IVの残留リスクに対し、ハード対策もしくは、ソフト対策が実施されていますか？また、残留リスクが作業標準に明記されていますか？ | I94: Production SV 製造職長 | N94: レ | X94: Review the risk record and work standard リスク記録および作業標準を確認する。 | Y94: There is at least one control prescribed for each risk identified. These controls are either administrative or technical by nature. The remaining risks are written in the work standard. 特定されたリスクに対するため、少なくとも１つの管理（ソフトもしくはハード対策）が存在する。また、残留リスクが作業標準内に明記されている。
C95: 3 | D95: All contractors receive H&S orientation/training prior to the work. The material includes emergency procedures, introduction to the Safety Mission Statement and Safety fundamental Activities. 協力会社の全従業員へ、作業開始前に安全教育/オリエンテーションが行われている。安全教育/オリエンテーション資料には、緊急時の手順および安全宣言・共通規定項目が含まれている。 | E95: Contractor management 協力会社の安全管理 | F95: Integration 関連付け | G95: 91 | H95: Do all contractor employees receive contractor H&S orientation/training prior to the start of the work? 協力会社の全従業員へ、作業開始前に安全教育/オリエンテーションを行っているか？ | I95: Safety Manager 安全担当課長 | S95: レ | V95: How orientation/training is conducted to contractors? どのような教育を協力会社へ行いますか？ | X95: Review the contractor H&S orientation/training material records. 協力会社へのオリエンテーション/安全教育記録を確認する。 | Y95: There are records that all contractors received H&S orientation/training from BS prior to the work. BSが、協力会社の全従業員へ、作業開始前に安全教育/オリエンテーションを行った記録がある。
C96: 3 | E96: Contractor management 協力会社の安全管理 | F96: Change & Emergency planning 変更管理 & 緊急事態準備 | G96: 92 | H96: Does the material of contractor H&S orientation/training includes emergency procedures, introduction to the Safety Mission Statement and Safety fundamental Activities? 協力会社への安全教育/オリエンテーションには、緊急時の手順および安全宣言・共通規定項目が含まれているか？ | I96: Safety Manager 安全担当課長 | S96: レ | V96: What items do contractor employees receive at the H&S orientation/training? 協力会社への安全教育/オリエンテーションの内容は何ですか？ | X96: Review the contractor H&S orientation/training material 協力会社へのオリエンテーション/安全教育資料を確認する。 | Y96: The material of contractor H&S orientation/training includes emergency procedures, introduction to the Safety Mission Statement and Safety fundamental Activities. 協力会社への安全教育/オリエンテーションには、緊急時の手順および安全宣言・共通規定項目が含まれていることを確認できる。
C97: 3 | D97: Large Tire Manual Handling Operation Procedure follows the Global Standard and teammates follow it accordingly. 大型タイヤ手動ハンドリング作業に関する標準は、グローバル標準に準拠しており、従業員はそれらを順守している。 | E97: Large Tire Manual Handling Operation 大型タイヤハンドリング作業 | F97: Integration 関連付け | G97: 93 | H97: Do employees follow proper procedure when manually handling large tires? 大型タイヤを手動ハンドリングする際に従業員は標準を順守しているか？ | I97: Teammate 技能員 | O97: レ | V97: What is the procedure to follow when executing Large Tire Manual Handling Operations? 大型タイヤ手動ハンドリング作業を実施する際に順守すべき手順は何か？ | Y97: The respondent can explain the procedure to follow when manually handling large tires. 回答者は、大型タイヤの手動ハンドリングを行う際に従うべき手順を説明できる。
C98: 3 | D98: Risk assessments are performed following the Global Ergonomics procedure for all identified Ergonomic hazards. 特定されたエルゴノミクス（腰痛等の疾病リスク）上の危険源に対して、グローバル標準に従いリスクアセスメントが実施されている。 | E98: Ergonomics エルゴノミクス | F98: Integration 関連付け | G98: 94 | H98: Are risk assessments for ergonomic hazards performed following the Global Ergonomics procedure? グローバル標準に従い、エルゴノミクス（腰痛等の疾病リスク）上の危険源に対しリスクアセスメントが実施されているか？ | I98: Production Manager 製造課長 | L98: レ | W98: Check in documentation that the risk assessments done for Ergonomic hazards are compliant with the Global Ergonomics procedure エルゴノミクス（腰痛等の疾病リスク）上の危険源に対してグローバル標準に沿ったリスクアセスメントが実施されていることを文書で確認する。 | X98: Procedure of the Ergonomic risks assessments must include all hazards identified, and the methods employed to reduce residual risks to an acceptable level. エルゴノミクス（腰痛等の疾病リスク）RAでは、特定された全ての危険源、残留リスクを受け入れ可能なリスクまで低減するための方法を含んでいる。あるいは、残留リスクが管理状態がAsである。 | Y98: Ergonomic Risk Assessments performed on site are compliant with the Global Ergonomics procedure, and countermeasures are being implemented for residual Ergonomic risks and their effectiveness are evaluated グローバル標準に準拠したエルゴノミクス（腰痛等の疾病リスク）RAが現場で実施されており、残存するリスクに対する対策が実施され、かつ、その有効性が評価されている。
C99: 3 | D99: Risk assessments are performed for all identified Chemical hazards according to Global Chemical Management procedure before they are approved to be used on site. There is a Hazard Communication Program (HCP) on site and required teammates are trained regularly to handle the specific chemical hazard types to which they may be exposed in their work area. Chemical air sampling protocol is in place for the site, and testing is done periodically. グローバル標準に従い、全ての化学物質に対して現場使用を承認される前に、リスクアセスメントが行われている。 現場では、危険源を周知する手順があり、化学物質を扱う必要のある従業員は、定期的に教育を受けている。 大気中の化学物質測定（作業環境測定）が定期的に行われている。 | E99: Chemical Management 化学物質管理 | F99: Integration 関連付け | G99: 95 | H99: Are risk assessments performed during the new chemical approval process for all identified chemical hazards? 全ての化学物質に対してリスクアセスメントが実施されているか？ | I99: Safety Manager / staff 安全または衛生担当課長、または担当部署 | S99: レ | V99: Check in documentation that risk assessments are completed for Chemical hazards and SDS in the local language are on site, and compliant with local regulations. 化学物質に対してリスクアセスメントが実施されており、現地の言語で記載されたSDSが現場にあり、現地の規制に準拠しているか、確認する。 | X99: Review risk assessments done for Chemical hazards, they must include SDS in the local language, content of restricted substances and presence of substances regulated by local authorities, associated hazards, and potential generation of hazardous decomposition byproducts as required by the Global Chemical Management procedure 化学物質の危険性に対するリスクアセスメントを確認し、グローバル標準に準拠しており、現地の言語で記載されたSDS、規制含有量、法規で制限される物質、関連する危険物、潜在的な分解副産物の情報が含まれていることを確認する。 | Y99: Risk assessments are completed for Chemical hazards and SDS in the local language are on site, and compliant with local regulations. 化学物質に対してリスクアセスメントが実施されており、現地の言語で記載されたSDSが現場にあり、現地の規制に準拠している。
C100: 3 | E100: Chemical Management 化学物質管理 | F100: Design 設計 | G100: 96 | H100: Is there a regular training and communication program on site for teammates exposed to chemical hazards? 化学物物質の危険源にさらされる従業員に対して、定期的な教育および現場でのコミュニケーション（周知）が実施されているか？ | I100: Safety Manager / staff 安全または衛生担当課長、または担当部署 | S100: レ | V100: How do you communicate and train teammates about Chemical hazards and how to reduce their exposure? 化学物質の危険性および暴露を低減に関し、どのように従業員に周知・教育しているか？ | X100: Review if training materials and communication tools indicate a transfer of knowledge regarding Chemical hazards to the people that require it. 教育資料およびコミュニケーションツールが、化学物質の危険性に関する知識を必要な人々に周知されていることを確認する。 | Y100: Training records or communication tools show that all relevant people within the site are aware of Chemical hazards and how to reduce their exposure 教育記録またはコミュニケーションツールにより、事業所内の全ての関係者が化学物質の危険性とその暴露を減らす方法を認識していることが分かる。
...

Sheet (Ref.)MA Dashboard
C3: G-SMS Maturity Assessment / 安全成熟度
C4: Site: | H4: G-SMS Maturity Assessment / 安全成熟度
C5: Date: | F5: 24-26 Mar.
C6: Assessment type/評価種類: | F6: Validation assessment 妥当性評価
C8: Summary Result of Safety Maturity Assessment 安全成熟度評価結果 サマリー
C10: Maturity Levels | F10: Safety Maturity Outcome / 安全成熟度 結果
F11: =(F15+L15)/2 -> 2.5 | G11: =IF(F11=0,"N/A",IF(F11<2,"Ad-Hoc",IF(F11<3,"Reactive",IF(F11<4,"Standardized",IF(F11<5,"Proactive",IF(F11=5,"Excellence","N/A")))))) -> Reactive
C12: 1 | D12: Ad-hoc
C14: 2 | D14: Reactive | F14: Safety Awareness ﾘｰﾀﾞｰ/一人ひとりの安全意識 | L14: System Implementation 安全ﾏﾈｼﾞﾒﾝﾄｼｽﾃﾑの運用度
F15: =(I19+F19)/2 -> 3 | G15: =IF(F15=0,"N/A",IF(F15<2,"Ad-Hoc",IF(F15<3,"Reactive",IF(F15<4,"Standardized",IF(F15<5,"Proactive",IF(F15=5,"Excellence","N/A")))))) -> Standardized | L15: =(L19+O19)/2 -> 2 | M15: =IF(L15=0,"N/A",IF(L15<2,"Ad-Hoc",IF(L15<3,"Reactive",IF(L15<4,"Standardized",IF(L15<5,"Proactive",IF(L15=5,"Excellence","N/A")))))) -> Reactive
C16: 3 | D16: Standardized
C18: 4 | D18: Proactive | F18: Leadership ﾘｰﾀﾞｰｼｯﾌﾟ | I18: Teammate Engagement 一人ひとり | L18: Organization 組織 | O18: System システム
F19: =IF(F23="Error","Error",(IF(F24="Error","Error",(IF(F25="Error","Error",MIN(F23:F25)))))) -> 4 | G19: =IF(F19=0,"N/A",IF(F19<2,"Ad-Hoc",IF(F19<3,"Reactive",IF(F19<4,"Standardized",IF(F19<5,"Proactive",IF(F19=5,"Excellence","N/A")))))) -> Proactive | I19: =IF(I23="Error","Error",(IF(I24="Error","Error",(IF(I25="Error","Error",MIN(I23:I25)))))) -> 2 | J19: =IF(I19=0,"N/A",IF(I19<2,"Ad-Hoc",IF(I19<3,"Reactive",IF(I19<4,"Standardized",IF(I19<5,"Proactive",IF(I19=5,"Excellence","N/A")))))) -> Reactive | L19: =IF(L23="Error","Error",(IF(L24="Error","Error",(IF(L25="Error","Error",MIN(L23:L25)))))) -> 2 | M19: =IF(L19=0,"N/A",IF(L19<2,"Ad-Hoc",IF(L19<3,"Reactive",IF(L19<4,"Standardized",IF(L19<5,"Proactive",IF(L19=5,"Excellence","N/A")))))) -> Reactive | O19: =IF(O23="Error","Error",(IF(O24="Error","Error",(IF(O25="Error","Error",MIN(O23:O25)))))) -> 2 | P19: =IF(O19=0,"N/A",IF(O19<2,"Ad-Hoc",IF(O19<3,"Reactive",IF(O19<4,"Standardized",IF(O19<5,"Proactive",IF(O19=5,"Excellence","N/A")))))) -> Reactive
C20: 5 | D20: Excellence
F22: Leadership Elements | I22: Teammate Engagement Elements | L22: Organization Elements | O22: System Elements
F23: ='2nd Cal (Leadership)'!Q10 -> 5 | G23: Prioritization 優先事項 | I23: ='2nd Cal (Teammate)'!K10 -> 2 | J23: Action 行動 | L23: ='2nd Cal (Organization)'!K10 -> 4 | M23: Participation 参画 | O23: ='2nd Cal (System)'!L10 -> 2 | P23: Design 設計
F24: ='2nd Cal (Leadership)'!W10 -> 4 | G24: Decision 意思決定 | I24: ='2nd Cal (Teammate)'!Q10 -> 3 | J24: Capability 能力 | L24: ='2nd Cal (Organization)'!Q10 -> 4 | M24: Information 情報 | O24: ='2nd Cal (System)'!R10 -> 2 | P24: Integration 統合
F25: ='2nd Cal (Leadership)'!K10 -> 5 | G25: Support 支援 | I25: ='2nd Cal (Teammate)'!W10 -> 5 | J25: Knowledge 知識 | L25: ='2nd Cal (Organization)'!W10 -> 2 | M25: Communication | O25: ='2nd Cal (System)'!X10 -> 2 | P25: Change & Emergency
C27: Output Visualization 成熟度の見える化
C29: Output Visualization 安全成熟度 | L29: Individual Process Results 規格の順守状況
F32: =F19 -> 4 | I32: =O19 -> 2
F43: =I19 -> 2 | I43: =L19 -> 2
C46: 4 Pillars | E46: Maturity level | G46: Strength 長所 | J46: Opportunity for Improvement 改善機会 | M46: Action items 実施事項 | P46: Due date 納期
C47: Leadership リーダーシップ | E47: =F19 -> 4 | G47: ▪ Encourage teammate by Positive approach e.g. reward recognition ▪ Make clear target & visualize to prevent similar issue e.g. improvement ratio of 3S check item, visualize patrol result atcommon area etc. ▪ Direct communicate with O/P onsite e.g.plant walk activity etc. | J47: There’s vision/expectation of long-term strategy. However, there’s no clear plan how to achieve plant’s vision from each section
C48: Teammate Engagement 一人ひとり | E48: =I19 -> 2 | G48: - | J48: Teammate don’t understand safety/DP risk e.g. check damaged F/L’s tire as OK, Missing ground wire/clamp, humidity check etc. and found non-compliance e.g. No use orange tag, not conduct KY & check before emergency maintenance etc. *Interview result: - If not do, they will get penalty - Safety told to do - They think that their work area is safe due to existed safety device e.g. fence, sensor etc.
C49: Organization 組織 | E49: =L19 -> 2 | G49: - | J49: 1. No confirm effectiveness of communication e.g. teammate didn’t understand detail of accident case. 2. Less aware/knowledge of safety/DP risk while patrol /monitoring (mostly found 3S issue) 3. Not understand importance of 4M change e.g. no design review of expansion project, Jib crane installation etc.
C50: System システム | E50: =O19 -> 2 | G50: - | J50: 1. Std. has existed and training, but lack of implement (integrate) onsite e.g. issue of 3S, LOTO, safety management for maintenance etc. 2. Not gather safety activity result to review & analyze for further enhancement as PDCA e.g. safety rule

Sheet (Ref.)MA Dashboard (DP_divide)
C3: G-SMS Maturity Assessment / 安全成熟度
C4: Site: | H4: G-SMS Maturity Assessment / 安全成熟度
C5: Date: | F5: 24-26 Mar.
C6: Assessment type/評価種類: | F6: Validation assessment 妥当性評価
C8: Summary Result of Safety Maturity Assessment 安全成熟度評価結果 サマリー
C10: Maturity Levels | F10: Safety Maturity Outcome / 安全成熟度 結果
F11: =(F15+N15)/2 -> 2.5 | G11: =IF(F11=0,"N/A",IF(F11<2,"Ad-Hoc",IF(F11<3,"Reactive",IF(F11<4,"Standardized",IF(F11<5,"Proactive",IF(F11=5,"Excellence","N/A")))))) -> Reactive
C12: 1 | D12: Ad-hoc
C14: 2 | D14: Reactive | F14: Safety Awareness ﾘｰﾀﾞｰ/一人ひとりの安全意識 | N14: System Implementation 安全ﾏﾈｼﾞﾒﾝﾄｼｽﾃﾑの運用度
F15: =(I19+F19)/2 -> 3 | G15: =IF(F15=0,"N/A",IF(F15<2,"Ad-Hoc",IF(F15<3,"Reactive",IF(F15<4,"Standardized",IF(F15<5,"Proactive",IF(F15=5,"Excellence","N/A")))))) -> Standardized | N15: =(N19+Q19)/2 -> 2 | O15: =IF(N15=0,"N/A",IF(N15<2,"Ad-Hoc",IF(N15<3,"Reactive",IF(N15<4,"Standardized",IF(N15<5,"Proactive",IF(N15=5,"Excellence","N/A")))))) -> Reactive
C16: 3 | D16: Standardized
C18: 4 | D18: Proactive | F18: Leadership ﾘｰﾀﾞｰｼｯﾌﾟ | I18: Teammate Engagement 一人ひとり | N18: Organization 組織 | Q18: System システム
F19: =IF(F23="Error","Error",(IF(F24="Error","Error",(IF(F25="Error","Error",MIN(F23:F25)))))) -> 4 | G19: =IF(F19=0,"N/A",IF(F19<2,"Ad-Hoc",IF(F19<3,"Reactive",IF(F19<4,"Standardized",IF(F19<5,"Proactive",IF(F19=5,"Excellence","N/A")))))) -> Proactive | I19: =IF(I23="Error","Error",(IF(I24="Error","Error",(IF(I25="Error","Error",MIN(I23:I25)))))) -> 2 | J19: =IF(I19=0,"N/A",IF(I19<2,"Ad-Hoc",IF(I19<3,"Reactive",IF(I19<4,"Standardized",IF(I19<5,"Proactive",IF(I19=5,"Excellence","N/A")))))) -> Reactive | N19: =IF(N23="Error","Error",(IF(N24="Error","Error",(IF(N25="Error","Error",MIN(N23:N25)))))) -> 2 | O19: =IF(N19=0,"N/A",IF(N19<2,"Ad-Hoc",IF(N19<3,"Reactive",IF(N19<4,"Standardized",IF(N19<5,"Proactive",IF(N19=5,"Excellence","N/A")))))) -> Reactive | Q19: =IF(Q23="Error","Error",(IF(Q24="Error","Error",(IF(Q25="Error","Error",MIN(Q23:Q25)))))) -> 2 | R19: =IF(Q19=0,"N/A",IF(Q19<2,"Ad-Hoc",IF(Q19<3,"Reactive",IF(Q19<4,"Standardized",IF(Q19<5,"Proactive",IF(Q19=5,"Excellence","N/A")))))) -> Reactive
C20: 5 | D20: Excellence
F22: Leadership Elements | I22: Teammate Engagement Elements | N22: Organization Elements | Q22: System Elements
F23: ='2nd Cal (Leadership)'!Q10 -> 5 | G23: Prioritization 優先事項 | I23: ='2nd Cal (Teammate)'!K10 -> 2 | J23: Action 行動 | N23: ='2nd Cal (Organization)'!K10 -> 4 | O23: Participation 参画 | Q23: ='2nd Cal (System)'!L10 -> 2 | R23: Design 設計
F24: ='2nd Cal (Leadership)'!W10 -> 4 | G24: Decision 意思決定 | I24: ='2nd Cal (Teammate)'!Q10 -> 3 | J24: Capability 能力 | N24: ='2nd Cal (Organization)'!Q10 -> 4 | O24: Information 情報 | Q24: ='2nd Cal (System)'!R10 -> 2 | R24: Integration 統合
F25: ='2nd Cal (Leadership)'!K10 -> 5 | G25: Support 支援 | I25: ='2nd Cal (Teammate)'!W10 -> 5 | J25: Knowledge 知識 | N25: ='2nd Cal (Organization)'!W10 -> 2 | O25: Communication | Q25: ='2nd Cal (System)'!X10 -> 2 | R25: Change & Emergency
C27: Output Visualization 成熟度の見える化
C29: Output Visualization 安全成熟度
F32: =F19 -> 4 | Q32: =Q19 -> 2
R34: =MIN('2nd Cal (System)'!L21,'2nd Cal (System)'!R21,'2nd Cal (System)'!X21) -> 2
R36: =MIN('2nd Cal (System)'!L31,'2nd Cal (System)'!R31,'2nd Cal (System)'!X31) -> 2
F43: =I19 -> 2 | Q43: =N19 -> 2
C46: System - Individual Process Results システムピラーにおける規格の順守状況
C48: Safety 安全 | L48: Disaster Prevention
C68: 4 Pillars | E68: Maturity level | G68: Strength 長所 | J68: Opportunity for Improvement 改善機会 | O68: Action items 実施事項 | R68: Due date 納期
C69: Leadership リーダーシップ | E69: =F19 -> 4 | G69: ▪ Encourage teammate by Positive approach e.g. reward recognition ▪ Make clear target & visualize to prevent similar issue e.g. improvement ratio of 3S check item, visualize patrol result atcommon area etc. ▪ Direct communicate with O/P onsite e.g.plant walk activity etc. | J69: There’s vision/expectation of long-term strategy. However, there’s no clear plan how to achieve plant’s vision from each sectionใ (Same as Safety)
C70: Teammate Engagement 一人ひとり | E70: =I19 -> 2 | J70: - The PIC was unable to identify and report issues related to the improper storage conditions of flammable materials during routine patrols, resulting in non-compliance with the required standards. - Misunderstanding of humidity level readings by the Mixing Operator indicated a lack of understanding or insufficient training regarding the procedures and requirements outlined in MUST11. Moreover, cannot detect abnormal by F/M
C71: Organization 組織 | E71: =N19 -> 2
C72: System システム | E72: =Q19 -> 2 | J72: Unclear area and DP equipment ownership responsibilities resulted in two fire extinguishers in the RM warehouse (P1 area) being overlooked during inspection, as found during the Genba.

Sheet Calculate Summary
B3: System Elements | C3: Design | D3: =IF('2nd Cal (System)'!$L$10="error",0,'2nd Cal (System)'!$L$10) -> 2
C4: Integration | D4: =IF('2nd Cal (System)'!$R$10="error",0,'2nd Cal (System)'!$R$10) -> 2
C5: Change & Emergency | D5: =IF('2nd Cal (System)'!$X$10="error",0,'2nd Cal (System)'!$X$10) -> 2
B7: Organization Elements | C7: Participation | D7: =IF('2nd Cal (Organization)'!$K$10="error",0,'2nd Cal (Organization)'!$K$10) -> 4
C8: Information | D8: =IF('2nd Cal (Organization)'!$Q$10="error",0,'2nd Cal (Organization)'!$Q$10) -> 4
C9: Communication | D9: =IF('2nd Cal (Organization)'!$W$10="error",0,'2nd Cal (Organization)'!$W$10) -> 2
B11: Teammate Engagement Elements | C11: Action | D11: =IF('2nd Cal (Teammate)'!$K$10="error",0,'2nd Cal (Teammate)'!$K$10) -> 2
C12: Capability | D12: =IF('2nd Cal (Teammate)'!$Q$10="error",0,'2nd Cal (Teammate)'!$Q$10) -> 3
C13: Knowledge | D13: =IF('2nd Cal (Teammate)'!$W$10="error",0,'2nd Cal (Teammate)'!$W$10) -> 5
B15: Leadership Elements | C15: Prioritization | D15: =IF('2nd Cal (Leadership)'!$K$10="error",0,'2nd Cal (Leadership)'!$K$10) -> 5
C16: Decision | D16: =IF('2nd Cal (Leadership)'!$Q$10="error",0,'2nd Cal (Leadership)'!$Q$10) -> 5
C17: Support | D17: =IF('2nd Cal (Leadership)'!$W$10="error",0,'2nd Cal (Leadership)'!$W$10) -> 4
D19: Score | E19: Individual Process Results
B20: System detail | C20: Safety communication | D20: ='2nd Cal (System)'!Z13 -> 3 | E20: ='2nd Cal (System)'!AD13 -> 0.77777778
C21: Incident Management | D21: ='2nd Cal (System)'!Z14 -> 5 | E21: ='2nd Cal (System)'!AD14 -> 1
C22: Management of Change | D22: ='2nd Cal (System)'!Z15 -> 2 | E22: ='2nd Cal (System)'!AD15 -> 0.5
C23: LOTO Standard | D23: ='2nd Cal (System)'!Z16 -> 2 | E23: ='2nd Cal (System)'!AD16 -> 0.72727273
C24: Safety Rules | D24: ='2nd Cal (System)'!Z17 -> 3 | E24: ='2nd Cal (System)'!AD17 -> 0.42857143
C25: Work at Height | D25: ='2nd Cal (System)'!Z18 -> 4 | E25: ='2nd Cal (System)'!AD18 -> 0.875
C26: Mobile Equipment | D26: ='2nd Cal (System)'!Z19 -> 2 | E26: ='2nd Cal (System)'!AD19 -> 0.42857143
C27: 3S | D27: ='2nd Cal (System)'!Z20 -> 2 | E27: ='2nd Cal (System)'!AD20 -> 0.6
C28: Crane and Hoist | D28: ='2nd Cal (System)'!Z21 -> 2 | E28: ='2nd Cal (System)'!AD21 -> 0.77777778
C29: KY | D29: ='2nd Cal (System)'!Z22 -> 3 | E29: ='2nd Cal (System)'!AD22 -> 0.66666667
C30: Risk Assessment | D30: ='2nd Cal (System)'!Z23 -> 4 | E30: ='2nd Cal (System)'!AD23 -> 0.875
C31: Contractor management | D31: ='2nd Cal (System)'!Z24 -> 3 | E31: ='2nd Cal (System)'!AD24 -> 0.85714286
C32: Large Tire Manual Handling Operation | D32: ='2nd Cal (System)'!Z25 -> 1 | E32: ='2nd Cal (System)'!AD25 -> #DIV/0!
... C42: Electric system | D42: ='2nd Cal (System)'!Z35 -> 3 | E42: ='2nd Cal (System)'!AD35 -> 0.6

Sheet 2nd Cal (Leadership)
F2: Count
A3: Leadership | G3: Prioritization 優先付け | H3: Prioritization 優先付け | I3: Prioritization 優先付け | J3: Prioritization 優先付け | K3: Prioritization 優先付け | M3: Decisions 意思決定 | N3: Decisions 意思決定 | O3: Decisions 意思決定 | P3: Decisions 意思決定 | Q3: Decisions 意思決定 | S3: Support 支援 | T3: Support 支援 | U3: Support 支援 | V3: Support 支援 | W3: Support 支援
A4: Level | B4: Element | C4: No. | D4: Judgement | F4: Level | G4: Yes | H4: No | I4: N/A | J4: Not rolled out yet | K4: Judgement | L4: Level | M4: Yes | N4: No | O4: N/A | P4: Not rolled out yet | Q4: Judgement | R4: Level | S4: Yes | T4: No | U4: N/A | V4: Not rolled out yet | W4: Judgement
A5: ='Leadership Checklist'!C3 -> 1 | B5: ='Leadership Checklist'!E3 -> Support 支援 | C5: ='Leadership Checklist'!F3 -> 1 | D5: ='Leadership Checklist'!Y3 -> Yes | F5: 1 | G5: =COUNTIFS($A$5:$A$200,$F5,$B$5:$B$200,G$3,$D$5:$D$200,G$4) -> 2 | H5: =COUNTIFS($A$5:$A$200,$F5,$B$5:$B$200,H$3,$D$5:$D$200,H$4) -> 0 | I5: =COUNTIFS($A$5:$A$200,$F5,$B$5:$B$200,I$3,$D$5:$D$200,I$4) -> 0 | J5: =COUNTIFS($A$5:$A$200,$F5,$B$5:$B$200,J$3,$D$5:$D$200,J$4) -> 0 | K5: =IF(SUM(G5:J5)=0,"",IF(H5>0,F5,"")) | L5: 1 | M5: =COUNTIFS($A$5:$A$200,$F5,$B$5:$B$200,M$3,$D$5:$D$200,M$4) -> 1 | N5: =COUNTIFS($A$5:$A$200,$F5,$B$5:$B$200,N$3,$D$5:$D$200,N$4) -> 0 | O5: =COUNTIFS($A$5:$A$200,$F5,$B$5:$B$200,O$3,$D$5:$D$200,O$4) -> 0 | P5: =COUNTIFS($A$5:$A$200,$F5,$B$5:$B$200,P$3,$D$5:$D$200,P$4) -> 0 | Q5: =IF(SUM(M5:P5)=0,"",IF(N5>0,L5,"")) | R5: 1 | S5: =COUNTIFS($A$5:$A$200,$F5,$B$5:$B$200,S$3,$D$5:$D$200,S$4) -> 2 | T5: =COUNTIFS($A$5:$A$200,$F5,$B$5:$B$200,T$3,$D$5:$D$200,T$4) -> 0 | U5: =COUNTIFS($A$5:$A$200,$F5,$B$5:$B$200,U$3,$D$5:$D$200,U$4) -> 0 | V5: =COUNTIFS($A$5:$A$200,$F5,$B$5:$B$200,V$3,$D$5:$D$200,V$4) -> 0 | W5: =IF(SUM(S5:V5)=0,"",IF(T5>0,R5,""))
A6: ='Leadership Checklist'!C4 -> 1 | B6: ='Leadership Checklist'!E4 -> Prioritization 優先付け | C6: ='Leadership Checklist'!F4 -> 2 | D6: ='Leadership Checklist'!Y4 -> Yes | F6: 2 | G6: =COUNTIFS($A$5:$A$200,$F6,$B$5:$B$200,G$3,$D$5:$D$200,G$4) -> 3 | H6: =COUNTIFS($A$5:$A$200,$F6,$B$5:$B$200,H$3,$D$5:$D$200,H$4) -> 0 | I6: =COUNTIFS($A$5:$A$200,$F6,$B$5:$B$200,I$3,$D$5:$D$200,I$4) -> 0 | J6: =COUNTIFS($A$5:$A$200,$F6,$B$5:$B$200,J$3,$D$5:$D$200,J$4) -> 0 | K6: =IF(SUM(G6:J6)=0,"",IF(SUM(H5)>0,"",IF(H6>0,F6-1,IF(SUM(G7:J9)>0,"",F6)))) | L6: 2 | M6: =COUNTIFS($A$5:$A$200,$F6,$B$5:$B$200,M$3,$D$5:$D$200,M$4) -> 1 | N6: =COUNTIFS($A$5:$A$200,$F6,$B$5:$B$200,N$3,$D$5:$D$200,N$4) -> 0 | O6: =COUNTIFS($A$5:$A$200,$F6,$B$5:$B$200,O$3,$D$5:$D$200,O$4) -> 0 | P6: =COUNTIFS($A$5:$A$200,$F6,$B$5:$B$200,P$3,$D$5:$D$200,P$4) -> 0 | Q6: =IF(SUM(M6:P6)=0,"",IF(SUM(N5)>0,"",IF(N6>0,L6-1,IF(SUM(M7:P9)>0,"",L6)))) | R6: 2 | S6: =COUNTIFS($A$5:$A$200,$F6,$B$5:$B$200,S$3,$D$5:$D$200,S$4) -> 1 | T6: =COUNTIFS($A$5:$A$200,$F6,$B$5:$B$200,T$3,$D$5:$D$200,T$4) -> 0 | U6: =COUNTIFS($A$5:$A$200,$F6,$B$5:$B$200,U$3,$D$5:$D$200,U$4) -> 0 | V6: =COUNTIFS($A$5:$A$200,$F6,$B$5:$B$200,V$3,$D$5:$D$200,V$4) -> 0 | W6: =IF(SUM(S6:V6)=0,"",IF(SUM(T5)>0,"",IF(T6>0,R6-1,IF(SUM(S7:V9)>0,"",R6))))
A7: ='Leadership Checklist'!C5 -> 1 | B7: ='Leadership Checklist'!E5 -> Prioritization 優先付け | C7: ='Leadership Checklist'!F5 -> 3 | D7: ='Leadership Checklist'!Y5 -> Yes | F7: 3 | G7: =COUNTIFS($A$5:$A$200,$F7,$B$5:$B$200,G$3,$D$5:$D$200,G$4) -> 1 | H7: =COUNTIFS($A$5:$A$200,$F7,$B$5:$B$200,H$3,$D$5:$D$200,H$4) -> 0 | I7: =COUNTIFS($A$5:$A$200,$F7,$B$5:$B$200,I$3,$D$5:$D$200,I$4) -> 0 | J7: =COUNTIFS($A$5:$A$200,$F7,$B$5:$B$200,J$3,$D$5:$D$200,J$4) -> 0 | K7: =IF(SUM(G7:J7)=0,"",IF(SUM(H5:H6)>0,"",IF(H7>0,F7-1,IF(SUM(G8:J9)>0,"",F7)))) | L7: 3 | M7: =COUNTIFS($A$5:$A$200,$F7,$B$5:$B$200,M$3,$D$5:$D$200,M$4) -> 2 | N7: =COUNTIFS($A$5:$A$200,$F7,$B$5:$B$200,N$3,$D$5:$D$200,N$4) -> 0 | O7: =COUNTIFS($A$5:$A$200,$F7,$B$5:$B$200,O$3,$D$5:$D$200,O$4) -> 0 | P7: =COUNTIFS($A$5:$A$200,$F7,$B$5:$B$200,P$3,$D$5:$D$200,P$4) -> 0 | Q7: =IF(SUM(M7:P7)=0,"",IF(SUM(N5:N6)>0,"",IF(N7>0,L7-1,IF(SUM(M8:P9)>0,"",L7)))) | R7: 3 | S7: =COUNTIFS($A$5:$A$200,$F7,$B$5:$B$200,S$3,$D$5:$D$200,S$4) -> 2 | T7: =COUNTIFS($A$5:$A$200,$F7,$B$5:$B$200,T$3,$D$5:$D$200,T$4) -> 0 | U7: =COUNTIFS($A$5:$A$200,$F7,$B$5:$B$200,U$3,$D$5:$D$200,U$4) -> 0 | V7: =COUNTIFS($A$5:$A$200,$F7,$B$5:$B$200,V$3,$D$5:$D$200,V$4) -> 0 | W7: =IF(SUM(S7:V7)=0,"",IF(SUM(T5:T6)>0,"",IF(T7>0,R7-1,IF(SUM(S8:V9)>0,"",R7))))
A8: ='Leadership Checklist'!C6 -> 1 | B8: ='Leadership Checklist'!E6 -> Decisions 意思決定 | C8: ='Leadership Checklist'!F6 -> 4 | D8: ='Leadership Checklist'!Y6 -> Yes | F8: 4 | G8: =COUNTIFS($A$5:$A$200,$F8,$B$5:$B$200,G$3,$D$5:$D$200,G$4) -> 3 | H8: =COUNTIFS($A$5:$A$200,$F8,$B$5:$B$200,H$3,$D$5:$D$200,H$4) -> 0 | I8: =COUNTIFS($A$5:$A$200,$F8,$B$5:$B$200,I$3,$D$5:$D$200,I$4) -> 0 | J8: =COUNTIFS($A$5:$A$200,$F8,$B$5:$B$200,J$3,$D$5:$D$200,J$4) -> 0 | K8: =IF(SUM(G8:J8)=0,"",IF(SUM(H5:H7)>0,"",IF(H8>0,F8-1,IF(SUM(G9:J9)>0,"",F8)))) | L8: 4 | M8: =COUNTIFS($A$5:$A$200,$F8,$B$5:$B$200,M$3,$D$5:$D$200,M$4) -> 1 | N8: =COUNTIFS($A$5:$A$200,$F8,$B$5:$B$200,N$3,$D$5:$D$200,N$4) -> 0 | O8: =COUNTIFS($A$5:$A$200,$F8,$B$5:$B$200,O$3,$D$5:$D$200,O$4) -> 0 | P8: =COUNTIFS($A$5:$A$200,$F8,$B$5:$B$200,P$3,$D$5:$D$200,P$4) -> 0 | Q8: =IF(SUM(M8:P8)=0,"",IF(SUM(N5:N7)>0,"",IF(N8>0,L8-1,IF(SUM(M9:P9)>0,"",L8)))) | R8: 4 | S8: =COUNTIFS($A$5:$A$200,$F8,$B$5:$B$200,S$3,$D$5:$D$200,S$4) -> 2 | T8: =COUNTIFS($A$5:$A$200,$F8,$B$5:$B$200,T$3,$D$5:$D$200,T$4) -> 0 | U8: =COUNTIFS($A$5:$A$200,$F8,$B$5:$B$200,U$3,$D$5:$D$200,U$4) -> 0 | V8: =COUNTIFS($A$5:$A$200,$F8,$B$5:$B$200,V$3,$D$5:$D$200,V$4) -> 0 | W8: =IF(SUM(S8:V8)=0,"",IF(SUM(T5:T7)>0,"",IF(T8>0,R8-1,IF(SUM(S9:V9)>0,"",R8))))
A9: ='Leadership Checklist'!C7 -> 1 | B9: ='Leadership Checklist'!E7 -> Support 支援 | C9: ='Leadership Checklist'!F7 -> 5 | D9: ='Leadership Checklist'!Y7 -> Yes | F9: 5 | G9: =COUNTIFS($A$5:$A$200,$F9,$B$5:$B$200,G$3,$D$5:$D$200,G$4) -> 1 | H9: =COUNTIFS($A$5:$A$200,$F9,$B$5:$B$200,H$3,$D$5:$D$200,H$4) -> 0 | I9: =COUNTIFS($A$5:$A$200,$F9,$B$5:$B$200,I$3,$D$5:$D$200,I$4) -> 0 | J9: =COUNTIFS($A$5:$A$200,$F9,$B$5:$B$200,J$3,$D$5:$D$200,J$4) -> 0 | K9: =IF(SUM(G9:J9)=0,"",IF(SUM(H5:H8)>0,"",IF(H9>0,IF(SUM(G8:J8)=0,IF(SUM(G7:J7)=0,IF(SUM(G6:J6)=0,IF(SUM(G5:J5)=0,F5),F6),F7),F8),F9))) -> 5 | L9: 5 | M9: =COUNTIFS($A$5:$A$200,$F9,$B$5:$B$200,M$3,$D$5:$D$200,M$4) -> 1 | N9: =COUNTIFS($A$5:$A$200,$F9,$B$5:$B$200,N$3,$D$5:$D$200,N$4) -> 0 | O9: =COUNTIFS($A$5:$A$200,$F9,$B$5:$B$200,O$3,$D$5:$D$200,O$4) -> 0 | P9: =COUNTIFS($A$5:$A$200,$F9,$B$5:$B$200,P$3,$D$5:$D$200,P$4) -> 0 | Q9: =IF(SUM(M9:P9)=0,"",IF(SUM(N5:N8)>0,"",IF(N9>0,IF(SUM(M8:P8)=0,IF(SUM(M7:P7)=0,IF(SUM(M6:P6)=0,IF(SUM(M5:P5)=0,L5),L6),L7),L8),L9))) -> 5 | R9: 5 | S9: =COUNTIFS($A$5:$A$200,$F9,$B$5:$B$200,S$3,$D$5:$D$200,S$4) -> 1 | T9: =COUNTIFS($A$5:$A$200,$F9,$B$5:$B$200,T$3,$D$5:$D$200,T$4) -> 2 | U9: =COUNTIFS($A$5:$A$200,$F9,$B$5:$B$200,U$3,$D$5:$D$200,U$4) -> 0 | V9: =COUNTIFS($A$5:$A$200,$F9,$B$5:$B$200,V$3,$D$5:$D$200,V$4) -> 0 | W9: =IF(SUM(S9:V9)=0,"",IF(SUM(T5:T8)>0,"",IF(T9>0,IF(SUM(S8:V8)=0,IF(SUM(S7:V7)=0,IF(SUM(S6:V6)=0,IF(SUM(S5:V5)=0,R5),R6),R7),R8),R9))) -> 4
A10: ='Leadership Checklist'!C8 -> 1 | B10: ='Leadership Checklist'!E8 -> 0 | C10: ='Leadership Checklist'!F8 -> 0 | D10: ='Leadership Checklist'!Y8 -> 0 | F10: Sum | G10: =SUM(G5:G9) -> 10 | H10: =SUM(H5:H9) -> 0 | I10: =SUM(I5:I9) -> 0 | J10: =SUM(J5:J9) -> 0 | K10: =IF(COUNTIF($B5:$B200,K$3)=SUM(G10:J10),MIN(K5:K9),"Error") -> 5 | L10: Sum | M10: =SUM(M5:M9) -> 6 | N10: =SUM(N5:N9) -> 0 | O10: =SUM(O5:O9) -> 0 | P10: =SUM(P5:P9) -> 0 | Q10: =IF(COUNTIF($B5:$B200,Q$3)=SUM(M10:P10),MIN(Q5:Q9),"Error") -> 5 | R10: Sum | S10: =SUM(S5:S9) -> 8 | T10: =SUM(T5:T9) -> 2 | U10: =SUM(U5:U9) -> 0 | V10: =SUM(V5:V9) -> 0 | W10: =IF(COUNTIF($B5:$B200,W$3)=SUM(S10:V10),MIN(W5:W9),"Error") -> 4
A11: ='Leadership Checklist'!C9 -> 2 | B11: ='Leadership Checklist'!E9 -> Support 支援 | C11: ='Leadership Checklist'!F9 -> 6 | D11: ='Leadership Checklist'!Y9 -> Yes
A12: ='Leadership Checklist'!C10 -> 2 | B12: ='Leadership Checklist'!E10 -> Prioritization 優先付け | C12: ='Leadership Checklist'!F10 -> 7 | D12: ='Leadership Checklist'!Y10 -> Yes
A13: ='Leadership Checklist'!C11 -> 2 | B13: ='Leadership Checklist'!E11 -> Prioritization 優先付け | C13: ='Leadership Checklist'!F11 -> 8 | D13: ='Leadership Checklist'!Y11 -> Yes
A14: ='Leadership Checklist'!C12 -> 2 | B14: ='Leadership Checklist'!E12 -> Prioritization 優先付け | C14: ='Leadership Checklist'!F12 -> 9 | D14: ='Leadership Checklist'!Y12 -> Yes
A15: ='Leadership Checklist'!C13 -> 2 | B15: ='Leadership Checklist'!E13 -> Decisions 意思決定 | C15: ='Leadership Checklist'!F13 -> 10 | D15: ='Leadership Checklist'!Y13 -> Yes
A16: ='Leadership Checklist'!C14 -> 2 | B16: ='Leadership Checklist'!E14 -> 0 | C16: ='Leadership Checklist'!F14 -> 0 | D16: ='Leadership Checklist'!Y14 -> 0
A17: ='Leadership Checklist'!C15 -> 3 | B17: ='Leadership Checklist'!E15 -> Support 支援 | C17: ='Leadership Checklist'!F15 -> 11 | D17: ='Leadership Checklist'!Y15 -> Yes
A18: ='Leadership Checklist'!C16 -> 3 | B18: ='Leadership Checklist'!E16 -> Support 支援 | C18: ='Leadership Checklist'!F16 -> 12 | D18: ='Leadership Checklist'!Y16 -> Yes
A19: ='Leadership Checklist'!C17 -> 3 | B19: ='Leadership Checklist'!E17 -> Decisions 意思決定 | C19: ='Leadership Checklist'!F17 -> 13 | D19: ='Leadership Checklist'!Y17 -> Yes
A20: ='Leadership Checklist'!C18 -> 3 | B20: ='Leadership Checklist'!E18 -> Decisions 意思決定 | C20: ='Leadership Checklist'!F18 -> 14 | D20: ='Leadership Checklist'!Y18 -> Yes
A21: ='Leadership Checklist'!C19 -> 3 | B21: ='Leadership Checklist'!E19 -> Prioritization 優先付け | C21: ='Leadership Checklist'!F19 -> 15 | D21: ='Leadership Checklist'!Y19 -> Yes
A22: ='Leadership Checklist'!C20 -> 3 | B22: ='Leadership Checklist'!E20 -> 0 | C22: ='Leadership Checklist'!F20 -> 0 | D22: ='Leadership Checklist'!Y20 -> 0
... A200: ='Leadership Checklist'!C198 -> 0 | B200: ='Leadership Checklist'!E198 -> 0 | C200: ='Leadership Checklist'!F198 -> 0 | D200: ='Leadership Checklist'!Y198 -> 0

Sheet 2nd Cal (Teammate)
F2: Count
A3: Teammate | G3: Action 行動 | H3: Action 行動 | I3: Action 行動 | J3: Action 行動 | K3: Action 行動 | M3: Capability 能力 | N3: Capability 能力 | O3: Capability 能力 | P3: Capability 能力 | Q3: Capability 能力 | S3: Knowledge 知識 | T3: Knowledge 知識 | U3: Knowledge 知識 | V3: Knowledge 知識 | W3: Knowledge 知識
A4: Level | B4: Element | C4: No. | D4: Judgement | F4: Level | G4: Yes | H4: No | I4: N/A | J4: Not rolled out yet | K4: Judgement | L4: Level | M4: Yes | N4: No | O4: N/A | P4: Not rolled out yet | Q4: Judgement | R4: Level | S4: Yes | T4: No | U4: N/A | V4: Not rolled out yet | W4: Judgement
A5: ='Teammate Engagement Checklist'!C3 -> 1 | B5: ='Teammate Engagement Checklist'!E3 -> Capability 能力 | C5: ='Teammate Engagement Checklist'!F3 -> 1 | D5: ='Teammate Engagement Checklist'!Y3 -> Yes | F5: 1 | G5: =COUNTIFS($A$5:$A$200,$F5,$B$5:$B$200,G$3,$D$5:$D$200,G$4) -> 1 | H5: =COUNTIFS($A$5:$A$200,$F5,$B$5:$B$200,H$3,$D$5:$D$200,H$4) -> 0 | I5: =COUNTIFS($A$5:$A$200,$F5,$B$5:$B$200,I$3,$D$5:$D$200,I$4) -> 0 | J5: =COUNTIFS($A$5:$A$200,$F5,$B$5:$B$200,J$3,$D$5:$D$200,J$4) -> 0 | K5: =IF(SUM(G5:J5)=0,"",IF(H5>0,F5,"")) | L5: 1 | M5: =COUNTIFS($A$5:$A$200,$F5,$B$5:$B$200,M$3,$D$5:$D$200,M$4) -> 2 | N5: =COUNTIFS($A$5:$A$200,$F5,$B$5:$B$200,N$3,$D$5:$D$200,N$4) -> 0 | O5: =COUNTIFS($A$5:$A$200,$F5,$B$5:$B$200,O$3,$D$5:$D$200,O$4) -> 0 | P5: =COUNTIFS($A$5:$A$200,$F5,$B$5:$B$200,P$3,$D$5:$D$200,P$4) -> 0 | Q5: =IF(SUM(M5:P5)=0,"",IF(N5>0,L5,"")) | R5: 1 | S5: =COUNTIFS($A$5:$A$200,$F5,$B$5:$B$200,S$3,$D$5:$D$200,S$4) -> 1 | T5: =COUNTIFS($A$5:$A$200,$F5,$B$5:$B$200,T$3,$D$5:$D$200,T$4) -> 0 | U5: =COUNTIFS($A$5:$A$200,$F5,$B$5:$B$200,U$3,$D$5:$D$200,U$4) -> 0 | V5: =COUNTIFS($A$5:$A$200,$F5,$B$5:$B$200,V$3,$D$5:$D$200,V$4) -> 0 | W5: =IF(SUM(S5:V5)=0,"",IF(T5>0,R5,""))
A6: ='Teammate Engagement Checklist'!C4 -> 1 | B6: ='Teammate Engagement Checklist'!E4 -> Action 行動 | C6: ='Teammate Engagement Checklist'!F4 -> 2 | D6: ='Teammate Engagement Checklist'!Y4 -> Yes | F6: 2 | G6: =COUNTIFS($A$5:$A$200,$F6,$B$5:$B$200,G$3,$D$5:$D$200,G$4) -> 1 | H6: =COUNTIFS($A$5:$A$200,$F6,$B$5:$B$200,H$3,$D$5:$D$200,H$4) -> 0 | I6: =COUNTIFS($A$5:$A$200,$F6,$B$5:$B$200,I$3,$D$5:$D$200,I$4) -> 0 | J6: =COUNTIFS($A$5:$A$200,$F6,$B$5:$B$200,J$3,$D$5:$D$200,J$4) -> 0 | K6: =IF(SUM(G6:J6)=0,"",IF(SUM(H5)>0,"",IF(H6>0,F6-1,IF(SUM(G7:J9)>0,"",F6)))) | L6: 2 | M6: =COUNTIFS($A$5:$A$200,$F6,$B$5:$B$200,M$3,$D$5:$D$200,M$4) -> 1 | N6: =COUNTIFS($A$5:$A$200,$F6,$B$5:$B$200,N$3,$D$5:$D$200,N$4) -> 0 | O6: =COUNTIFS($A$5:$A$200,$F6,$B$5:$B$200,O$3,$D$5:$D$200,O$4) -> 0 | P6: =COUNTIFS($A$5:$A$200,$F6,$B$5:$B$200,P$3,$D$5:$D$200,P$4) -> 0 | Q6: =IF(SUM(M6:P6)=0,"",IF(SUM(N5)>0,"",IF(N6>0,L6-1,IF(SUM(M7:P9)>0,"",L6)))) | R6: 2 | S6: =COUNTIFS($A$5:$A$200,$F6,$B$5:$B$200,S$3,$D$5:$D$200,S$4) -> 1 | T6: =COUNTIFS($A$5:$A$200,$F6,$B$5:$B$200,T$3,$D$5:$D$200,T$4) -> 0 | U6: =COUNTIFS($A$5:$A$200,$F6,$B$5:$B$200,U$3,$D$5:$D$200,U$4) -> 0 | V6: =COUNTIFS($A$5:$A$200,$F6,$B$5:$B$200,V$3,$D$5:$D$200,V$4) -> 0 | W6: =IF(SUM(S6:V6)=0,"",IF(SUM(T5)>0,"",IF(T6>0,R6-1,IF(SUM(S7:V9)>0,"",R6))))
A7: ='Teammate Engagement Checklist'!C5 -> 1 | B7: ='Teammate Engagement Checklist'!E5 -> Capability 能力 | C7: ='Teammate Engagement Checklist'!F5 -> 3 | D7: ='Teammate Engagement Checklist'!Y5 -> Yes | F7: 3 | G7: =COUNTIFS($A$5:$A$200,$F7,$B$5:$B$200,G$3,$D$5:$D$200,G$4) -> 0 | H7: =COUNTIFS($A$5:$A$200,$F7,$B$5:$B$200,H$3,$D$5:$D$200,H$4) -> 1 | I7: =COUNTIFS($A$5:$A$200,$F7,$B$5:$B$200,I$3,$D$5:$D$200,I$4) -> 0 | J7: =COUNTIFS($A$5:$A$200,$F7,$B$5:$B$200,J$3,$D$5:$D$200,J$4) -> 0 | K7: =IF(SUM(G7:J7)=0,"",IF(SUM(H5:H6)>0,"",IF(H7>0,F7-1,IF(SUM(G8:J9)>0,"",F7)))) -> 2 | L7: 3 | M7: =COUNTIFS($A$5:$A$200,$F7,$B$5:$B$200,M$3,$D$5:$D$200,M$4) -> 1 | N7: =COUNTIFS($A$5:$A$200,$F7,$B$5:$B$200,N$3,$D$5:$D$200,N$4) -> 0 | O7: =COUNTIFS($A$5:$A$200,$F7,$B$5:$B$200,O$3,$D$5:$D$200,O$4) -> 0 | P7: =COUNTIFS($A$5:$A$200,$F7,$B$5:$B$200,P$3,$D$5:$D$200,P$4) -> 0 | Q7: =IF(SUM(M7:P7)=0,"",IF(SUM(N5:N6)>0,"",IF(N7>0,L7-1,IF(SUM(M8:P9)>0,"",L7)))) | R7: 3 | S7: =COUNTIFS($A$5:$A$200,$F7,$B$5:$B$200,S$3,$D$5:$D$200,S$4) -> 1 | T7: =COUNTIFS($A$5:$A$200,$F7,$B$5:$B$200,T$3,$D$5:$D$200,T$4) -> 0 | U7: =COUNTIFS($A$5:$A$200,$F7,$B$5:$B$200,U$3,$D$5:$D$200,U$4) -> 0 | V7: =COUNTIFS($A$5:$A$200,$F7,$B$5:$B$200,V$3,$D$5:$D$200,V$4) -> 0 | W7: =IF(SUM(S7:V7)=0,"",IF(SUM(T5:T6)>0,"",IF(T7>0,R7-1,IF(SUM(S8:V9)>0,"",R7))))
A8: ='Teammate Engagement Checklist'!C6 -> 1 | B8: ='Teammate Engagement Checklist'!E6 -> Knowledge 知識 | C8: ='Teammate Engagement Checklist'!F6 -> 4 | D8: ='Teammate Engagement Checklist'!Y6 -> Yes | F8: 4 | G8: =COUNTIFS($A$5:$A$200,$F8,$B$5:$B$200,G$3,$D$5:$D$200,G$4) -> 2 | H8: =COUNTIFS($A$5:$A$200,$F8,$B$5:$B$200,H$3,$D$5:$D$200,H$4) -> 0 | I8: =COUNTIFS($A$5:$A$200,$F8,$B$5:$B$200,I$3,$D$5:$D$200,I$4) -> 0 | J8: =COUNTIFS($A$5:$A$200,$F8,$B$5:$B$200,J$3,$D$5:$D$200,J$4) -> 0 | K8: =IF(SUM(G8:J8)=0,"",IF(SUM(H5:H7)>0,"",IF(H8>0,F8-1,IF(SUM(G9:J9)>0,"",F8)))) | L8: 4 | M8: =COUNTIFS($A$5:$A$200,$F8,$B$5:$B$200,M$3,$D$5:$D$200,M$4) -> 1 | N8: =COUNTIFS($A$5:$A$200,$F8,$B$5:$B$200,N$3,$D$5:$D$200,N$4) -> 2 | O8: =COUNTIFS($A$5:$A$200,$F8,$B$5:$B$200,O$3,$D$5:$D$200,O$4) -> 0 | P8: =COUNTIFS($A$5:$A$200,$F8,$B$5:$B$200,P$3,$D$5:$D$200,P$4) -> 0 | Q8: =IF(SUM(M8:P8)=0,"",IF(SUM(N5:N7)>0,"",IF(N8>0,L8-1,IF(SUM(M9:P9)>0,"",L8)))) -> 3 | R8: 4 | S8: =COUNTIFS($A$5:$A$200,$F8,$B$5:$B$200,S$3,$D$5:$D$200,S$4) -> 1 | T8: =COUNTIFS($A$5:$A$200,$F8,$B$5:$B$200,T$3,$D$5:$D$200,T$4) -> 0 | U8: =COUNTIFS($A$5:$A$200,$F8,$B$5:$B$200,U$3,$D$5:$D$200,U$4) -> 0 | V8: =COUNTIFS($A$5:$A$200,$F8,$B$5:$B$200,V$3,$D$5:$D$200,V$4) -> 0 | W8: =IF(SUM(S8:V8)=0,"",IF(SUM(T5:T7)>0,"",IF(T8>0,R8-1,IF(SUM(S9:V9)>0,"",R8))))
A9: ='Teammate Engagement Checklist'!C7 -> 1 | B9: ='Teammate Engagement Checklist'!E7 -> 0 | C9: ='Teammate Engagement Checklist'!F7 -> 0 | D9: ='Teammate Engagement Checklist'!Y7 -> 0 | F9: 5 | G9: =COUNTIFS($A$5:$A$200,$F9,$B$5:$B$200,G$3,$D$5:$D$200,G$4) -> 0 | H9: =COUNTIFS($A$5:$A$200,$F9,$B$5:$B$200,H$3,$D$5:$D$200,H$4) -> 1 | I9: =COUNTIFS($A$5:$A$200,$F9,$B$5:$B$200,I$3,$D$5:$D$200,I$4) -> 0 | J9: =COUNTIFS($A$5:$A$200,$F9,$B$5:$B$200,J$3,$D$5:$D$200,J$4) -> 0 | K9: =IF(SUM(G9:J9)=0,"",IF(SUM(H5:H8)>0,"",IF(H9>0,IF(SUM(G8:J8)=0,IF(SUM(G7:J7)=0,IF(SUM(G6:J6)=0,IF(SUM(G5:J5)=0,F5),F6),F7),F8),F9))) | L9: 5 | M9: =COUNTIFS($A$5:$A$200,$F9,$B$5:$B$200,M$3,$D$5:$D$200,M$4) -> 0 | N9: =COUNTIFS($A$5:$A$200,$F9,$B$5:$B$200,N$3,$D$5:$D$200,N$4) -> 1 | O9: =COUNTIFS($A$5:$A$200,$F9,$B$5:$B$200,O$3,$D$5:$D$200,O$4) -> 0 | P9: =COUNTIFS($A$5:$A$200,$F9,$B$5:$B$200,P$3,$D$5:$D$200,P$4) -> 0 | Q9: =IF(SUM(M9:P9)=0,"",IF(SUM(N5:N8)>0,"",IF(N9>0,IF(SUM(M8:P8)=0,IF(SUM(M7:P7)=0,IF(SUM(M6:P6)=0,IF(SUM(M5:P5)=0,L5),L6),L7),L8),L9))) | R9: 5 | S9: =COUNTIFS($A$5:$A$200,$F9,$B$5:$B$200,S$3,$D$5:$D$200,S$4) -> 2 | T9: =COUNTIFS($A$5:$A$200,$F9,$B$5:$B$200,T$3,$D$5:$D$200,T$4) -> 0 | U9: =COUNTIFS($A$5:$A$200,$F9,$B$5:$B$200,U$3,$D$5:$D$200,U$4) -> 0 | V9: =COUNTIFS($A$5:$A$200,$F9,$B$5:$B$200,V$3,$D$5:$D$200,V$4) -> 0 | W9: =IF(SUM(S9:V9)=0,"",IF(SUM(T5:T8)>0,"",IF(T9>0,IF(SUM(S8:V8)=0,IF(SUM(S7:V7)=0,IF(SUM(S6:V6)=0,IF(SUM(S5:V5)=0,R5),R6),R7),R8),R9))) -> 5
A10: ='Teammate Engagement Checklist'!C8 -> 2 | B10: ='Teammate Engagement Checklist'!E8 -> Capability 能力 | C10: ='Teammate Engagement Checklist'!F8 -> 5 | D10: ='Teammate Engagement Checklist'!Y8 -> Yes | F10: Sum | G10: =SUM(G5:G9) -> 4 | H10: =SUM(H5:H9) -> 2 | I10: =SUM(I5:I9) -> 0 | J10: =SUM(J5:J9) -> 0 | K10: =IF(COUNTIF($B5:$B200,K$3)=SUM(G10:J10),MIN(K5:K9),"Error") -> 2 | L10: Sum | M10: =SUM(M5:M9) -> 5 | N10: =SUM(N5:N9) -> 3 | O10: =SUM(O5:O9) -> 0 | P10: =SUM(P5:P9) -> 0 | Q10: =IF(COUNTIF($B5:$B200,Q$3)=SUM(M10:P10),MIN(Q5:Q9),"Error") -> 3 | R10: Sum | S10: =SUM(S5:S9) -> 6 | T10: =SUM(T5:T9) -> 0 | U10: =SUM(U5:U9) -> 0 | V10: =SUM(V5:V9) -> 0 | W10: =IF(COUNTIF($B5:$B200,W$3)=SUM(S10:V10),MIN(W5:W9),"Error") -> 5
A11: ='Teammate Engagement Checklist'!C9 -> 2 | B11: ='Teammate Engagement Checklist'!E9 -> Action 行動 | C11: ='Teammate Engagement Checklist'!F9 -> 6 | D11: ='Teammate Engagement Checklist'!Y9 -> Yes
A12: ='Teammate Engagement Checklist'!C10 -> 2 | B12: ='Teammate Engagement Checklist'!E10 -> Knowledge 知識 | C12: ='Teammate Engagement Checklist'!F10 -> 7 | D12: ='Teammate Engagement Checklist'!Y10 -> Yes
A13: ='Teammate Engagement Checklist'!C11 -> 2 | B13: ='Teammate Engagement Checklist'!E11 -> 0 | C13: ='Teammate Engagement Checklist'!F11 -> 0 | D13: ='Teammate Engagement Checklist'!Y11 -> 0
A14: ='Teammate Engagement Checklist'!C12 -> 3 | B14: ='Teammate Engagement Checklist'!E12 -> Capability 能力 | C14: ='Teammate Engagement Checklist'!F12 -> 8 | D14: ='Teammate Engagement Checklist'!Y12 -> Yes
A15: ='Teammate Engagement Checklist'!C13 -> 3 | B15: ='Teammate Engagement Checklist'!E13 -> Knowledge 知識 | C15: ='Teammate Engagement Checklist'!F13 -> 9 | D15: ='Teammate Engagement Checklist'!Y13 -> Yes
A16: ='Teammate Engagement Checklist'!C14 -> 3 | B16: ='Teammate Engagement Checklist'!E14 -> Action 行動 | C16: ='Teammate Engagement Checklist'!F14 -> 10 | D16: ='Teammate Engagement Checklist'!Y14 -> No
A17: ='Teammate Engagement Checklist'!C15 -> 3 | B17: ='Teammate Engagement Checklist'!E15 -> 0 | C17: ='Teammate Engagement Checklist'!F15 -> 0 | D17: ='Teammate Engagement Checklist'!Y15 -> 0
A18: ='Teammate Engagement Checklist'!C16 -> 4 | B18: ='Teammate Engagement Checklist'!E16 -> Knowledge 知識 | C18: ='Teammate Engagement Checklist'!F16 -> 11 | D18: ='Teammate Engagement Checklist'!Y16 -> Yes
A19: ='Teammate Engagement Checklist'!C17 -> 4 | B19: ='Teammate Engagement Checklist'!E17 -> Capability 能力 | C19: ='Teammate Engagement Checklist'!F17 -> 12 | D19: ='Teammate Engagement Checklist'!Y17 -> No
A20: ='Teammate Engagement Checklist'!C18 -> 4 | B20: ='Teammate Engagement Checklist'!E18 -> Capability 能力 | C20: ='Teammate Engagement Checklist'!F18 -> 13 | D20: ='Teammate Engagement Checklist'!Y18 -> Yes
A21: ='Teammate Engagement Checklist'!C19 -> 4 | B21: ='Teammate Engagement Checklist'!E19 -> Capability 能力 | C21: ='Teammate Engagement Checklist'!F19 -> 14 | D21: ='Teammate Engagement Checklist'!Y19 -> No
A22: ='Teammate Engagement Checklist'!C20 -> 4 | B22: ='Teammate Engagement Checklist'!E20 -> Action 行動 | C22: ='Teammate Engagement Checklist'!F20 -> 15 | D22: ='Teammate Engagement Checklist'!Y20 -> Yes
... A200: ='Teammate Engagement Checklist'!C198 -> 0 | B200: ='Teammate Engagement Checklist'!E198 -> 0 | C200: ='Teammate Engagement Checklist'!F198 -> 0 | D200: ='Teammate Engagement Checklist'!Y198 -> 0

Sheet 2nd Cal (Organization)
F2: Count
A3: Teammate | G3: Participation 参加 | H3: Participation 参加 | I3: Participation 参加 | J3: Participation 参加 | K3: Participation 参加 | M3: Information 情報 | N3: Information 情報 | O3: Information 情報 | P3: Information 情報 | Q3: Information 情報 | S3: Communication コミュニケーション | T3: Communication コミュニケーション | U3: Communication コミュニケーション | V3: Communication コミュニケーション | W3: Communication コミュニケーション
A4: Level | B4: Element | C4: No. | D4: Judgement | F4: Level | G4: Yes | H4: No | I4: N/A | J4: Not rolled out yet | K4: Judgement | L4: Level | M4: Yes | N4: No | O4: N/A | P4: Not rolled out yet | Q4: Judgement | R4: Level | S4: Yes | T4: No | U4: N/A | V4: Not rolled out yet | W4: Judgement
A5: ='Organization Checklist'!C3 -> 1 | B5: ='Organization Checklist'!E3 -> Information 情報 | C5: ='Organization Checklist'!F3 -> 1 | D5: ='Organization Checklist'!Y3 -> Yes | F5: 1 | G5: =COUNTIFS($A$5:$A$200,$F5,$B$5:$B$200,G$3,$D$5:$D$200,G$4) -> 1 | H5: =COUNTIFS($A$5:$A$200,$F5,$B$5:$B$200,H$3,$D$5:$D$200,H$4) -> 0 | I5: =COUNTIFS($A$5:$A$200,$F5,$B$5:$B$200,I$3,$D$5:$D$200,I$4) -> 0 | J5: =COUNTIFS($A$5:$A$200,$F5,$B$5:$B$200,J$3,$D$5:$D$200,J$4) -> 0 | K5: =IF(SUM(G5:J5)=0,"",IF(H5>0,F5,"")) | L5: 1 | M5: =COUNTIFS($A$5:$A$200,$F5,$B$5:$B$200,M$3,$D$5:$D$200,M$4) -> 1 | N5: =COUNTIFS($A$5:$A$200,$F5,$B$5:$B$200,N$3,$D$5:$D$200,N$4) -> 0 | O5: =COUNTIFS($A$5:$A$200,$F5,$B$5:$B$200,O$3,$D$5:$D$200,O$4) -> 0 | P5: =COUNTIFS($A$5:$A$200,$F5,$B$5:$B$200,P$3,$D$5:$D$200,P$4) -> 0 | Q5: =IF(SUM(M5:P5)=0,"",IF(N5>0,L5,"")) | R5: 1 | S5: =COUNTIFS($A$5:$A$200,$F5,$B$5:$B$200,S$3,$D$5:$D$200,S$4) -> 2 | T5: =COUNTIFS($A$5:$A$200,$F5,$B$5:$B$200,T$3,$D$5:$D$200,T$4) -> 0 | U5: =COUNTIFS($A$5:$A$200,$F5,$B$5:$B$200,U$3,$D$5:$D$200,U$4) -> 0 | V5: =COUNTIFS($A$5:$A$200,$F5,$B$5:$B$200,V$3,$D$5:$D$200,V$4) -> 0 | W5: =IF(SUM(S5:V5)=0,"",IF(T5>0,R5,""))
A6: ='Organization Checklist'!C4 -> 1 | B6: ='Organization Checklist'!E4 -> Communication コミュニケーション | C6: ='Organization Checklist'!F4 -> 2 | D6: ='Organization Checklist'!Y4 -> Yes | F6: 2 | G6: =COUNTIFS($A$5:$A$200,$F6,$B$5:$B$200,G$3,$D$5:$D$200,G$4) -> 2 | H6: =COUNTIFS($A$5:$A$200,$F6,$B$5:$B$200,H$3,$D$5:$D$200,H$4) -> 0 | I6: =COUNTIFS($A$5:$A$200,$F6,$B$5:$B$200,I$3,$D$5:$D$200,I$4) -> 0 | J6: =COUNTIFS($A$5:$A$200,$F6,$B$5:$B$200,J$3,$D$5:$D$200,J$4) -> 0 | K6: =IF(SUM(G6:J6)=0,"",IF(SUM(H5)>0,"",IF(H6>0,F6-1,IF(SUM(G7:J9)>0,"",F6)))) | L6: 2 | M6: =COUNTIFS($A$5:$A$200,$F6,$B$5:$B$200,M$3,$D$5:$D$200,M$4) -> 1 | N6: =COUNTIFS($A$5:$A$200,$F6,$B$5:$B$200,N$3,$D$5:$D$200,N$4) -> 0 | O6: =COUNTIFS($A$5:$A$200,$F6,$B$5:$B$200,O$3,$D$5:$D$200,O$4) -> 0 | P6: =COUNTIFS($A$5:$A$200,$F6,$B$5:$B$200,P$3,$D$5:$D$200,P$4) -> 0 | Q6: =IF(SUM(M6:P6)=0,"",IF(SUM(N5)>0,"",IF(N6>0,L6-1,IF(SUM(M7:P9)>0,"",L6)))) | R6: 2 | S6: =COUNTIFS($A$5:$A$200,$F6,$B$5:$B$200,S$3,$D$5:$D$200,S$4) -> 1 | T6: =COUNTIFS($A$5:$A$200,$F6,$B$5:$B$200,T$3,$D$5:$D$200,T$4) -> 0 | U6: =COUNTIFS($A$5:$A$200,$F6,$B$5:$B$200,U$3,$D$5:$D$200,U$4) -> 0 | V6: =COUNTIFS($A$5:$A$200,$F6,$B$5:$B$200,V$3,$D$5:$D$200,V$4) -> 0 | W6: =IF(SUM(S6:V6)=0,"",IF(SUM(T5)>0,"",IF(T6>0,R6-1,IF(SUM(S7:V9)>0,"",R6))))
A7: ='Organization Checklist'!C5 -> 1 | B7: ='Organization Checklist'!E5 -> Communication コミュニケーション | C7: ='Organization Checklist'!F5 -> 3 | D7: ='Organization Checklist'!Y5 -> Yes | F7: 3 | G7: =COUNTIFS($A$5:$A$200,$F7,$B$5:$B$200,G$3,$D$5:$D$200,G$4) -> 1 | H7: =COUNTIFS($A$5:$A$200,$F7,$B$5:$B$200,H$3,$D$5:$D$200,H$4) -> 0 | I7: =COUNTIFS($A$5:$A$200,$F7,$B$5:$B$200,I$3,$D$5:$D$200,I$4) -> 0 | J7: =COUNTIFS($A$5:$A$200,$F7,$B$5:$B$200,J$3,$D$5:$D$200,J$4) -> 0 | K7: =IF(SUM(G7:J7)=0,"",IF(SUM(H5:H6)>0,"",IF(H7>0,F7-1,IF(SUM(G8:J9)>0,"",F7)))) | L7: 3 | M7: =COUNTIFS($A$5:$A$200,$F7,$B$5:$B$200,M$3,$D$5:$D$200,M$4) -> 2 | N7: =COUNTIFS($A$5:$A$200,$F7,$B$5:$B$200,N$3,$D$5:$D$200,N$4) -> 0 | O7: =COUNTIFS($A$5:$A$200,$F7,$B$5:$B$200,O$3,$D$5:$D$200,O$4) -> 0 | P7: =COUNTIFS($A$5:$A$200,$F7,$B$5:$B$200,P$3,$D$5:$D$200,P$4) -> 0 | Q7: =IF(SUM(M7:P7)=0,"",IF(SUM(N5:N6)>0,"",IF(N7>0,L7-1,IF(SUM(M8:P9)>0,"",L7)))) | R7: 3 | S7: =COUNTIFS($A$5:$A$200,$F7,$B$5:$B$200,S$3,$D$5:$D$200,S$4) -> 1 | T7: =COUNTIFS($A$5:$A$200,$F7,$B$5:$B$200,T$3,$D$5:$D$200,T$4) -> 1 | U7: =COUNTIFS($A$5:$A$200,$F7,$B$5:$B$200,U$3,$D$5:$D$200,U$4) -> 0 | V7: =COUNTIFS($A$5:$A$200,$F7,$B$5:$B$200,V$3,$D$5:$D$200,V$4) -> 0 | W7: =IF(SUM(S7:V7)=0,"",IF(SUM(T5:T6)>0,"",IF(T7>0,R7-1,IF(SUM(S8:V9)>0,"",R7)))) -> 2
A8: ='Organization Checklist'!C6 -> 1 | B8: ='Organization Checklist'!E6 -> Participation 参加 | C8: ='Organization Checklist'!F6 -> 4 | D8: ='Organization Checklist'!Y6 -> Yes | F8: 4 | G8: =COUNTIFS($A$5:$A$200,$F8,$B$5:$B$200,G$3,$D$5:$D$200,G$4) -> 1 | H8: =COUNTIFS($A$5:$A$200,$F8,$B$5:$B$200,H$3,$D$5:$D$200,H$4) -> 0 | I8: =COUNTIFS($A$5:$A$200,$F8,$B$5:$B$200,I$3,$D$5:$D$200,I$4) -> 0 | J8: =COUNTIFS($A$5:$A$200,$F8,$B$5:$B$200,J$3,$D$5:$D$200,J$4) -> 0 | K8: =IF(SUM(G8:J8)=0,"",IF(SUM(H5:H7)>0,"",IF(H8>0,F8-1,IF(SUM(G9:J9)>0,"",F8)))) | L8: 4 | M8: =COUNTIFS($A$5:$A$200,$F8,$B$5:$B$200,M$3,$D$5:$D$200,M$4) -> 1 | N8: =COUNTIFS($A$5:$A$200,$F8,$B$5:$B$200,N$3,$D$5:$D$200,N$4) -> 0 | O8: =COUNTIFS($A$5:$A$200,$F8,$B$5:$B$200,O$3,$D$5:$D$200,O$4) -> 0 | P8: =COUNTIFS($A$5:$A$200,$F8,$B$5:$B$200,P$3,$D$5:$D$200,P$4) -> 0 | Q8: =IF(SUM(M8:P8)=0,"",IF(SUM(N5:N7)>0,"",IF(N8>0,L8-1,IF(SUM(M9:P9)>0,"",L8)))) | R8: 4 | S8: =COUNTIFS($A$5:$A$200,$F8,$B$5:$B$200,S$3,$D$5:$D$200,S$4) -> 1 | T8: =COUNTIFS($A$5:$A$200,$F8,$B$5:$B$200,T$3,$D$5:$D$200,T$4) -> 1 | U8: =COUNTIFS($A$5:$A$200,$F8,$B$5:$B$200,U$3,$D$5:$D$200,U$4) -> 0 | V8: =COUNTIFS($A$5:$A$200,$F8,$B$5:$B$200,V$3,$D$5:$D$200,V$4) -> 0 | W8: =IF(SUM(S8:V8)=0,"",IF(SUM(T5:T7)>0,"",IF(T8>0,R8-1,IF(SUM(S9:V9)>0,"",R8))))
A9: ='Organization Checklist'!C7 -> 1 | B9: ='Organization Checklist'!E7 -> 0 | C9: ='Organization Checklist'!F7 -> 0 | D9: ='Organization Checklist'!Y7 -> 0 | F9: 5 | G9: =COUNTIFS($A$5:$A$200,$F9,$B$5:$B$200,G$3,$D$5:$D$200,G$4) -> 0 | H9: =COUNTIFS($A$5:$A$200,$F9,$B$5:$B$200,H$3,$D$5:$D$200,H$4) -> 2 | I9: =COUNTIFS($A$5:$A$200,$F9,$B$5:$B$200,I$3,$D$5:$D$200,I$4) -> 0 | J9: =COUNTIFS($A$5:$A$200,$F9,$B$5:$B$200,J$3,$D$5:$D$200,J$4) -> 0 | K9: =IF(SUM(G9:J9)=0,"",IF(SUM(H5:H8)>0,"",IF(H9>0,IF(SUM(G8:J8)=0,IF(SUM(G7:J7)=0,IF(SUM(G6:J6)=0,IF(SUM(G5:J5)=0,F5),F6),F7),F8),F9))) -> 4 | L9: 5 | M9: =COUNTIFS($A$5:$A$200,$F9,$B$5:$B$200,M$3,$D$5:$D$200,M$4) -> 0 | N9: =COUNTIFS($A$5:$A$200,$F9,$B$5:$B$200,N$3,$D$5:$D$200,N$4) -> 1 | O9: =COUNTIFS($A$5:$A$200,$F9,$B$5:$B$200,O$3,$D$5:$D$200,O$4) -> 0 | P9: =COUNTIFS($A$5:$A$200,$F9,$B$5:$B$200,P$3,$D$5:$D$200,P$4) -> 0 | Q9: =IF(SUM(M9:P9)=0,"",IF(SUM(N5:N8)>0,"",IF(N9>0,IF(SUM(M8:P8)=0,IF(SUM(M7:P7)=0,IF(SUM(M6:P6)=0,IF(SUM(M5:P5)=0,L5),L6),L7),L8),L9))) -> 4 | R9: 5 | S9: =COUNTIFS($A$5:$A$200,$F9,$B$5:$B$200,S$3,$D$5:$D$200,S$4) -> 1 | T9: =COUNTIFS($A$5:$A$200,$F9,$B$5:$B$200,T$3,$D$5:$D$200,T$4) -> 0 | U9: =COUNTIFS($A$5:$A$200,$F9,$B$5:$B$200,U$3,$D$5:$D$200,U$4) -> 0 | V9: =COUNTIFS($A$5:$A$200,$F9,$B$5:$B$200,V$3,$D$5:$D$200,V$4) -> 0 | W9: =IF(SUM(S9:V9)=0,"",IF(SUM(T5:T8)>0,"",IF(T9>0,IF(SUM(S8:V8)=0,IF(SUM(S7:V7)=0,IF(SUM(S6:V6)=0,IF(SUM(S5:V5)=0,R5),R6),R7),R8),R9)))
A10: ='Organization Checklist'!C8 -> 2 | B10: ='Organization Checklist'!E8 -> Information 情報 | C10: ='Organization Checklist'!F8 -> 5 | D10: ='Organization Checklist'!Y8 -> Yes | F10: Sum | G10: =SUM(G5:G9) -> 5 | H10: =SUM(H5:H9) -> 2 | I10: =SUM(I5:I9) -> 0 | J10: =SUM(J5:J9) -> 0 | K10: =IF(COUNTIF($B5:$B200,K$3)=SUM(G10:J10),MIN(K5:K9),"Error") -> 4 | L10: Sum | M10: =SUM(M5:M9) -> 5 | N10: =SUM(N5:N9) -> 1 | O10: =SUM(O5:O9) -> 0 | P10: =SUM(P5:P9) -> 0 | Q10: =IF(COUNTIF($B5:$B200,Q$3)=SUM(M10:P10),MIN(Q5:Q9),"Error") -> 4 | R10: Sum | S10: =SUM(S5:S9) -> 6 | T10: =SUM(T5:T9) -> 2 | U10: =SUM(U5:U9) -> 0 | V10: =SUM(V5:V9) -> 0 | W10: =IF(COUNTIF($B5:$B200,W$3)=SUM(S10:V10),MIN(W5:W9),"Error") -> 2
A11: ='Organization Checklist'!C9 -> 2 | B11: ='Organization Checklist'!E9 -> Communication コミュニケーション | C11: ='Organization Checklist'!F9 -> 6 | D11: ='Organization Checklist'!Y9 -> Yes
A12: ='Organization Checklist'!C10 -> 2 | B12: ='Organization Checklist'!E10 -> Participation 参加 | C12: ='Organization Checklist'!F10 -> 7 | D12: ='Organization Checklist'!Y10 -> Yes
A13: ='Organization Checklist'!C11 -> 2 | B13: ='Organization Checklist'!E11 -> Participation 参加 | C13: ='Organization Checklist'!F11 -> 8 | D13: ='Organization Checklist'!Y11 -> Yes
A14: ='Organization Checklist'!C12 -> 2 | B14: ='Organization Checklist'!E12 -> 0 | C14: ='Organization Checklist'!F12 -> 0 | D14: ='Organization Checklist'!Y12 -> 0
A15: ='Organization Checklist'!C13 -> 3 | B15: ='Organization Checklist'!E13 -> Information 情報 | C15: ='Organization Checklist'!F13 -> 9 | D15: ='Organization Checklist'!Y13 -> Yes
A16: ='Organization Checklist'!C14 -> 3 | B16: ='Organization Checklist'!E14 -> Communication コミュニケーション | C16: ='Organization Checklist'!F14 -> 10 | D16: ='Organization Checklist'!Y14 -> Yes
A17: ='Organization Checklist'!C15 -> 3 | B17: ='Organization Checklist'!E15 -> Information 情報 | C17: ='Organization Checklist'!F15 -> 11 | D17: ='Organization Checklist'!Y15 -> Yes
A18: ='Organization Checklist'!C16 -> 3 | B18: ='Organization Checklist'!E16 -> Participation 参加 | C18: ='Organization Checklist'!F16 -> 12 | D18: ='Organization Checklist'!Y16 -> Yes
A19: ='Organization Checklist'!C17 -> 3 | B19: ='Organization Checklist'!E17 -> Communication コミュニケーション | C19: ='Organization Checklist'!F17 -> 13 | D19: ='Organization Checklist'!Y17 -> No
A20: ='Organization Checklist'!C18 -> 3 | B20: ='Organization Checklist'!E18 -> 0 | C20: ='Organization Checklist'!F18 -> 0 | D20: ='Organization Checklist'!Y18 -> 0
A21: ='Organization Checklist'!C19 -> 4 | B21: ='Organization Checklist'!E19 -> Communication コミュニケーション | C21: ='Organization Checklist'!F19 -> 14 | D21: ='Organization Checklist'!Y19 -> No
A22: ='Organization Checklist'!C20 -> 4 | B22: ='Organization Checklist'!E20 -> Information 情報 | C22: ='Organization Checklist'!F20 -> 15 | D22: ='Organization Checklist'!Y20 -> Yes
... A200: ='Organization Checklist'!C198 -> 0 | B200: ='Organization Checklist'!E198 -> 0 | C200: ='Organization Checklist'!F198 -> 0 | D200: ='Organization Checklist'!Y198 -> 0

Sheet 2nd Cal (System)
G2: Count | Z2: Count
A3: Teammate | H3: Design 設計 | I3: Design 設計 | J3: Design 設計 | K3: Design 設計 | L3: Design 設計 | N3: Integration 関連付け | O3: Integration 関連付け | P3: Integration 関連付け | Q3: Integration 関連付け | R3: Integration 関連付け | T3: Change & Emergency planning 変更管理 & 緊急事態準備 | U3: Change & Emergency planning 変更管理 & 緊急事態準備 | V3: Change & Emergency planning 変更管理 & 緊急事態準備 | W3: Change & Emergency planning 変更管理 & 緊急事態準備 | X3: Change & Emergency planning 変更管理 & 緊急事態準備 | AA3: Safety communication 安全コミュニケーション | AB3: Safety communication 安全コミュニケーション | AC3: Safety communication 安全コミュニケーション | AD3: Safety communication 安全コミュニケーション | AE3: Safety communication 安全コミュニケーション | AG3: Incident Management インシデント管理 | AH3: Incident Management インシデント管理 | AI3: Incident Management インシデント管理 | AJ3: Incident Management インシデント管理 | AK3: Incident Management インシデント管理 | AM3: Management of Change 変更管理 | AN3: Management of Change 変更管理 | AO3: Management of Change 変更管理 | AP3: Management of Change 変更管理 | AQ3: Management of Change 変更管理 | AS3: LOTO Standard LOTO標準 | AT3: LOTO Standard LOTO標準 | AU3: LOTO Standard LOTO標準 | AV3: LOTO Standard LOTO標準 | AW3: LOTO Standard LOTO標準 | AY3: Safety Rules 安全ルール | AZ3: Safety Rules 安全ルール | BA3: Safety Rules 安全ルール | BB3: Safety Rules 安全ルール | BC3: Safety Rules 安全ルール | BE3: Work at Height 高所作業 | BF3: Work at Height 高所作業 | BG3: Work at Height 高所作業 | BH3: Work at Height 高所作業 | BI3: Work at Height 高所作業 | BK3: Mobile Equipment 動力車 | BL3: Mobile Equipment 動力車 | BM3: Mobile Equipment 動力車 | BN3: Mobile Equipment 動力車 | BO3: Mobile Equipment 動力車 | BQ3: 3S | BR3: 3S | BS3: 3S | BT3: 3S | BU3: 3S | BW3: Crane and Hoist クレーン・ホイスト | BX3: Crane and Hoist クレーン・ホイスト | BY3: Crane and Hoist クレーン・ホイスト | BZ3: Crane and Hoist クレーン・ホイスト | CA3: Crane and Hoist クレーン・ホイスト | CC3: KY | CD3: KY | CE3: KY | CF3: KY | CG3: KY | CI3: Risk Assessment リスクアセスメント | CJ3: Risk Assessment リスクアセスメント | CK3: Risk Assessment リスクアセスメント | CL3: Risk Assessment リスクアセスメント | CM3: Risk Assessment リスクアセスメント | CO3: Contractor management 協力会社の安全管理 | CP3: Contractor management 協力会社の安全管理 | CQ3: Contractor management 協力会社の安全管理 | CR3: Contractor management 協力会社の安全管理 | CS3: Contractor management 協力会社の安全管理 | CU3: Large Tire Manual Handling Operation 大型タイヤハンドリング作業 | CV3: Large Tire Manual Handling Operation 大型タイヤハンドリング作業 | CW3: Large Tire Manual Handling Operation 大型タイヤハンドリング作業 | CX3: Large Tire Manual Handling Operation 大型タイヤハンドリング作業 | CY3: Large Tire Manual Handling Operation 大型タイヤハンドリング作業 | DA3: Ergonomics エルゴノミクス | DB3: Ergonomics エルゴノミクス | DC3: Ergonomics エルゴノミクス | DD3: Ergonomics エルゴノミクス | DE3: Ergonomics エルゴノミクス | DG3: Chemical Management 化学物質管理 | DH3: Chemical Management 化学物質管理 | DI3: Chemical Management 化学物質管理 | DJ3: Chemical Management 化学物質管理 | DK3: Chemical Management 化学物質管理 | DM3: General safety management for maintenance 一般保全安全管理 | DN3: General safety management for maintenance 一般保全安全管理 | DO3: General safety management for maintenance 一般保全安全管理 | DP3: General safety management for maintenance 一般保全安全管理 | DQ3: General safety management for maintenance 一般保全安全管理 | DS3: Fire Risk Assessment 火災RA | DT3: Fire Risk Assessment 火災RA | DU3: Fire Risk Assessment 火災RA | DV3: Fire Risk Assessment 火災RA | DW3: Fire Risk Assessment 火災RA | DY3: Flammable Materials Management 危険物管理 | DZ3: Flammable Materials Management 危険物管理 | EA3: Flammable Materials Management 危険物管理 | EB3: Flammable Materials Management 危険物管理 | EC3: Flammable Materials Management 危険物管理 | EE3: Hot Work Management 火気使用 | EF3: Hot Work Management 火気使用 | EG3: Hot Work Management 火気使用 | EH3: Hot Work Management 火気使用 | EI3: Hot Work Management 火気使用 | EK3: Fire Fighting 消火設備 | EL3: Fire Fighting 消火設備 | EM3: Fire Fighting 消火設備 | EN3: Fire Fighting 消火設備 | EO3: Fire Fighting 消火設備 | EQ3: Mixing MUST-11 精練MUST11 | ER3: Mixing MUST-11 精練MUST11 | ES3: Mixing MUST-11 精練MUST11 | ET3: Mixing MUST-11 精練MUST11 | EU3: Mixing MUST-11 精練MUST11 | EW3: Disaster Prevention General 一般事項 | EX3: Disaster Prevention General 一般事項 | EY3: Disaster Prevention General 一般事項 | EZ3: Disaster Prevention General 一般事項 | FA3: Disaster Prevention General 一般事項 | FC3: Electric system 電気配線 | FD3: Electric system 電気配線 | FE3: Electric system 電気配線 | FF3: Electric system 電気配線 | FG3: Electric system 電気配線
A4: Level | B4: Element1 | C4: Element2 | D4: No. | E4: Judgement | F4: Safety/DP | G4: Level | H4: Yes | I4: No | J4: N/A | K4: Not rolled out yet | L4: Judgement | M4: Level | N4: Yes | O4: No | P4: N/A | Q4: Not rolled out yet | R4: Judgement | S4: Level | T4: Yes | U4: No | V4: N/A | W4: Not rolled out yet | X4: Judgement | Z4: Level | AA4: Yes | AB4: No | AC4: N/A | AD4: Not rolled out yet | AE4: Judgement | AF4: Level | AG4: Yes | AH4: No | AI4: N/A | AJ4: Not rolled out yet | AK4: Judgement | AL4: Level | AM4: Yes | AN4: No | AO4: N/A | AP4: Not rolled out yet | AQ4: Judgement | AR4: Level | AS4: Yes | AT4: No | AU4: N/A | AV4: Not rolled out yet | AW4: Judgement | AX4: Level | AY4: Yes | AZ4: No | BA4: N/A | BB4: Not rolled out yet | BC4: Judgement | BD4: Level | BE4: Yes | BF4: No | BG4: N/A | BH4: Not rolled out yet | BI4: Judgement | BJ4: Level | BK4: Yes | BL4: No | BM4: N/A | BN4: Not rolled out yet | BO4: Judgement | BP4: Level | BQ4: Yes | BR4: No | BS4: N/A | BT4: Not rolled out yet | BU4: Judgement | BV4: Level | BW4: Yes | BX4: No | BY4: N/A | BZ4: Not rolled out yet | CA4: Judgement | CB4: Level | CC4: Yes | CD4: No | CE4: N/A | CF4: Not rolled out yet | CG4: Judgement | CH4: Level | CI4: Yes | CJ4: No | CK4: N/A | CL4: Not rolled out yet | CM4: Judgement | CN4: Level | CO4: Yes | CP4: No | CQ4: N/A | CR4: Not rolled out yet | CS4: Judgement | CT4: Level | CU4: Yes | CV4: No | CW4: N/A | CX4: Not rolled out yet | CY4: Judgement | CZ4: Level | DA4: Yes | DB4: No | DC4: N/A | DD4: Not rolled out yet | DE4: Judgement | DF4: Level | DG4: Yes | DH4: No | DI4: N/A | DJ4: Not rolled out yet | DK4: Judgement | DL4: Level | DM4: Yes | DN4: No | DO4: N/A | DP4: Not rolled out yet | DQ4: Judgement | DR4: Level | DS4: Yes | DT4: No | DU4: N/A | DV4: Not rolled out yet | DW4: Judgement | DX4: Level | DY4: Yes | DZ4: No | EA4: N/A | EB4: Not rolled out yet | EC4: Judgement | ED4: Level | EE4: Yes | EF4: No | EG4: N/A | EH4: Not rolled out yet | EI4: Judgement | EJ4: Level | EK4: Yes | EL4: No | EM4: N/A | EN4: Not rolled out yet | EO4: Judgement | EP4: Level | EQ4: Yes | ER4: No | ES4: N/A | ET4: Not rolled out yet | EU4: Judgement | EV4: Level | EW4: Yes | EX4: No | EY4: N/A | EZ4: Not rolled out yet | FA4: Judgement | FB4: Level | FC4: Yes | FD4: No | FE4: N/A | FF4: Not rolled out yet | FG4: Judgement
A5: ='System Checklist'!C3 -> 1 | B5: ='System Checklist'!E3 -> Safety communication 安全コミュニケーション | C5: ='System Checklist'!F3 -> Design 設計 | D5: ='System Checklist'!G3 -> 1 | E5: ='System Checklist'!Z3 -> Yes | F5: Safety | G5: 1 | H5: =COUNTIFS($A$5:$A$200,$G5,$C$5:$C$200,H$3,$E$5:$E$200,H$4) -> 6 | I5: =COUNTIFS($A$5:$A$200,$G5,$C$5:$C$200,I$3,$E$5:$E$200,I$4) -> 0 | J5: =COUNTIFS($A$5:$A$200,$G5,$C$5:$C$200,J$3,$E$5:$E$200,J$4) -> 0 | K5: =COUNTIFS($A$5:$A$200,$G5,$C$5:$C$200,K$3,$E$5:$E$200,K$4) -> 0 | L5: =IF(SUM(H5:K5)=0,"",IF(I5>0,G5,"")) | M5: 1 | N5: =COUNTIFS($A$5:$A$200,$G5,$C$5:$C$200,N$3,$E$5:$E$200,N$4) -> 26 | O5: =COUNTIFS($A$5:$A$200,$G5,$C$5:$C$200,O$3,$E$5:$E$200,O$4) -> 0 | P5: =COUNTIFS($A$5:$A$200,$G5,$C$5:$C$200,P$3,$E$5:$E$200,P$4) -> 2 | Q5: =COUNTIFS($A$5:$A$200,$G5,$C$5:$C$200,Q$3,$E$5:$E$200,Q$4) -> 0 | R5: =IF(SUM(N5:Q5)=0,"",IF(O5>0,M5,"")) | S5: 1 | T5: =COUNTIFS($A$5:$A$200,$G5,$C$5:$C$200,T$3,$E$5:$E$200,T$4) -> 2 | U5: =COUNTIFS($A$5:$A$200,$G5,$C$5:$C$200,U$3,$E$5:$E$200,U$4) -> 0 | V5: =COUNTIFS($A$5:$A$200,$G5,$C$5:$C$200,V$3,$E$5:$E$200,V$4) -> 0 | W5: =COUNTIFS($A$5:$A$200,$G5,$C$5:$C$200,W$3,$E$5:$E$200,W$4) -> 0 | X5: =IF(SUM(T5:W5)=0,"",IF(U5>0,S5,"")) | Z5: 1 | AA5: =COUNTIFS($A$5:$A$200,$G5,$B$5:$B$200,AA$3,$E$5:$E$200,AA$4) -> 2 | AB5: =COUNTIFS($A$5:$A$200,$G5,$B$5:$B$200,AB$3,$E$5:$E$200,AB$4) -> 0 | AC5: =COUNTIFS($A$5:$A$200,$G5,$B$5:$B$200,AC$3,$E$5:$E$200,AC$4) -> 0 | AD5: =COUNTIFS($A$5:$A$200,$G5,$B$5:$B$200,AD$3,$E$5:$E$200,AD$4) -> 0 | AE5: =IF(AB5>0,1,"") | AF5: 1 | AG5: =COUNTIFS($A$5:$A$200,$G5,$B$5:$B$200,AG$3,$E$5:$E$200,AG$4) -> 2 | AH5: =COUNTIFS($A$5:$A$200,$G5,$B$5:$B$200,AH$3,$E$5:$E$200,AH$4) -> 0 | AI5: =COUNTIFS($A$5:$A$200,$G5,$B$5:$B$200,AI$3,$E$5:$E$200,AI$4) -> 0 | AJ5: =COUNTIFS($A$5:$A$200,$G5,$B$5:$B$200,AJ$3,$E$5:$E$200,AJ$4) -> 0 | AK5: =IF(AH5>0,1,"") | AL5: 1 | AM5: =COUNTIFS($A$5:$A$200,$G5,$B$5:$B$200,AM$3,$E$5:$E$200,AM$4) -> 2 | AN5: =COUNTIFS($A$5:$A$200,$G5,$B$5:$B$200,AN$3,$E$5:$E$200,AN$4) -> 0 | AO5: =COUNTIFS($A$5:$A$200,$G5,$B$5:$B$200,AO$3,$E$5:$E$200,AO$4) -> 0 | AP5: =COUNTIFS($A$5:$A$200,$G5,$B$5:$B$200,AP$3,$E$5:$E$200,AP$4) -> 0 | AQ5: =IF(AN5>0,1,"") | AR5: 1 | AS5: =COUNTIFS($A$5:$A$200,$G5,$B$5:$B$200,AS$3,$E$5:$E$200,AS$4) -> 2 | AT5: =COUNTIFS($A$5:$A$200,$G5,$B$5:$B$200,AT$3,$E$5:$E$200,AT$4) -> 0 | AU5: =COUNTIFS($A$5:$A$200,$G5,$B$5:$B$200,AU$3,$E$5:$E$200,AU$4) -> 0 | AV5: =COUNTIFS($A$5:$A$200,$G5,$B$5:$B$200,AV$3,$E$5:$E$200,AV$4) -> 0 | AW5: =IF(AT5>0,1,"") | AX5: 1 | AY5: =COUNTIFS($A$5:$A$200,$G5,$B$5:$B$200,AY$3,$E$5:$E$200,AY$4) -> 1 | AZ5: =COUNTIFS($A$5:$A$200,$G5,$B$5:$B$200,AZ$3,$E$5:$E$200,AZ$4) -> 0 | BA5: =COUNTIFS($A$5:$A$200,$G5,$B$5:$B$200,BA$3,$E$5:$E$200,BA$4) -> 0 | BB5: =COUNTIFS($A$5:$A$200,$G5,$B$5:$B$200,BB$3,$E$5:$E$200,BB$4) -> 0 | BC5: =IF(AZ5>0,1,"") | BD5: 1 | BE5: =COUNTIFS($A$5:$A$200,$G5,$B$5:$B$200,BE$3,$E$5:$E$200,BE$4) -> 2 | BF5: =COUNTIFS($A$5:$A$200,$G5,$B$5:$B$200,BF$3,$E$5:$E$200,BF$4) -> 0 | BG5: =COUNTIFS($A$5:$A$200,$G5,$B$5:$B$200,BG$3,$E$5:$E$200,BG$4) -> 0 | BH5: =COUNTIFS($A$5:$A$200,$G5,$B$5:$B$200,BH$3,$E$5:$E$200,BH$4) -> 0 | BI5: =IF(BF5>0,1,"") | BJ5: 1 | BK5: =COUNTIFS($A$5:$A$200,$G5,$B$5:$B$200,BK$3,$E$5:$E$200,BK$4) -> 1 | BL5: =COUNTIFS($A$5:$A$200,$G5,$B$5:$B$200,BL$3,$E$5:$E$200,BL$4) -> 0 | BM5: =COUNTIFS($A$5:$A$200,$G5,$B$5:$B$200,BM$3,$E$5:$E$200,BM$4) -> 0 | BN5: =COUNTIFS($A$5:$A$200,$G5,$B$5:$B$200,BN$3,$E$5:$E$200,BN$4) -> 0 | BO5: =IF(BL5>0,1,"") | BP5: 1 | BQ5: =COUNTIFS($A$5:$A$200,$G5,$B$5:$B$200,BQ$3,$E$5:$E$200,BQ$4) -> 3 | BR5: =COUNTIFS($A$5:$A$200,$G5,$B$5:$B$200,BR$3,$E$5:$E$200,BR$4) -> 0 | BS5: =COUNTIFS($A$5:$A$200,$G5,$B$5:$B$200,BS$3,$E$5:$E$200,BS$4) -> 0 | BT5: =COUNTIFS($A$5:$A$200,$G5,$B$5:$B$200,BT$3,$E$5:$E$200,BT$4) -> 0 | BU5: =IF(BR5>0,1,"") | BV5: 1 | BW5: =COUNTIFS($A$5:$A$200,$G5,$B$5:$B$200,BW$3,$E$5:$E$200,BW$4) -> 3 | BX5: =COUNTIFS($A$5:$A$200,$G5,$B$5:$B$200,BX$3,$E$5:$E$200,BX$4) -> 0 | BY5: =COUNTIFS($A$5:$A$200,$G5,$B$5:$B$200,BY$3,$E$5:$E$200,BY$4) -> 0 | BZ5: =COUNTIFS($A$5:$A$200,$G5,$B$5:$B$200,BZ$3,$E$5:$E$200,BZ$4) -> 0 | CA5: =IF(BX5>0,1,"") | CB5: 1 | CC5: =COUNTIFS($A$5:$A$200,$G5,$B$5:$B$200,CC$3,$E$5:$E$200,CC$4) -> 1 | CD5: =COUNTIFS($A$5:$A$200,$G5,$B$5:$B$200,CD$3,$E$5:$E$200,CD$4) -> 0 | CE5: =COUNTIFS($A$5:$A$200,$G5,$B$5:$B$200,CE$3,$E$5:$E$200,CE$4) -> 0 | CF5: =COUNTIFS($A$5:$A$200,$G5,$B$5:$B$200,CF$3,$E$5:$E$200,CF$4) -> 0 | CG5: =IF(CD5>0,1,"") | CH5: 1 | CI5: =COUNTIFS($A$5:$A$200,$G5,$B$5:$B$200,CI$3,$E$5:$E$200,CI$4) -> 2 | CJ5: =COUNTIFS($A$5:$A$200,$G5,$B$5:$B$200,CJ$3,$E$5:$E$200,CJ$4) -> 0 | CK5: =COUNTIFS($A$5:$A$200,$G5,$B$5:$B$200,CK$3,$E$5:$E$200,CK$4) -> 0 | CL5: =COUNTIFS($A$5:$A$200,$G5,$B$5:$B$200,CL$3,$E$5:$E$200,CL$4) -> 0 | CM5: =IF(CJ5>0,1,"") | CN5: 1 | CO5: =COUNTIFS($A$5:$A$200,$G5,$B$5:$B$200,CO$3,$E$5:$E$200,CO$4) -> 1 | CP5: =COUNTIFS($A$5:$A$200,$G5,$B$5:$B$200,CP$3,$E$5:$E$200,CP$4) -> 0 | CQ5: =COUNTIFS($A$5:$A$200,$G5,$B$5:$B$200,CQ$3,$E$5:$E$200,CQ$4) -> 0 | CR5: =COUNTIFS($A$5:$A$200,$G5,$B$5:$B$200,CR$3,$E$5:$E$200,CR$4) -> 0 | CS5: =IF(CP5>0,1,"") | CT5: 1 | CU5: =COUNTIFS($A$5:$A$200,$G5,$B$5:$B$200,CU$3,$E$5:$E$200,CU$4) -> 0 | CV5: =COUNTIFS($A$5:$A$200,$G5,$B$5:$B$200,CV$3,$E$5:$E$200,CV$4) -> 0 | CW5: =COUNTIFS($A$5:$A$200,$G5,$B$5:$B$200,CW$3,$E$5:$E$200,CW$4) -> 2 | CX5: =COUNTIFS($A$5:$A$200,$G5,$B$5:$B$200,CX$3,$E$5:$E$200,CX$4) -> 0 | CY5: =IF(CV5>0,1,"") | CZ5: 1 | DA5: =COUNTIFS($A$5:$A$200,$G5,$B$5:$B$200,DA$3,$E$5:$E$200,DA$4) -> 1 | DB5: =COUNTIFS($A$5:$A$200,$G5,$B$5:$B$200,DB$3,$E$5:$E$200,DB$4) -> 0 | DC5: =COUNTIFS($A$5:$A$200,$G5,$B$5:$B$200,DC$3,$E$5:$E$200,DC$4) -> 0 | DD5: =COUNTIFS($A$5:$A$200,$G5,$B$5:$B$200,DD$3,$E$5:$E$200,DD$4) -> 0 | DE5: =IF(DB5>0,1,"") | DF5: 1 | DG5: =COUNTIFS($A$5:$A$200,$G5,$B$5:$B$200,DG$3,$E$5:$E$200,DG$4) -> 3 | DH5: =COUNTIFS($A$5:$A$200,$G5,$B$5:$B$200,DH$3,$E$5:$E$200,DH$4) -> 0 | DI5: =COUNTIFS($A$5:$A$200,$G5,$B$5:$B$200,DI$3,$E$5:$E$200,DI$4) -> 0 | DJ5: =COUNTIFS($A$5:$A$200,$G5,$B$5:$B$200,DJ$3,$E$5:$E$200,DJ$4) -> 0 | DK5: =IF(DH5>0,1,"") | DL5: 1 | DM5: =COUNTIFS($A$5:$A$200,$G5,$B$5:$B$200,DM$3,$E$5:$E$200,DM$4) -> 1 | DN5: =COUNTIFS($A$5:$A$200,$G5,$B$5:$B$200,DN$3,$E$5:$E$200,DN$4) -> 0 | DO5: =COUNTIFS($A$5:$A$200,$G5,$B$5:$B$200,DO$3,$E$5:$E$200,DO$4) -> 0 | DP5: =COUNTIFS($A$5:$A$200,$G5,$B$5:$B$200,DP$3,$E$5:$E$200,DP$4) -> 0 | DQ5: =IF(DN5>0,1,"") | DR5: 1 | DS5: =COUNTIFS($A$5:$A$200,$G5,$B$5:$B$200,DS$3,$E$5:$E$200,DS$4) -> 1 | DT5: =COUNTIFS($A$5:$A$200,$G5,$B$5:$B$200,DT$3,$E$5:$E$200,DT$4) -> 0 | DU5: =COUNTIFS($A$5:$A$200,$G5,$B$5:$B$200,DU$3,$E$5:$E$200,DU$4) -> 0 | DV5: =COUNTIFS($A$5:$A$200,$G5,$B$5:$B$200,DV$3,$E$5:$E$200,DV$4) -> 0 | DW5: =IF(DT5>0,1,"") | DX5: 1 | DY5: =COUNTIFS($A$5:$A$200,$G5,$B$5:$B$200,DY$3,$E$5:$E$200,DY$4) -> 1 | DZ5: =COUNTIFS($A$5:$A$200,$G5,$B$5:$B$200,DZ$3,$E$5:$E$200,DZ$4) -> 0 | EA5: =COUNTIFS($A$5:$A$200,$G5,$B$5:$B$200,EA$3,$E$5:$E$200,EA$4) -> 0 | EB5: =COUNTIFS($A$5:$A$200,$G5,$B$5:$B$200,EB$3,$E$5:$E$200,EB$4) -> 0 | EC5: =IF(DZ5>0,1,"") | ED5: 1 | EE5: =COUNTIFS($A$5:$A$200,$G5,$B$5:$B$200,EE$3,$E$5:$E$200,EE$4) -> 1 | EF5: =COUNTIFS($A$5:$A$200,$G5,$B$5:$B$200,EF$3,$E$5:$E$200,EF$4) -> 0 | EG5: =COUNTIFS($A$5:$A$200,$G5,$B$5:$B$200,EG$3,$E$5:$E$200,EG$4) -> 0 | EH5: =COUNTIFS($A$5:$A$200,$G5,$B$5:$B$200,EH$3,$E$5:$E$200,EH$4) -> 0 | EI5: =IF(EF5>0,1,"") | EJ5: 1 | EK5: =COUNTIFS($A$5:$A$200,$G5,$B$5:$B$200,EK$3,$E$5:$E$200,EK$4) -> 1 | EL5: =COUNTIFS($A$5:$A$200,$G5,$B$5:$B$200,EL$3,$E$5:$E$200,EL$4) -> 0 | EM5: =COUNTIFS($A$5:$A$200,$G5,$B$5:$B$200,EM$3,$E$5:$E$200,EM$4) -> 0 | EN5: =COUNTIFS($A$5:$A$200,$G5,$B$5:$B$200,EN$3,$E$5:$E$200,EN$4) -> 0 | EO5: =IF(EL5>0,1,"") | EP5: 1 | EQ5: =COUNTIFS($A$5:$A$200,$G5,$B$5:$B$200,EQ$3,$E$5:$E$200,EQ$4) -> 1 | ER5: =COUNTIFS($A$5:$A$200,$G5,$B$5:$B$200,ER$3,$E$5:$E$200,ER$4) -> 0 | ES5: =COUNTIFS($A$5:$A$200,$G5,$B$5:$B$200,ES$3,$E$5:$E$200,ES$4) -> 0 | ET5: =COUNTIFS($A$5:$A$200,$G5,$B$5:$B$200,ET$3,$E$5:$E$200,ET$4) -> 0 | EU5: =IF(ER5>0,1,"") | EV5: 1 | EW5: =COUNTIFS($A$5:$A$200,$G5,$B$5:$B$200,EW$3,$E$5:$E$200,EW$4) -> 1 | EX5: =COUNTIFS($A$5:$A$200,$G5,$B$5:$B$200,EX$3,$E$5:$E$200,EX$4) -> 0 | EY5: =COUNTIFS($A$5:$A$200,$G5,$B$5:$B$200,EY$3,$E$5:$E$200,EY$4) -> 0 | EZ5: =COUNTIFS($A$5:$A$200,$G5,$B$5:$B$200,EZ$3,$E$5:$E$200,EZ$4) -> 0 | FA5: =IF(EX5>0,1,"") | FB5: 1 | FC5: =COUNTIFS($A$5:$A$200,$G5,$B$5:$B$200,FC$3,$E$5:$E$200,FC$4) -> 1 | FD5: =COUNTIFS($A$5:$A$200,$G5,$B$5:$B$200,FD$3,$E$5:$E$200,FD$4) -> 0 | FE5: =COUNTIFS($A$5:$A$200,$G5,$B$5:$B$200,FE$3,$E$5:$E$200,FE$4) -> 0 | FF5: =COUNTIFS($A$5:$A$200,$G5,$B$5:$B$200,FF$3,$E$5:$E$200,FF$4) -> 0 | FG5: =IF(FD5>0,1,"")
